Workbook
Name Cash_Minimum: 'Cash flow forecast'!#REF!
Name Start_Date: 'Cash flow forecast'!#REF!

Sheet Assumptions
A1: *Note: all dates in the assumptions tab must start on the 1st
A2: Model Start Date | B2: 45809
A3: Select Sheet Quality Costs | B3: TC250
A4: Unit Inputs
A6: Products
B7: Price/Unit | C7: Cost/Unit | D7: $ Mark up | E7: Mark up%
A8: Twin Package:
A9: Twin Top Sheet | B9: =C9*(1+$E9) -> 7.71 | C9: =INDEX('Unit Costs'!$C$5:$C$42,MATCH(Assumptions!$A9,'Unit Costs'!$B$5:$B$42,0)) -> 5.14 | D9: =B9-C9 -> 2.57 | E9: 0.5
A10: Twin Bottom Sheet | B10: =C10*(1+$E10) -> 0 | C10: =INDEX('Unit Costs'!$C$5:$C$42,MATCH(Assumptions!$A10,'Unit Costs'!$B$5:$B$42,0)) -> 0 | D10: =B10-C10 -> 0 | E10: 0.5
A11: Twin Decorative Sheet | B11: =C11*(1+$E11) -> 9.225 | C11: =INDEX('Unit Costs'!$C$5:$C$42,MATCH(Assumptions!$A11,'Unit Costs'!$B$5:$B$42,0)) -> 6.15 | D11: =B11-C11 -> 3.075 | E11: 0.5
A12: Twin Fitted Sheet | B12: =C12*(1+$E12) -> 8.76 | C12: =INDEX('Unit Costs'!$C$5:$C$42,MATCH(Assumptions!$A12,'Unit Costs'!$B$5:$B$42,0)) -> 5.84 | D12: =B12-C12 -> 2.92 | E12: 0.5
A13: Std Pillow Case | B13: =C13*(1+$E13) -> 1.71 | C13: =INDEX('Unit Costs'!$C$5:$C$42,MATCH(Assumptions!$A13,'Unit Costs'!$B$5:$B$42,0)) -> 1.14 | D13: =B13-C13 -> 0.57 | E13: 0.5
A14: Total Twin | B14: =SUM(B9:B13) -> 27.405 | C14: =SUM(C9:C13) -> 18.27 | D14: =SUM(D9:D13) -> 9.135 | E14: =D14/C14 -> 0.5
A16: Full Package:
A17: Full Top Sheet | B17: =C17*(1+$E17) -> 6 | C17: =INDEX('Unit Costs'!$C$5:$C$42,MATCH(Assumptions!$A17,'Unit Costs'!$B$5:$B$42,0)) -> 4 | D17: =B17-C17 -> 2 | E17: 0.5
A18: Full Bottom Sheet | B18: =C18*(1+$E18) -> 0 | C18: =INDEX('Unit Costs'!$C$5:$C$42,MATCH(Assumptions!$A18,'Unit Costs'!$B$5:$B$42,0)) -> 0 | D18: =B18-C18 -> 0 | E18: 0.5
A19: Full Decorative Sheet | B19: =C19*(1+$E19) -> 10.5 | C19: =INDEX('Unit Costs'!$C$5:$C$42,MATCH(Assumptions!$A19,'Unit Costs'!$B$5:$B$42,0)) -> 7 | D19: =B19-C19 -> 3.5 | E19: 0.5
A20: Full Fitted Sheet | B20: =C20*(1+$E20) -> 4.5 | C20: =INDEX('Unit Costs'!$C$5:$C$42,MATCH(Assumptions!$A20,'Unit Costs'!$B$5:$B$42,0)) -> 3 | D20: =B20-C20 -> 1.5 | E20: 0.5
A21: Std Pillow Case | B21: =C21*(1+$E21) -> 1.71 | C21: =INDEX('Unit Costs'!$C$5:$C$42,MATCH(Assumptions!$A21,'Unit Costs'!$B$5:$B$42,0)) -> 1.14 | D21: =B21-C21 -> 0.57 | E21: 0.5
A22: Total Full | B22: =SUM(B17:B21) -> 22.71 | C22: =SUM(C17:C21) -> 15.14 | D22: =SUM(D17:D21) -> 7.57 | E22: =D22/C22 -> 0.5
A24: Queen Package:
A25: Queen Top (Flat) Sheet | B25: =C25*(1+$E25) -> 13.5 | C25: =INDEX('Unit Costs'!$C$5:$C$42,MATCH(Assumptions!$A25,'Unit Costs'!$B$5:$B$42,0)) -> 9 | D25: =B25-C25 -> 4.5 | E25: 0.5
A26: Queen Bottom (fitted 2.0) Sheet | B26: =C26*(1+$E26) -> 0 | C26: =INDEX('Unit Costs'!$C$5:$C$42,MATCH(Assumptions!$A26,'Unit Costs'!$B$5:$B$42,0)) -> 0 | D26: =B26-C26 -> 0 | E26: 0.5
A27: Queen Decorative Sheet | B27: =C27*(1+$E27) -> 10.5 | C27: =INDEX('Unit Costs'!$C$5:$C$42,MATCH(Assumptions!$A27,'Unit Costs'!$B$5:$B$42,0)) -> 7 | D27: =B27-C27 -> 3.5 | E27: 0.5
A28: Queen Fitted Sheet | B28: =C28*(1+$E28) -> 10.5 | C28: =INDEX('Unit Costs'!$C$5:$C$42,MATCH(Assumptions!$A28,'Unit Costs'!$B$5:$B$42,0)) -> 7 | D28: =B28-C28 -> 3.5 | E28: 0.5
A29: Queen Pillow Case | B29: =C29*(1+$E29) -> 4.5 | C29: =INDEX('Unit Costs'!$C$5:$C$42,MATCH(Assumptions!$A29,'Unit Costs'!$B$5:$B$42,0)) -> 3 | D29: =B29-C29 -> 1.5 | E29: 0.5
A30: Total Queen | B30: =SUM(B25:B29) -> 39 | C30: =SUM(C25:C29) -> 26 | D30: =SUM(D25:D29) -> 13 | E30: =D30/C30 -> 0.5
A32: King Package:
A33: King Top Sheet | B33: =C33*(1+$E33) -> 15 | C33: =INDEX('Unit Costs'!$C$5:$C$42,MATCH(Assumptions!$A33,'Unit Costs'!$B$5:$B$42,0)) -> 10 | D33: =B33-C33 -> 5 | E33: 0.5
A34: King Bottom Sheet | B34: =C34*(1+$E34) -> 0 | C34: =INDEX('Unit Costs'!$C$5:$C$42,MATCH(Assumptions!$A34,'Unit Costs'!$B$5:$B$42,0)) -> 0 | D34: =B34-C34 -> 0 | E34: 0.5
A35: King Decor Sheet | B35: =C35*(1+$E35) -> 10.5 | C35: =INDEX('Unit Costs'!$C$5:$C$42,MATCH(Assumptions!$A35,'Unit Costs'!$B$5:$B$42,0)) -> 7 | D35: =B35-C35 -> 3.5 | E35: 0.5
A36: King Fitted Sheet | B36: =C36*(1+$E36) -> 13.5 | C36: =INDEX('Unit Costs'!$C$5:$C$42,MATCH(Assumptions!$A36,'Unit Costs'!$B$5:$B$42,0)) -> 9 | D36: =B36-C36 -> 4.5 | E36: 0.5
A37: King Pillow Case | B37: =C37*(1+$E37) -> 12 | C37: =INDEX('Unit Costs'!$C$5:$C$42,MATCH(Assumptions!$A37,'Unit Costs'!$B$5:$B$42,0)) -> 8 | D37: =B37-C37 -> 4 | E37: 0.5
A38: Total King | B38: =SUM(B33:B37) -> 51 | C38: =SUM(C33:C37) -> 34 | D38: =SUM(D33:D37) -> 17 | E38: =D38/C38 -> 0.5
A40: Universal Package:
A41: Universal Top Sheet | B41: =C41*(1+$E41) -> 13.065 | C41: =INDEX('Unit Costs'!$C$5:$C$42,MATCH(Assumptions!$A41,'Unit Costs'!$B$5:$B$42,0)) -> 8.71 | D41: =B41-C41 -> 4.355 | E41: 0.5
A42: Universal Bottom Sheet | B42: =C42*(1+$E42) -> 0 | C42: =INDEX('Unit Costs'!$C$5:$C$42,MATCH(Assumptions!$A42,'Unit Costs'!$B$5:$B$42,0)) -> 0 | D42: =B42-C42 -> 0 | E42: 0.5
A43: Universal Decor Sheet | B43: =C43*(1+$E43) -> 0 | C43: =INDEX('Unit Costs'!$C$5:$C$42,MATCH(Assumptions!$A43,'Unit Costs'!$B$5:$B$42,0)) -> 0 | D43: =B43-C43 -> 0 | E43: 0.5
A44: Universal Fitted Sheet | B44: =C44*(1+$E44) -> 0 | C44: =INDEX('Unit Costs'!$C$5:$C$42,MATCH(Assumptions!$A44,'Unit Costs'!$B$5:$B$42,0)) -> 0 | D44: =B44-C44 -> 0 | E44: 0.5
A45: Universal Pillow Case | B45: =C45*(1+$E45) -> 0 | C45: =INDEX('Unit Costs'!$C$5:$C$42,MATCH(Assumptions!$A45,'Unit Costs'!$B$5:$B$42,0)) -> 0 | D45: =B45-C45 -> 0 | E45: 0.5
A46: Total Universal | B46: =SUM(B41:B45) -> 13.065 | C46: =SUM(C41:C45) -> 8.71 | D46: =SUM(D41:D45) -> 4.355 | E46: =D46/C46 -> 0.5
A48: Wholesale Inputs
A50: Small Hotels: | B50: YR 1 | C50: YR 2
A51: Starting Hotels | B51: 5 | C51: =B53 -> 7
A52: # of New Hotels/Yr | B52: 2 | C52: 5
A53: Total Hotels | B53: =SUM(B51:B52) -> 7 | C53: =SUM(C51:C52) -> 12
A54: Month of new hotels | B54: 2 | C54: 9
A56: Avg. Bedrooms | B56: =C65 -> 150
A57: Reorders/yr | B57: 1
A58: Reorder months | B58: 6
B59: Avg. Bed/bedroom | C59: Rooms by bed type | D59: # of PARS | E59: # of Orders
A60: Twin Package Orders | B60: 1 | C60: 25 | D60: 3 | E60: =C60*B60*D60 -> 75
A61: Full Package Orders | B61: 0 | C61: 0 | D61: 0 | E61: =C61*B61*D61 -> 0
A62: Queen Package Orders | B62: 2 | C62: 100 | D62: 3 | E62: =C62*B62*D62 -> 600
A63: King Package Orders | B63: 1 | C63: 25 | D63: 3 | E63: =C63*B63*D63 -> 75
A64: Universal Package Orders | B64: 0 | C64: 0 | D64: 0 | E64: =C64*B64*D64 -> 0
A65: Total | B65: =SUM(B60:B64) -> 4 | C65: =SUM(C60:C64) -> 150 | D65: =SUM(D60:D64) -> 9 | E65: =SUM(E60:E64) -> 750
A67: Churn Rate | B67: -0.1
A69: Medium Hotels: | B69: YR 1 | C69: YR 2
A70: Starting Hotels | B70: 1 | C70: =B72 -> 2
A71: # of New Hotels/Yr | B71: 1 | C71: 0
A72: Total Hotels | B72: =SUM(B70:B71) -> 2 | C72: =SUM(C70:C71) -> 2
A74: Avg. Bedrooms | B74: =C83 -> 150
A75: Reorders/yr | B75: 1
A76: Reorder months | B76: 4
B77: Avg. Bed/bedroom | C77: Rooms by bed type | D77: # of PARS | E77: # of Orders
A78: Twin Package Orders | B78: 1 | C78: 25 | D78: 3 | E78: =C78*B78*D78 -> 75
A79: Full Package Orders | B79: 1 | C79: 0 | D79: 0 | E79: =C79*B79*D79 -> 0
A80: Queen Package Orders | B80: 2 | C80: 100 | D80: 3 | E80: =C80*B80*D80 -> 600
A81: King Package Orders | B81: 1 | C81: 25 | D81: 3 | E81: =C81*B81*D81 -> 75
A82: Universal Package Orders | B82: 1 | C82: 0 | D82: 0 | E82: =C82*B82*D82 -> 0
A83: Total | B83: =SUM(B78:B82) -> 6 | C83: =SUM(C78:C82) -> 150 | D83: =SUM(D78:D82) -> 9 | E83: =SUM(E78:E82) -> 750
A85: Churn Rate | B85: -0.1
A87: Large Hotels: | B87: YR 1 | C87: YR 2
A88: Starting Hotels | B88: 1 | C88: =B90 -> 2
A89: # of New Hotels/Yr | B89: 1 | C89: 1
A90: Total Hotels | B90: =SUM(B88:B89) -> 2 | C90: =SUM(C88:C89) -> 3
A92: Avg. Bedrooms | B92: =C101 -> 150
A93: Reorders/yr | B93: 1
A94: Reorder months | B94: 6
B95: Avg. Bed/bedroom | C95: Rooms by bed type | D95: # of PARS | E95: # of Orders
A96: Twin Package Orders | B96: 1 | C96: 25 | D96: 3 | E96: =C96*B96*D96 -> 75
A97: Full Package Orders | B97: 1 | C97: 0 | D97: 0 | E97: =C97*B97*D97 -> 0
A98: Queen Package Orders | B98: 2 | C98: 100 | D98: 3 | E98: =C98*B98*D98 -> 600
A99: King Package Orders | B99: 1 | C99: 25 | D99: 3 | E99: =C99*B99*D99 -> 75
A100: Universal Package Orders | B100: 1 | C100: 0 | D100: 0 | E100: =C100*B100*D100 -> 0
A101: Total | B101: =SUM(B96:B100) -> 6 | C101: =SUM(C96:C100) -> 150 | D101: =SUM(D96:D100) -> 9 | E101: =SUM(E96:E100) -> 750
A103: Churn Rate | B103: -0.1
A105: Retail Inputs
A106: Start Date | B106: 45901
B107: Starting units sold | C107: Growth Rate/Yr | D107: Churn Rate/Yr | E107: Mark-Up
A108: Twin Package Orders | B108: 5 | C108: 0.1 | D108: -0.02 | E108: 0.8
A109: Full Package Orders | B109: 5 | C109: 0.05 | D109: -0.02 | E109: 0.8
A110: Queen Package Orders | B110: 5 | C110: 0.05 | D110: -0.02 | E110: 0.8
A111: King Package Orders | B111: 5 | C111: 0.05 | D111: -0.02 | E111: 0.8
A112: Universal Package Orders | B112: 5 | C112: 0.05 | D112: -0.02 | E112: 0.8
A117: Licensing Inputs
A118: Start Date | B118: 45809
A119: Exclusive:
A120: Initial Fee/Yr | B120: 10000
...

Sheet Cash flow forecast
B1: NeetSheets
B2: Cash Flow Forecast
C3: =YEAR(C5) -> 2025 | D3: =YEAR(D5) -> 2025 | E3: =YEAR(E5) -> 2025 | F3: =YEAR(F5) -> 2025 | G3: =YEAR(G5) -> 2025 | H3: =YEAR(H5) -> 2025 | I3: =YEAR(I5) -> 2025 | J3: =YEAR(J5) -> 2026 | ... Z3: =YEAR(Z5) -> 2027
C4: 1 | D4: =C4+1 -> 2 | E4: =D4+1 -> 3 | F4: =E4+1 -> 4 | G4: =F4+1 -> 5 | H4: =G4+1 -> 6 | I4: =H4+1 -> 7 | J4: =I4+1 -> 8 | K4: =J4+1 -> 9 | ... N4: =M4+1 -> 12 | O4: 1 | P4: =O4+1 -> 2 | Q4: =P4+1 -> 3 | R4: =Q4+1 -> 4 | S4: =R4+1 -> 5 | T4: =S4+1 -> 6 | U4: =T4+1 -> 7 | V4: =U4+1 -> 8 | W4: =V4+1 -> 9 | ... Z4: =Y4+1 -> 12
C5: =Assumptions!$B$2 -> 45809 | D5: =EDATE(C5,1) -> 45839 | E5: =EDATE(D5,1) -> 45870 | F5: =EDATE(E5,1) -> 45901 | G5: =EDATE(F5,1) -> 45931 | H5: =EDATE(G5,1) -> 45962 | I5: =EDATE(H5,1) -> 45992 | J5: =EDATE(I5,1) -> 46023 | K5: =EDATE(J5,1) -> 46054 | ... Z5: =EDATE(Y5,1) -> 46508 | AA5: =$C$6 -> Q2 | AB5: =IF(RIGHT(AA$5,1)="4","Q1","Q"&RIGHT(AA5,1)+1) -> Q3 | AC5: =IF(RIGHT(AB$5,1)="4","Q1","Q"&RIGHT(AB5,1)+1) -> Q4 | AD5: =IF(RIGHT(AC$5,1)="4","Q1","Q"&RIGHT(AC5,1)+1) -> Q1 | AE5: Trailing 12 Month | AF5: =$O$6 -> Q2 | AG5: =IF(RIGHT(AF$5,1)="4","Q1","Q"&RIGHT(AF5,1)+1) -> Q3 | AH5: =IF(RIGHT(AG$5,1)="4","Q1","Q"&RIGHT(AG5,1)+1) -> Q4 | AI5: =IF(RIGHT(AH$5,1)="4","Q1","Q"&RIGHT(AH5,1)+1) -> Q1 | AJ5: Trailing 12 Month
C6: =INDEX(Formatting!$B$2:$B$13,MATCH(MONTH('Cash flow forecast'!C$5),Formatting!$C$2:$C$13,0)) -> Q2 | D6: =INDEX(Formatting!$B$2:$B$13,MATCH(MONTH('Cash flow forecast'!D$5),Formatting!$C$2:$C$13,0)) -> Q3 | E6: =INDEX(Formatting!$B$2:$B$13,MATCH(MONTH('Cash flow forecast'!E$5),Formatting!$C$2:$C$13,0)) -> Q3 | F6: =INDEX(Formatting!$B$2:$B$13,MATCH(MONTH('Cash flow forecast'!F$5),Formatting!$C$2:$C$13,0)) -> Q3 | G6: =INDEX(Formatting!$B$2:$B$13,MATCH(MONTH('Cash flow forecast'!G$5),Formatting!$C$2:$C$13,0)) -> Q4 | H6: =INDEX(Formatting!$B$2:$B$13,MATCH(MONTH('Cash flow forecast'!H$5),Formatting!$C$2:$C$13,0)) -> Q4 | I6: =INDEX(Formatting!$B$2:$B$13,MATCH(MONTH('Cash flow forecast'!I$5),Formatting!$C$2:$C$13,0)) -> Q4 | J6: =INDEX(Formatting!$B$2:$B$13,MATCH(MONTH('Cash flow forecast'!J$5),Formatting!$C$2:$C$13,0)) -> Q1 | ... Z6: =INDEX(Formatting!$B$2:$B$13,MATCH(MONTH('Cash flow forecast'!Z$5),Formatting!$C$2:$C$13,0)) -> Q2 | AA6: =INDEX($C$3:$N$3,MATCH(AA$5,$C$6:$N$6,0)) -> 2025 | AB6: =INDEX($C$3:$N$3,MATCH(AB$5,$C$6:$N$6,0)) -> 2025 | AC6: =INDEX($C$3:$N$3,MATCH(AC$5,$C$6:$N$6,0)) -> 2025 | AD6: =INDEX($C$3:$N$3,MATCH(AD$5,$C$6:$N$6,0)) -> 2026 | AF6: =INDEX($O$3:$Z$3,MATCH(AF$5,$O$6:$Z$6,0)) -> 2026 | AG6: =INDEX($O$3:$Z$3,MATCH(AG$5,$O$6:$Z$6,0)) -> 2026 | AH6: =INDEX($O$3:$Z$3,MATCH(AH$5,$O$6:$Z$6,0)) -> 2026 | AI6: =INDEX($O$3:$Z$3,MATCH(AI$5,$O$6:$Z$6,0)) -> 2027
B7: Revenue
B8: Wholesale Revenue: | AK8: Annual % of Revenue
B9: Small Hotels
B10: # of New Hotels | C10: =SUMIFS(Formatting!$A$23:$A$27,Formatting!$E$23:$E$27,'Cash flow forecast'!C$5) -> 5 | D10: =SUMIFS(Formatting!$A$23:$A$27,Formatting!$E$23:$E$27,'Cash flow forecast'!D$5) -> 0 | E10: =SUMIFS(Formatting!$A$23:$A$27,Formatting!$E$23:$E$27,'Cash flow forecast'!E$5) -> 2 | F10: =SUMIFS(Formatting!$A$23:$A$27,Formatting!$E$23:$E$27,'Cash flow forecast'!F$5) -> 0 | G10: =SUMIFS(Formatting!$A$23:$A$27,Formatting!$E$23:$E$27,'Cash flow forecast'!G$5) -> 0 | H10: =SUMIFS(Formatting!$A$23:$A$27,Formatting!$E$23:$E$27,'Cash flow forecast'!H$5) -> 0 | I10: =SUMIFS(Formatting!$A$23:$A$27,Formatting!$E$23:$E$27,'Cash flow forecast'!I$5) -> 0 | J10: =SUMIFS(Formatting!$A$23:$A$27,Formatting!$E$23:$E$27,'Cash flow forecast'!J$5) -> 0 | ... Z10: =SUMIFS(Formatting!$A$23:$A$27,Formatting!$E$23:$E$27,'Cash flow forecast'!Z$5) -> 0
B11: # of Renew Orders | C11: =IFERROR(INDEX(Formatting!$F$24:$T$24,MATCH('Cash flow forecast'!C$5,Formatting!$F$23:$T$23,0)),0)+IFERROR(INDEX(Formatting!$F$26:$T$26,MATCH('Cash flow forecast'!C$5,Formatting!$F$25:$T$25,0)),0)+IFERROR(INDEX(Formatting!$F$28:$T$28,MATCH('Cash flow forecast'!C$5,Formatting!$F$27:$T$27,0)),0) -> 0 | D11: =IFERROR(INDEX(Formatting!$F$24:$T$24,MATCH('Cash flow forecast'!D$5,Formatting!$F$23:$T$23,0)),0)+IFERROR(INDEX(Formatting!$F$26:$T$26,MATCH('Cash flow forecast'!D$5,Formatting!$F$25:$T$25,0)),0)+IFERROR(INDEX(Formatting!$F$28:$T$28,MATCH('Cash flow forecast'!D$5,Formatting!$F$27:$T$27,0)),0) -> 0 | E11: =IFERROR(INDEX(Formatting!$F$24:$T$24,MATCH('Cash flow forecast'!E$5,Formatting!$F$23:$T$23,0)),0)+IFERROR(INDEX(Formatting!$F$26:$T$26,MATCH('Cash flow forecast'!E$5,Formatting!$F$25:$T$25,0)),0)+IFERROR(INDEX(Formatting!$F$28:$T$28,MATCH('Cash flow forecast'!E$5,Formatting!$F$27:$T$27,0)),0) -> 0 | F11: =IFERROR(INDEX(Formatting!$F$24:$T$24,MATCH('Cash flow forecast'!F$5,Formatting!$F$23:$T$23,0)),0)+IFERROR(INDEX(Formatting!$F$26:$T$26,MATCH('Cash flow forecast'!F$5,Formatting!$F$25:$T$25,0)),0)+IFERROR(INDEX(Formatting!$F$28:$T$28,MATCH('Cash flow forecast'!F$5,Formatting!$F$27:$T$27,0)),0) -> 0 | G11: =IFERROR(INDEX(Formatting!$F$24:$T$24,MATCH('Cash flow forecast'!G$5,Formatting!$F$23:$T$23,0)),0)+IFERROR(INDEX(Formatting!$F$26:$T$26,MATCH('Cash flow forecast'!G$5,Formatting!$F$25:$T$25,0)),0)+IFERROR(INDEX(Formatting!$F$28:$T$28,MATCH('Cash flow forecast'!G$5,Formatting!$F$27:$T$27,0)),0) -> 0 | H11: =IFERROR(INDEX(Formatting!$F$24:$T$24,MATCH('Cash flow forecast'!H$5,Formatting!$F$23:$T$23,0)),0)+IFERROR(INDEX(Formatting!$F$26:$T$26,MATCH('Cash flow forecast'!H$5,Formatting!$F$25:$T$25,0)),0)+IFERROR(INDEX(Formatting!$F$28:$T$28,MATCH('Cash flow forecast'!H$5,Formatting!$F$27:$T$27,0)),0) -> 0 | I11: =IFERROR(INDEX(Formatting!$F$24:$T$24,MATCH('Cash flow forecast'!I$5,Formatting!$F$23:$T$23,0)),0)+IFERROR(INDEX(Formatting!$F$26:$T$26,MATCH('Cash flow forecast'!I$5,Formatting!$F$25:$T$25,0)),0)+IFERROR(INDEX(Formatting!$F$28:$T$28,MATCH('Cash flow forecast'!I$5,Formatting!$F$27:$T$27,0)),0) -> 5 | J11: =IFERROR(INDEX(Formatting!$F$24:$T$24,MATCH('Cash flow forecast'!J$5,Formatting!$F$23:$T$23,0)),0)+IFERROR(INDEX(Formatting!$F$26:$T$26,MATCH('Cash flow forecast'!J$5,Formatting!$F$25:$T$25,0)),0)+IFERROR(INDEX(Formatting!$F$28:$T$28,MATCH('Cash flow forecast'!J$5,Formatting!$F$27:$T$27,0)),0) -> 0 | ... Z11: =IFERROR(INDEX(Formatting!$F$24:$T$24,MATCH('Cash flow forecast'!Z$5,Formatting!$F$23:$T$23,0)),0)+IFERROR(INDEX(Formatting!$F$26:$T$26,MATCH('Cash flow forecast'!Z$5,Formatting!$F$25:$T$25,0)),0)+IFERROR(INDEX(Formatting!$F$28:$T$28,MATCH('Cash flow forecast'!Z$5,Formatting!$F$27:$T$27,0)),0) -> 0
B12: Twin Package Orders | C12: =((INDEX(Assumptions!$B$8:$B$46,MATCH("Total Twin",Assumptions!$A$8:$A$46,0)))*((C$10+C$11)*INDEX(Assumptions!$E$60:$E$65,MATCH('Cash flow forecast'!$B12,Assumptions!$A$60:$A$65,0)))) -> 10276.875 | D12: =(((INDEX(Assumptions!$B$8:$B$46,MATCH("Total Twin",Assumptions!$A$8:$A$46,0)))*((D$10+D$11)*INDEX(Assumptions!$E$60:$E$65,MATCH('Cash flow forecast'!$B12,Assumptions!$A$60:$A$65,0)))))*(1+Assumptions!$B$67) -> 0 | E12: =(((INDEX(Assumptions!$B$8:$B$46,MATCH("Total Twin",Assumptions!$A$8:$A$46,0)))*((E$10+E$11)*INDEX(Assumptions!$E$60:$E$65,MATCH('Cash flow forecast'!$B12,Assumptions!$A$60:$A$65,0)))))*(1+Assumptions!$B$67) -> 3699.675 | F12: =(((INDEX(Assumptions!$B$8:$B$46,MATCH("Total Twin",Assumptions!$A$8:$A$46,0)))*((F$10+F$11)*INDEX(Assumptions!$E$60:$E$65,MATCH('Cash flow forecast'!$B12,Assumptions!$A$60:$A$65,0)))))*(1+Assumptions!$B$67) -> 0 | G12: =(((INDEX(Assumptions!$B$8:$B$46,MATCH("Total Twin",Assumptions!$A$8:$A$46,0)))*((G$10+G$11)*INDEX(Assumptions!$E$60:$E$65,MATCH('Cash flow forecast'!$B12,Assumptions!$A$60:$A$65,0)))))*(1+Assumptions!$B$67) -> 0 | H12: =(((INDEX(Assumptions!$B$8:$B$46,MATCH("Total Twin",Assumptions!$A$8:$A$46,0)))*((H$10+H$11)*INDEX(Assumptions!$E$60:$E$65,MATCH('Cash flow forecast'!$B12,Assumptions!$A$60:$A$65,0)))))*(1+Assumptions!$B$67) -> 0 | I12: =(((INDEX(Assumptions!$B$8:$B$46,MATCH("Total Twin",Assumptions!$A$8:$A$46,0)))*((I$10+I$11)*INDEX(Assumptions!$E$60:$E$65,MATCH('Cash flow forecast'!$B12,Assumptions!$A$60:$A$65,0)))))*(1+Assumptions!$B$67) -> 9249.1875 | J12: =(((INDEX(Assumptions!$B$8:$B$46,MATCH("Total Twin",Assumptions!$A$8:$A$46,0)))*((J$10+J$11)*INDEX(Assumptions!$E$60:$E$65,MATCH('Cash flow forecast'!$B12,Assumptions!$A$60:$A$65,0)))))*(1+Assumptions!$B$67) -> 0 | K12: =(((INDEX(Assumptions!$B$8:$B$46,MATCH("Total Twin",Assumptions!$A$8:$A$46,0)))*((K$10+K$11)*INDEX(Assumptions!$E$60:$E$65,MATCH('Cash flow forecast'!$B12,Assumptions!$A$60:$A$65,0)))))*(1+Assumptions!$B$67) -> 3699.675 | ... Z12: =(((INDEX(Assumptions!$B$8:$B$46,MATCH("Total Twin",Assumptions!$A$8:$A$46,0)))*((Z$10+Z$11)*INDEX(Assumptions!$E$60:$E$65,MATCH('Cash flow forecast'!$B12,Assumptions!$A$60:$A$65,0)))))*(1+Assumptions!$B$67) -> 0 | AA12: =SUMIFS($C12:$N12,$C$6:$N$6,AA$5) -> 10276.875 | AB12: =SUMIFS($C12:$N12,$C$6:$N$6,AB$5) -> 3699.675 | AC12: =SUMIFS($C12:$N12,$C$6:$N$6,AC$5) -> 9249.1875 | AD12: =SUMIFS($C12:$N12,$C$6:$N$6,AD$5) -> 3699.675 | AE12: =SUM($C12:$N12) -> 26925.412 | AF12: =SUMIFS($O12:$Z12,$O$6:$Z$6,AF$5) -> 9249.1875 | AG12: =SUMIFS($O12:$Z12,$O$6:$Z$6,AG$5) -> 3699.675 | AH12: =SUMIFS($O12:$Z12,$O$6:$Z$6,AH$5) -> 9249.1875 | AI12: =SUMIFS($O12:$Z12,$O$6:$Z$6,AI$5) -> 12948.862 | AJ12: =SUM($O12:$Z12) -> 35146.912 | AK12: =AVERAGE(AE12,AJ12)/AVERAGE($AE$58,$AJ$58) -> 0.044935212
B13: Full Package Orders | C13: =((INDEX(Assumptions!$B$8:$B$46,MATCH("Total Full",Assumptions!$A$8:$A$46,0)))*((C$10+C$11)*INDEX(Assumptions!$E$60:$E$65,MATCH('Cash flow forecast'!$B13,Assumptions!$A$60:$A$65,0)))) -> 0 | D13: =(((INDEX(Assumptions!$B$8:$B$46,MATCH("Total Full",Assumptions!$A$8:$A$46,0)))*((D$10+D$11)*INDEX(Assumptions!$E$60:$E$65,MATCH('Cash flow forecast'!$B13,Assumptions!$A$60:$A$65,0)))))*(1+Assumptions!$B$67) -> 0 | E13: =(((INDEX(Assumptions!$B$8:$B$46,MATCH("Total Full",Assumptions!$A$8:$A$46,0)))*((E$10+E$11)*INDEX(Assumptions!$E$60:$E$65,MATCH('Cash flow forecast'!$B13,Assumptions!$A$60:$A$65,0)))))*(1+Assumptions!$B$67) -> 0 | F13: =(((INDEX(Assumptions!$B$8:$B$46,MATCH("Total Full",Assumptions!$A$8:$A$46,0)))*((F$10+F$11)*INDEX(Assumptions!$E$60:$E$65,MATCH('Cash flow forecast'!$B13,Assumptions!$A$60:$A$65,0)))))*(1+Assumptions!$B$67) -> 0 | G13: =(((INDEX(Assumptions!$B$8:$B$46,MATCH("Total Full",Assumptions!$A$8:$A$46,0)))*((G$10+G$11)*INDEX(Assumptions!$E$60:$E$65,MATCH('Cash flow forecast'!$B13,Assumptions!$A$60:$A$65,0)))))*(1+Assumptions!$B$67) -> 0 | H13: =(((INDEX(Assumptions!$B$8:$B$46,MATCH("Total Full",Assumptions!$A$8:$A$46,0)))*((H$10+H$11)*INDEX(Assumptions!$E$60:$E$65,MATCH('Cash flow forecast'!$B13,Assumptions!$A$60:$A$65,0)))))*(1+Assumptions!$B$67) -> 0 | I13: =(((INDEX(Assumptions!$B$8:$B$46,MATCH("Total Full",Assumptions!$A$8:$A$46,0)))*((I$10+I$11)*INDEX(Assumptions!$E$60:$E$65,MATCH('Cash flow forecast'!$B13,Assumptions!$A$60:$A$65,0)))))*(1+Assumptions!$B$67) -> 0 | J13: =(((INDEX(Assumptions!$B$8:$B$46,MATCH("Total Full",Assumptions!$A$8:$A$46,0)))*((J$10+J$11)*INDEX(Assumptions!$E$60:$E$65,MATCH('Cash flow forecast'!$B13,Assumptions!$A$60:$A$65,0)))))*(1+Assumptions!$B$67) -> 0 | K13: =(((INDEX(Assumptions!$B$8:$B$46,MATCH("Total Full",Assumptions!$A$8:$A$46,0)))*((K$10+K$11)*INDEX(Assumptions!$E$60:$E$65,MATCH('Cash flow forecast'!$B13,Assumptions!$A$60:$A$65,0)))))*(1+Assumptions!$B$67) -> 0 | ... Z13: =(((INDEX(Assumptions!$B$8:$B$46,MATCH("Total Full",Assumptions!$A$8:$A$46,0)))*((Z$10+Z$11)*INDEX(Assumptions!$E$60:$E$65,MATCH('Cash flow forecast'!$B13,Assumptions!$A$60:$A$65,0)))))*(1+Assumptions!$B$67) -> 0 | AA13: =SUMIFS($C13:$N13,$C$6:$N$6,AA$5) -> 0 | AB13: =SUMIFS($C13:$N13,$C$6:$N$6,AB$5) -> 0 | AC13: =SUMIFS($C13:$N13,$C$6:$N$6,AC$5) -> 0 | AD13: =SUMIFS($C13:$N13,$C$6:$N$6,AD$5) -> 0 | AE13: =SUM($C13:$N13) -> 0 | AF13: =SUMIFS($O13:$Z13,$O$6:$Z$6,AF$5) -> 0 | AG13: =SUMIFS($O13:$Z13,$O$6:$Z$6,AG$5) -> 0 | AH13: =SUMIFS($O13:$Z13,$O$6:$Z$6,AH$5) -> 0 | AI13: =SUMIFS($O13:$Z13,$O$6:$Z$6,AI$5) -> 0 | AJ13: =SUM($O13:$Z13) -> 0 | AK13: =AVERAGE(AE13,AJ13)/AVERAGE($AE$58,$AJ$58) -> 0
B14: Queen Package Orders | C14: =((INDEX(Assumptions!$B$8:$B$46,MATCH("Total Queen",Assumptions!$A$8:$A$46,0)))*((C$10+C$11)*INDEX(Assumptions!$E$60:$E$65,MATCH('Cash flow forecast'!$B14,Assumptions!$A$60:$A$65,0)))) -> 117000 | D14: =(((INDEX(Assumptions!$B$8:$B$46,MATCH("Total Queen",Assumptions!$A$8:$A$46,0)))*((D$10+D$11)*INDEX(Assumptions!$E$60:$E$65,MATCH('Cash flow forecast'!$B14,Assumptions!$A$60:$A$65,0)))))*(1+Assumptions!$B$67) -> 0 | E14: =(((INDEX(Assumptions!$B$8:$B$46,MATCH("Total Queen",Assumptions!$A$8:$A$46,0)))*((E$10+E$11)*INDEX(Assumptions!$E$60:$E$65,MATCH('Cash flow forecast'!$B14,Assumptions!$A$60:$A$65,0)))))*(1+Assumptions!$B$67) -> 42120 | F14: =(((INDEX(Assumptions!$B$8:$B$46,MATCH("Total Queen",Assumptions!$A$8:$A$46,0)))*((F$10+F$11)*INDEX(Assumptions!$E$60:$E$65,MATCH('Cash flow forecast'!$B14,Assumptions!$A$60:$A$65,0)))))*(1+Assumptions!$B$67) -> 0 | G14: =(((INDEX(Assumptions!$B$8:$B$46,MATCH("Total Queen",Assumptions!$A$8:$A$46,0)))*((G$10+G$11)*INDEX(Assumptions!$E$60:$E$65,MATCH('Cash flow forecast'!$B14,Assumptions!$A$60:$A$65,0)))))*(1+Assumptions!$B$67) -> 0 | H14: =(((INDEX(Assumptions!$B$8:$B$46,MATCH("Total Queen",Assumptions!$A$8:$A$46,0)))*((H$10+H$11)*INDEX(Assumptions!$E$60:$E$65,MATCH('Cash flow forecast'!$B14,Assumptions!$A$60:$A$65,0)))))*(1+Assumptions!$B$67) -> 0 | I14: =(((INDEX(Assumptions!$B$8:$B$46,MATCH("Total Queen",Assumptions!$A$8:$A$46,0)))*((I$10+I$11)*INDEX(Assumptions!$E$60:$E$65,MATCH('Cash flow forecast'!$B14,Assumptions!$A$60:$A$65,0)))))*(1+Assumptions!$B$67) -> 105300 | J14: =(((INDEX(Assumptions!$B$8:$B$46,MATCH("Total Queen",Assumptions!$A$8:$A$46,0)))*((J$10+J$11)*INDEX(Assumptions!$E$60:$E$65,MATCH('Cash flow forecast'!$B14,Assumptions!$A$60:$A$65,0)))))*(1+Assumptions!$B$67) -> 0 | K14: =(((INDEX(Assumptions!$B$8:$B$46,MATCH("Total Queen",Assumptions!$A$8:$A$46,0)))*((K$10+K$11)*INDEX(Assumptions!$E$60:$E$65,MATCH('Cash flow forecast'!$B14,Assumptions!$A$60:$A$65,0)))))*(1+Assumptions!$B$67) -> 42120 | ... Z14: =(((INDEX(Assumptions!$B$8:$B$46,MATCH("Total Queen",Assumptions!$A$8:$A$46,0)))*((Z$10+Z$11)*INDEX(Assumptions!$E$60:$E$65,MATCH('Cash flow forecast'!$B14,Assumptions!$A$60:$A$65,0)))))*(1+Assumptions!$B$67) -> 0 | AA14: =SUMIFS($C14:$N14,$C$6:$N$6,AA$5) -> 117000 | AB14: =SUMIFS($C14:$N14,$C$6:$N$6,AB$5) -> 42120 | AC14: =SUMIFS($C14:$N14,$C$6:$N$6,AC$5) -> 105300 | AD14: =SUMIFS($C14:$N14,$C$6:$N$6,AD$5) -> 42120 | AE14: =SUM($C14:$N14) -> 306540 | AF14: =SUMIFS($O14:$Z14,$O$6:$Z$6,AF$5) -> 105300 | AG14: =SUMIFS($O14:$Z14,$O$6:$Z$6,AG$5) -> 42120 | AH14: =SUMIFS($O14:$Z14,$O$6:$Z$6,AH$5) -> 105300 | AI14: =SUMIFS($O14:$Z14,$O$6:$Z$6,AI$5) -> 147420 | AJ14: =SUM($O14:$Z14) -> 400140 | AK14: =AVERAGE(AE14,AJ14)/AVERAGE($AE$58,$AJ$58) -> 0.51157767
B15: King Package Orders | C15: =((INDEX(Assumptions!$B$8:$B$46,MATCH("Total King",Assumptions!$A$8:$A$46,0)))*((C$10+C$11)*INDEX(Assumptions!$E$60:$E$65,MATCH('Cash flow forecast'!$B15,Assumptions!$A$60:$A$65,0)))) -> 19125 | D15: =(((INDEX(Assumptions!$B$8:$B$46,MATCH("Total King",Assumptions!$A$8:$A$46,0)))*((D$10+D$11)*INDEX(Assumptions!$E$60:$E$65,MATCH('Cash flow forecast'!$B15,Assumptions!$A$60:$A$65,0)))))*(1+Assumptions!$B$67) -> 0 | E15: =(((INDEX(Assumptions!$B$8:$B$46,MATCH("Total King",Assumptions!$A$8:$A$46,0)))*((E$10+E$11)*INDEX(Assumptions!$E$60:$E$65,MATCH('Cash flow forecast'!$B15,Assumptions!$A$60:$A$65,0)))))*(1+Assumptions!$B$67) -> 6885 | F15: =(((INDEX(Assumptions!$B$8:$B$46,MATCH("Total King",Assumptions!$A$8:$A$46,0)))*((F$10+F$11)*INDEX(Assumptions!$E$60:$E$65,MATCH('Cash flow forecast'!$B15,Assumptions!$A$60:$A$65,0)))))*(1+Assumptions!$B$67) -> 0 | G15: =(((INDEX(Assumptions!$B$8:$B$46,MATCH("Total King",Assumptions!$A$8:$A$46,0)))*((G$10+G$11)*INDEX(Assumptions!$E$60:$E$65,MATCH('Cash flow forecast'!$B15,Assumptions!$A$60:$A$65,0)))))*(1+Assumptions!$B$67) -> 0 | H15: =(((INDEX(Assumptions!$B$8:$B$46,MATCH("Total King",Assumptions!$A$8:$A$46,0)))*((H$10+H$11)*INDEX(Assumptions!$E$60:$E$65,MATCH('Cash flow forecast'!$B15,Assumptions!$A$60:$A$65,0)))))*(1+Assumptions!$B$67) -> 0 | I15: =(((INDEX(Assumptions!$B$8:$B$46,MATCH("Total King",Assumptions!$A$8:$A$46,0)))*((I$10+I$11)*INDEX(Assumptions!$E$60:$E$65,MATCH('Cash flow forecast'!$B15,Assumptions!$A$60:$A$65,0)))))*(1+Assumptions!$B$67) -> 17212.5 | J15: =(((INDEX(Assumptions!$B$8:$B$46,MATCH("Total King",Assumptions!$A$8:$A$46,0)))*((J$10+J$11)*INDEX(Assumptions!$E$60:$E$65,MATCH('Cash flow forecast'!$B15,Assumptions!$A$60:$A$65,0)))))*(1+Assumptions!$B$67) -> 0 | K15: =(((INDEX(Assumptions!$B$8:$B$46,MATCH("Total King",Assumptions!$A$8:$A$46,0)))*((K$10+K$11)*INDEX(Assumptions!$E$60:$E$65,MATCH('Cash flow forecast'!$B15,Assumptions!$A$60:$A$65,0)))))*(1+Assumptions!$B$67) -> 6885 | ... Z15: =(((INDEX(Assumptions!$B$8:$B$46,MATCH("Total King",Assumptions!$A$8:$A$46,0)))*((Z$10+Z$11)*INDEX(Assumptions!$E$60:$E$65,MATCH('Cash flow forecast'!$B15,Assumptions!$A$60:$A$65,0)))))*(1+Assumptions!$B$67) -> 0 | AA15: =SUMIFS($C15:$N15,$C$6:$N$6,AA$5) -> 19125 | AB15: =SUMIFS($C15:$N15,$C$6:$N$6,AB$5) -> 6885 | AC15: =SUMIFS($C15:$N15,$C$6:$N$6,AC$5) -> 17212.5 | AD15: =SUMIFS($C15:$N15,$C$6:$N$6,AD$5) -> 6885 | AE15: =SUM($C15:$N15) -> 50107.5 | AF15: =SUMIFS($O15:$Z15,$O$6:$Z$6,AF$5) -> 17212.5 | AG15: =SUMIFS($O15:$Z15,$O$6:$Z$6,AG$5) -> 6885 | AH15: =SUMIFS($O15:$Z15,$O$6:$Z$6,AH$5) -> 17212.5 | AI15: =SUMIFS($O15:$Z15,$O$6:$Z$6,AI$5) -> 24097.5 | AJ15: =SUM($O15:$Z15) -> 65407.5 | AK15: =AVERAGE(AE15,AJ15)/AVERAGE($AE$58,$AJ$58) -> 0.083623273
B16: Universal Package Orders | C16: =((INDEX(Assumptions!$B$8:$B$46,MATCH("Total Universal",Assumptions!$A$8:$A$46,0)))*((C$10+C$11)*INDEX(Assumptions!$E$60:$E$65,MATCH('Cash flow forecast'!$B16,Assumptions!$A$60:$A$65,0)))) -> 0 | D16: =(((INDEX(Assumptions!$B$8:$B$46,MATCH("Total Universal",Assumptions!$A$8:$A$46,0)))*((D$10+D$11)*INDEX(Assumptions!$E$60:$E$65,MATCH('Cash flow forecast'!$B16,Assumptions!$A$60:$A$65,0)))))*(1+Assumptions!$B$67) -> 0 | E16: =(((INDEX(Assumptions!$B$8:$B$46,MATCH("Total Universal",Assumptions!$A$8:$A$46,0)))*((E$10+E$11)*INDEX(Assumptions!$E$60:$E$65,MATCH('Cash flow forecast'!$B16,Assumptions!$A$60:$A$65,0)))))*(1+Assumptions!$B$67) -> 0 | F16: =(((INDEX(Assumptions!$B$8:$B$46,MATCH("Total Universal",Assumptions!$A$8:$A$46,0)))*((F$10+F$11)*INDEX(Assumptions!$E$60:$E$65,MATCH('Cash flow forecast'!$B16,Assumptions!$A$60:$A$65,0)))))*(1+Assumptions!$B$67) -> 0 | G16: =(((INDEX(Assumptions!$B$8:$B$46,MATCH("Total Universal",Assumptions!$A$8:$A$46,0)))*((G$10+G$11)*INDEX(Assumptions!$E$60:$E$65,MATCH('Cash flow forecast'!$B16,Assumptions!$A$60:$A$65,0)))))*(1+Assumptions!$B$67) -> 0 | H16: =(((INDEX(Assumptions!$B$8:$B$46,MATCH("Total Universal",Assumptions!$A$8:$A$46,0)))*((H$10+H$11)*INDEX(Assumptions!$E$60:$E$65,MATCH('Cash flow forecast'!$B16,Assumptions!$A$60:$A$65,0)))))*(1+Assumptions!$B$67) -> 0 | I16: =(((INDEX(Assumptions!$B$8:$B$46,MATCH("Total Universal",Assumptions!$A$8:$A$46,0)))*((I$10+I$11)*INDEX(Assumptions!$E$60:$E$65,MATCH('Cash flow forecast'!$B16,Assumptions!$A$60:$A$65,0)))))*(1+Assumptions!$B$67) -> 0 | J16: =(((INDEX(Assumptions!$B$8:$B$46,MATCH("Total Universal",Assumptions!$A$8:$A$46,0)))*((J$10+J$11)*INDEX(Assumptions!$E$60:$E$65,MATCH('Cash flow forecast'!$B16,Assumptions!$A$60:$A$65,0)))))*(1+Assumptions!$B$67) -> 0 | K16: =(((INDEX(Assumptions!$B$8:$B$46,MATCH("Total Universal",Assumptions!$A$8:$A$46,0)))*((K$10+K$11)*INDEX(Assumptions!$E$60:$E$65,MATCH('Cash flow forecast'!$B16,Assumptions!$A$60:$A$65,0)))))*(1+Assumptions!$B$67) -> 0 | ... Z16: =(((INDEX(Assumptions!$B$8:$B$46,MATCH("Total Universal",Assumptions!$A$8:$A$46,0)))*((Z$10+Z$11)*INDEX(Assumptions!$E$60:$E$65,MATCH('Cash flow forecast'!$B16,Assumptions!$A$60:$A$65,0)))))*(1+Assumptions!$B$67) -> 0 | AA16: =SUMIFS($C16:$N16,$C$6:$N$6,AA$5) -> 0 | AB16: =SUMIFS($C16:$N16,$C$6:$N$6,AB$5) -> 0 | AC16: =SUMIFS($C16:$N16,$C$6:$N$6,AC$5) -> 0 | AD16: =SUMIFS($C16:$N16,$C$6:$N$6,AD$5) -> 0 | AE16: =SUM($C16:$N16) -> 0 | AF16: =SUMIFS($O16:$Z16,$O$6:$Z$6,AF$5) -> 0 | AG16: =SUMIFS($O16:$Z16,$O$6:$Z$6,AG$5) -> 0 | AH16: =SUMIFS($O16:$Z16,$O$6:$Z$6,AH$5) -> 0 | AI16: =SUMIFS($O16:$Z16,$O$6:$Z$6,AI$5) -> 0 | AJ16: =SUM($O16:$Z16) -> 0 | AK16: =AVERAGE(AE16,AJ16)/AVERAGE($AE$58,$AJ$58) -> 0
B17: Total | C17: =SUM(C12:C16) -> 146401.88 | D17: =SUM(D12:D16) -> 0 | E17: =SUM(E12:E16) -> 52704.675 | F17: =SUM(F12:F16) -> 0 | G17: =SUM(G12:G16) -> 0 | H17: =SUM(H12:H16) -> 0 | I17: =SUM(I12:I16) -> 131761.69 | J17: =SUM(J12:J16) -> 0 | ... AJ17: =SUM(AJ12:AJ16) -> 500694.41 | AK17: =AVERAGE(AE17,AJ17)/AVERAGE($AE$58,$AJ$58) -> 0.64013616
B18: Medium Hotels
B19: # of New Hotels | C19: =SUMIFS(Formatting!$A$33:$A$37,Formatting!$E$33:$E$37,'Cash flow forecast'!C$5) -> 1 | D19: =SUMIFS(Formatting!$A$33:$A$37,Formatting!$E$33:$E$37,'Cash flow forecast'!D$5) -> 0 | E19: =SUMIFS(Formatting!$A$33:$A$37,Formatting!$E$33:$E$37,'Cash flow forecast'!E$5) -> 1 | F19: =SUMIFS(Formatting!$A$33:$A$37,Formatting!$E$33:$E$37,'Cash flow forecast'!F$5) -> 0 | G19: =SUMIFS(Formatting!$A$33:$A$37,Formatting!$E$33:$E$37,'Cash flow forecast'!G$5) -> 0 | H19: =SUMIFS(Formatting!$A$33:$A$37,Formatting!$E$33:$E$37,'Cash flow forecast'!H$5) -> 0 | I19: =SUMIFS(Formatting!$A$33:$A$37,Formatting!$E$33:$E$37,'Cash flow forecast'!I$5) -> 0 | J19: =SUMIFS(Formatting!$A$33:$A$37,Formatting!$E$33:$E$37,'Cash flow forecast'!J$5) -> 0 | ... Z19: =SUMIFS(Formatting!$A$33:$A$37,Formatting!$E$33:$E$37,'Cash flow forecast'!Z$5) -> 0
B20: # of Renew Orders | C20: =IFERROR(INDEX(Formatting!$F$34:$T$34,MATCH('Cash flow forecast'!C$5,Formatting!$F$33:$T$33,0)),0)+IFERROR(INDEX(Formatting!$F$36:$T$36,MATCH('Cash flow forecast'!C$5,Formatting!$F$35:$T$35,0)),0)+IFERROR(INDEX(Formatting!$F$38:$T$38,MATCH('Cash flow forecast'!C$5,Formatting!$F$37:$T$37,0)),0) -> 0 | D20: =IFERROR(INDEX(Formatting!$F$34:$T$34,MATCH('Cash flow forecast'!D$5,Formatting!$F$33:$T$33,0)),0)+IFERROR(INDEX(Formatting!$F$36:$T$36,MATCH('Cash flow forecast'!D$5,Formatting!$F$35:$T$35,0)),0)+IFERROR(INDEX(Formatting!$F$38:$T$38,MATCH('Cash flow forecast'!D$5,Formatting!$F$37:$T$37,0)),0) -> 0 | E20: =IFERROR(INDEX(Formatting!$F$34:$T$34,MATCH('Cash flow forecast'!E$5,Formatting!$F$33:$T$33,0)),0)+IFERROR(INDEX(Formatting!$F$36:$T$36,MATCH('Cash flow forecast'!E$5,Formatting!$F$35:$T$35,0)),0)+IFERROR(INDEX(Formatting!$F$38:$T$38,MATCH('Cash flow forecast'!E$5,Formatting!$F$37:$T$37,0)),0) -> 0 | F20: =IFERROR(INDEX(Formatting!$F$34:$T$34,MATCH('Cash flow forecast'!F$5,Formatting!$F$33:$T$33,0)),0)+IFERROR(INDEX(Formatting!$F$36:$T$36,MATCH('Cash flow forecast'!F$5,Formatting!$F$35:$T$35,0)),0)+IFERROR(INDEX(Formatting!$F$38:$T$38,MATCH('Cash flow forecast'!F$5,Formatting!$F$37:$T$37,0)),0) -> 0 | G20: =IFERROR(INDEX(Formatting!$F$34:$T$34,MATCH('Cash flow forecast'!G$5,Formatting!$F$33:$T$33,0)),0)+IFERROR(INDEX(Formatting!$F$36:$T$36,MATCH('Cash flow forecast'!G$5,Formatting!$F$35:$T$35,0)),0)+IFERROR(INDEX(Formatting!$F$38:$T$38,MATCH('Cash flow forecast'!G$5,Formatting!$F$37:$T$37,0)),0) -> 0 | H20: =IFERROR(INDEX(Formatting!$F$34:$T$34,MATCH('Cash flow forecast'!H$5,Formatting!$F$33:$T$33,0)),0)+IFERROR(INDEX(Formatting!$F$36:$T$36,MATCH('Cash flow forecast'!H$5,Formatting!$F$35:$T$35,0)),0)+IFERROR(INDEX(Formatting!$F$38:$T$38,MATCH('Cash flow forecast'!H$5,Formatting!$F$37:$T$37,0)),0) -> 0 | I20: =IFERROR(INDEX(Formatting!$F$34:$T$34,MATCH('Cash flow forecast'!I$5,Formatting!$F$33:$T$33,0)),0)+IFERROR(INDEX(Formatting!$F$36:$T$36,MATCH('Cash flow forecast'!I$5,Formatting!$F$35:$T$35,0)),0)+IFERROR(INDEX(Formatting!$F$38:$T$38,MATCH('Cash flow forecast'!I$5,Formatting!$F$37:$T$37,0)),0) -> 1 | J20: =IFERROR(INDEX(Formatting!$F$34:$T$34,MATCH('Cash flow forecast'!J$5,Formatting!$F$33:$T$33,0)),0)+IFERROR(INDEX(Formatting!$F$36:$T$36,MATCH('Cash flow forecast'!J$5,Formatting!$F$35:$T$35,0)),0)+IFERROR(INDEX(Formatting!$F$38:$T$38,MATCH('Cash flow forecast'!J$5,Formatting!$F$37:$T$37,0)),0) -> 0 | ... Z20: =IFERROR(INDEX(Formatting!$F$34:$T$34,MATCH('Cash flow forecast'!Z$5,Formatting!$F$33:$T$33,0)),0)+IFERROR(INDEX(Formatting!$F$36:$T$36,MATCH('Cash flow forecast'!Z$5,Formatting!$F$35:$T$35,0)),0)+IFERROR(INDEX(Formatting!$F$38:$T$38,MATCH('Cash flow forecast'!Z$5,Formatting!$F$37:$T$37,0)),0) -> 0
B21: Twin Package Orders | C21: =((INDEX(Assumptions!$B$8:$B$46,MATCH("Total Twin",Assumptions!$A$8:$A$46,0)))*((C$19+C$20)*INDEX(Assumptions!$E$78:$E$83,MATCH('Cash flow forecast'!$B21,Assumptions!$A$78:$A$83,0)))) -> 2055.375 | D21: =(((INDEX(Assumptions!$B$8:$B$46,MATCH("Total Twin",Assumptions!$A$8:$A$46,0)))*((D$19+D$20)*INDEX(Assumptions!$E$78:$E$83,MATCH('Cash flow forecast'!$B21,Assumptions!$A$78:$A$83,0)))))*(1+Assumptions!$B$85) -> 0 | E21: =(((INDEX(Assumptions!$B$8:$B$46,MATCH("Total Twin",Assumptions!$A$8:$A$46,0)))*((E$19+E$20)*INDEX(Assumptions!$E$78:$E$83,MATCH('Cash flow forecast'!$B21,Assumptions!$A$78:$A$83,0)))))*(1+Assumptions!$B$85) -> 1849.8375 | F21: =(((INDEX(Assumptions!$B$8:$B$46,MATCH("Total Twin",Assumptions!$A$8:$A$46,0)))*((F$19+F$20)*INDEX(Assumptions!$E$78:$E$83,MATCH('Cash flow forecast'!$B21,Assumptions!$A$78:$A$83,0)))))*(1+Assumptions!$B$85) -> 0 | G21: =(((INDEX(Assumptions!$B$8:$B$46,MATCH("Total Twin",Assumptions!$A$8:$A$46,0)))*((G$19+G$20)*INDEX(Assumptions!$E$78:$E$83,MATCH('Cash flow forecast'!$B21,Assumptions!$A$78:$A$83,0)))))*(1+Assumptions!$B$85) -> 0 | H21: =(((INDEX(Assumptions!$B$8:$B$46,MATCH("Total Twin",Assumptions!$A$8:$A$46,0)))*((H$19+H$20)*INDEX(Assumptions!$E$78:$E$83,MATCH('Cash flow forecast'!$B21,Assumptions!$A$78:$A$83,0)))))*(1+Assumptions!$B$85) -> 0 | I21: =(((INDEX(Assumptions!$B$8:$B$46,MATCH("Total Twin",Assumptions!$A$8:$A$46,0)))*((I$19+I$20)*INDEX(Assumptions!$E$78:$E$83,MATCH('Cash flow forecast'!$B21,Assumptions!$A$78:$A$83,0)))))*(1+Assumptions!$B$85) -> 1849.8375 | J21: =(((INDEX(Assumptions!$B$8:$B$46,MATCH("Total Twin",Assumptions!$A$8:$A$46,0)))*((J$19+J$20)*INDEX(Assumptions!$E$78:$E$83,MATCH('Cash flow forecast'!$B21,Assumptions!$A$78:$A$83,0)))))*(1+Assumptions!$B$85) -> 0 | K21: =(((INDEX(Assumptions!$B$8:$B$46,MATCH("Total Twin",Assumptions!$A$8:$A$46,0)))*((K$19+K$20)*INDEX(Assumptions!$E$78:$E$83,MATCH('Cash flow forecast'!$B21,Assumptions!$A$78:$A$83,0)))))*(1+Assumptions!$B$85) -> 1849.8375 | ... Z21: =(((INDEX(Assumptions!$B$8:$B$46,MATCH("Total Twin",Assumptions!$A$8:$A$46,0)))*((Z$19+Z$20)*INDEX(Assumptions!$E$78:$E$83,MATCH('Cash flow forecast'!$B21,Assumptions!$A$78:$A$83,0)))))*(1+Assumptions!$B$85) -> 0 | AA21: =SUMIFS($C21:$N21,$C$6:$N$6,AA$5) -> 2055.375 | AB21: =SUMIFS($C21:$N21,$C$6:$N$6,AB$5) -> 1849.8375 | AC21: =SUMIFS($C21:$N21,$C$6:$N$6,AC$5) -> 1849.8375 | AD21: =SUMIFS($C21:$N21,$C$6:$N$6,AD$5) -> 1849.8375 | AE21: =SUM($C21:$N21) -> 7604.8875 | AF21: =SUMIFS($O21:$Z21,$O$6:$Z$6,AF$5) -> 1849.8375 | AG21: =SUMIFS($O21:$Z21,$O$6:$Z$6,AG$5) -> 1849.8375 | AH21: =SUMIFS($O21:$Z21,$O$6:$Z$6,AH$5) -> 1849.8375 | AI21: =SUMIFS($O21:$Z21,$O$6:$Z$6,AI$5) -> 1849.8375 | AJ21: =SUM($O21:$Z21) -> 7399.35 | AK21: =AVERAGE(AE21,AJ21)/AVERAGE($AE$58,$AJ$58) -> 0.010861823
B22: Full Package Orders | C22: =((INDEX(Assumptions!$B$8:$B$46,MATCH("Total Full",Assumptions!$A$8:$A$46,0)))*((C$19+C$20)*INDEX(Assumptions!$E$78:$E$83,MATCH('Cash flow forecast'!$B22,Assumptions!$A$78:$A$83,0)))) -> 0 | D22: =(((INDEX(Assumptions!$B$8:$B$46,MATCH("Total Full",Assumptions!$A$8:$A$46,0)))*((D$19+D$20)*INDEX(Assumptions!$E$78:$E$83,MATCH('Cash flow forecast'!$B22,Assumptions!$A$78:$A$83,0)))))*(1+Assumptions!$B$85) -> 0 | E22: =(((INDEX(Assumptions!$B$8:$B$46,MATCH("Total Full",Assumptions!$A$8:$A$46,0)))*((E$19+E$20)*INDEX(Assumptions!$E$78:$E$83,MATCH('Cash flow forecast'!$B22,Assumptions!$A$78:$A$83,0)))))*(1+Assumptions!$B$85) -> 0 | F22: =(((INDEX(Assumptions!$B$8:$B$46,MATCH("Total Full",Assumptions!$A$8:$A$46,0)))*((F$19+F$20)*INDEX(Assumptions!$E$78:$E$83,MATCH('Cash flow forecast'!$B22,Assumptions!$A$78:$A$83,0)))))*(1+Assumptions!$B$85) -> 0 | G22: =(((INDEX(Assumptions!$B$8:$B$46,MATCH("Total Full",Assumptions!$A$8:$A$46,0)))*((G$19+G$20)*INDEX(Assumptions!$E$78:$E$83,MATCH('Cash flow forecast'!$B22,Assumptions!$A$78:$A$83,0)))))*(1+Assumptions!$B$85) -> 0 | H22: =(((INDEX(Assumptions!$B$8:$B$46,MATCH("Total Full",Assumptions!$A$8:$A$46,0)))*((H$19+H$20)*INDEX(Assumptions!$E$78:$E$83,MATCH('Cash flow forecast'!$B22,Assumptions!$A$78:$A$83,0)))))*(1+Assumptions!$B$85) -> 0 | I22: =(((INDEX(Assumptions!$B$8:$B$46,MATCH("Total Full",Assumptions!$A$8:$A$46,0)))*((I$19+I$20)*INDEX(Assumptions!$E$78:$E$83,MATCH('Cash flow forecast'!$B22,Assumptions!$A$78:$A$83,0)))))*(1+Assumptions!$B$85) -> 0 | J22: =(((INDEX(Assumptions!$B$8:$B$46,MATCH("Total Full",Assumptions!$A$8:$A$46,0)))*((J$19+J$20)*INDEX(Assumptions!$E$78:$E$83,MATCH('Cash flow forecast'!$B22,Assumptions!$A$78:$A$83,0)))))*(1+Assumptions!$B$85) -> 0 | K22: =(((INDEX(Assumptions!$B$8:$B$46,MATCH("Total Full",Assumptions!$A$8:$A$46,0)))*((K$19+K$20)*INDEX(Assumptions!$E$78:$E$83,MATCH('Cash flow forecast'!$B22,Assumptions!$A$78:$A$83,0)))))*(1+Assumptions!$B$85) -> 0 | ... Z22: =(((INDEX(Assumptions!$B$8:$B$46,MATCH("Total Full",Assumptions!$A$8:$A$46,0)))*((Z$19+Z$20)*INDEX(Assumptions!$E$78:$E$83,MATCH('Cash flow forecast'!$B22,Assumptions!$A$78:$A$83,0)))))*(1+Assumptions!$B$85) -> 0 | AA22: =SUMIFS($C22:$N22,$C$6:$N$6,AA$5) -> 0 | AB22: =SUMIFS($C22:$N22,$C$6:$N$6,AB$5) -> 0 | AC22: =SUMIFS($C22:$N22,$C$6:$N$6,AC$5) -> 0 | AD22: =SUMIFS($C22:$N22,$C$6:$N$6,AD$5) -> 0 | AE22: =SUM($C22:$N22) -> 0 | AF22: =SUMIFS($O22:$Z22,$O$6:$Z$6,AF$5) -> 0 | AG22: =SUMIFS($O22:$Z22,$O$6:$Z$6,AG$5) -> 0 | AH22: =SUMIFS($O22:$Z22,$O$6:$Z$6,AH$5) -> 0 | AI22: =SUMIFS($O22:$Z22,$O$6:$Z$6,AI$5) -> 0 | AJ22: =SUM($O22:$Z22) -> 0 | AK22: =AVERAGE(AE22,AJ22)/AVERAGE($AE$58,$AJ$58) -> 0
B23: Queen Package Orders | C23: =((INDEX(Assumptions!$B$8:$B$46,MATCH("Total Queen",Assumptions!$A$8:$A$46,0)))*((C$19+C$20)*INDEX(Assumptions!$E$78:$E$83,MATCH('Cash flow forecast'!$B23,Assumptions!$A$78:$A$83,0)))) -> 23400 | D23: =(((INDEX(Assumptions!$B$8:$B$46,MATCH("Total Queen",Assumptions!$A$8:$A$46,0)))*((D$19+D$20)*INDEX(Assumptions!$E$78:$E$83,MATCH('Cash flow forecast'!$B23,Assumptions!$A$78:$A$83,0)))))*(1+Assumptions!$B$85) -> 0 | E23: =(((INDEX(Assumptions!$B$8:$B$46,MATCH("Total Queen",Assumptions!$A$8:$A$46,0)))*((E$19+E$20)*INDEX(Assumptions!$E$78:$E$83,MATCH('Cash flow forecast'!$B23,Assumptions!$A$78:$A$83,0)))))*(1+Assumptions!$B$85) -> 21060 | F23: =(((INDEX(Assumptions!$B$8:$B$46,MATCH("Total Queen",Assumptions!$A$8:$A$46,0)))*((F$19+F$20)*INDEX(Assumptions!$E$78:$E$83,MATCH('Cash flow forecast'!$B23,Assumptions!$A$78:$A$83,0)))))*(1+Assumptions!$B$85) -> 0 | G23: =(((INDEX(Assumptions!$B$8:$B$46,MATCH("Total Queen",Assumptions!$A$8:$A$46,0)))*((G$19+G$20)*INDEX(Assumptions!$E$78:$E$83,MATCH('Cash flow forecast'!$B23,Assumptions!$A$78:$A$83,0)))))*(1+Assumptions!$B$85) -> 0 | H23: =(((INDEX(Assumptions!$B$8:$B$46,MATCH("Total Queen",Assumptions!$A$8:$A$46,0)))*((H$19+H$20)*INDEX(Assumptions!$E$78:$E$83,MATCH('Cash flow forecast'!$B23,Assumptions!$A$78:$A$83,0)))))*(1+Assumptions!$B$85) -> 0 | I23: =(((INDEX(Assumptions!$B$8:$B$46,MATCH("Total Queen",Assumptions!$A$8:$A$46,0)))*((I$19+I$20)*INDEX(Assumptions!$E$78:$E$83,MATCH('Cash flow forecast'!$B23,Assumptions!$A$78:$A$83,0)))))*(1+Assumptions!$B$85) -> 21060 | J23: =(((INDEX(Assumptions!$B$8:$B$46,MATCH("Total Queen",Assumptions!$A$8:$A$46,0)))*((J$19+J$20)*INDEX(Assumptions!$E$78:$E$83,MATCH('Cash flow forecast'!$B23,Assumptions!$A$78:$A$83,0)))))*(1+Assumptions!$B$85) -> 0 | K23: =(((INDEX(Assumptions!$B$8:$B$46,MATCH("Total Queen",Assumptions!$A$8:$A$46,0)))*((K$19+K$20)*INDEX(Assumptions!$E$78:$E$83,MATCH('Cash flow forecast'!$B23,Assumptions!$A$78:$A$83,0)))))*(1+Assumptions!$B$85) -> 21060 | ... Z23: =(((INDEX(Assumptions!$B$8:$B$46,MATCH("Total Queen",Assumptions!$A$8:$A$46,0)))*((Z$19+Z$20)*INDEX(Assumptions!$E$78:$E$83,MATCH('Cash flow forecast'!$B23,Assumptions!$A$78:$A$83,0)))))*(1+Assumptions!$B$85) -> 0 | AA23: =SUMIFS($C23:$N23,$C$6:$N$6,AA$5) -> 23400 | AB23: =SUMIFS($C23:$N23,$C$6:$N$6,AB$5) -> 21060 | AC23: =SUMIFS($C23:$N23,$C$6:$N$6,AC$5) -> 21060 | AD23: =SUMIFS($C23:$N23,$C$6:$N$6,AD$5) -> 21060 | AE23: =SUM($C23:$N23) -> 86580 | AF23: =SUMIFS($O23:$Z23,$O$6:$Z$6,AF$5) -> 21060 | AG23: =SUMIFS($O23:$Z23,$O$6:$Z$6,AG$5) -> 21060 | AH23: =SUMIFS($O23:$Z23,$O$6:$Z$6,AH$5) -> 21060 | AI23: =SUMIFS($O23:$Z23,$O$6:$Z$6,AI$5) -> 21060 | AJ23: =SUM($O23:$Z23) -> 84240 | AK23: =AVERAGE(AE23,AJ23)/AVERAGE($AE$58,$AJ$58) -> 0.1236595
B24: King Package Orders | C24: =((INDEX(Assumptions!$B$8:$B$46,MATCH("Total King",Assumptions!$A$8:$A$46,0)))*((C$19+C$20)*INDEX(Assumptions!$E$78:$E$83,MATCH('Cash flow forecast'!$B24,Assumptions!$A$78:$A$83,0)))) -> 3825 | D24: =(((INDEX(Assumptions!$B$8:$B$46,MATCH("Total King",Assumptions!$A$8:$A$46,0)))*((D$19+D$20)*INDEX(Assumptions!$E$78:$E$83,MATCH('Cash flow forecast'!$B24,Assumptions!$A$78:$A$83,0)))))*(1+Assumptions!$B$85) -> 0 | E24: =(((INDEX(Assumptions!$B$8:$B$46,MATCH("Total King",Assumptions!$A$8:$A$46,0)))*((E$19+E$20)*INDEX(Assumptions!$E$78:$E$83,MATCH('Cash flow forecast'!$B24,Assumptions!$A$78:$A$83,0)))))*(1+Assumptions!$B$85) -> 3442.5 | F24: =(((INDEX(Assumptions!$B$8:$B$46,MATCH("Total King",Assumptions!$A$8:$A$46,0)))*((F$19+F$20)*INDEX(Assumptions!$E$78:$E$83,MATCH('Cash flow forecast'!$B24,Assumptions!$A$78:$A$83,0)))))*(1+Assumptions!$B$85) -> 0 | G24: =(((INDEX(Assumptions!$B$8:$B$46,MATCH("Total King",Assumptions!$A$8:$A$46,0)))*((G$19+G$20)*INDEX(Assumptions!$E$78:$E$83,MATCH('Cash flow forecast'!$B24,Assumptions!$A$78:$A$83,0)))))*(1+Assumptions!$B$85) -> 0 | H24: =(((INDEX(Assumptions!$B$8:$B$46,MATCH("Total King",Assumptions!$A$8:$A$46,0)))*((H$19+H$20)*INDEX(Assumptions!$E$78:$E$83,MATCH('Cash flow forecast'!$B24,Assumptions!$A$78:$A$83,0)))))*(1+Assumptions!$B$85) -> 0 | I24: =(((INDEX(Assumptions!$B$8:$B$46,MATCH("Total King",Assumptions!$A$8:$A$46,0)))*((I$19+I$20)*INDEX(Assumptions!$E$78:$E$83,MATCH('Cash flow forecast'!$B24,Assumptions!$A$78:$A$83,0)))))*(1+Assumptions!$B$85) -> 3442.5 | J24: =(((INDEX(Assumptions!$B$8:$B$46,MATCH("Total King",Assumptions!$A$8:$A$46,0)))*((J$19+J$20)*INDEX(Assumptions!$E$78:$E$83,MATCH('Cash flow forecast'!$B24,Assumptions!$A$78:$A$83,0)))))*(1+Assumptions!$B$85) -> 0 | K24: =(((INDEX(Assumptions!$B$8:$B$46,MATCH("Total King",Assumptions!$A$8:$A$46,0)))*((K$19+K$20)*INDEX(Assumptions!$E$78:$E$83,MATCH('Cash flow forecast'!$B24,Assumptions!$A$78:$A$83,0)))))*(1+Assumptions!$B$85) -> 3442.5 | ... Z24: =(((INDEX(Assumptions!$B$8:$B$46,MATCH("Total King",Assumptions!$A$8:$A$46,0)))*((Z$19+Z$20)*INDEX(Assumptions!$E$78:$E$83,MATCH('Cash flow forecast'!$B24,Assumptions!$A$78:$A$83,0)))))*(1+Assumptions!$B$85) -> 0 | AA24: =SUMIFS($C24:$N24,$C$6:$N$6,AA$5) -> 3825 | AB24: =SUMIFS($C24:$N24,$C$6:$N$6,AB$5) -> 3442.5 | AC24: =SUMIFS($C24:$N24,$C$6:$N$6,AC$5) -> 3442.5 | AD24: =SUMIFS($C24:$N24,$C$6:$N$6,AD$5) -> 3442.5 | AE24: =SUM($C24:$N24) -> 14152.5 | AF24: =SUMIFS($O24:$Z24,$O$6:$Z$6,AF$5) -> 3442.5 | AG24: =SUMIFS($O24:$Z24,$O$6:$Z$6,AG$5) -> 3442.5 | AH24: =SUMIFS($O24:$Z24,$O$6:$Z$6,AH$5) -> 3442.5 | AI24: =SUMIFS($O24:$Z24,$O$6:$Z$6,AI$5) -> 3442.5 | AJ24: =SUM($O24:$Z24) -> 13770 | AK24: =AVERAGE(AE24,AJ24)/AVERAGE($AE$58,$AJ$58) -> 0.020213573
B25: Universal Package Orders | C25: =((INDEX(Assumptions!$B$8:$B$46,MATCH("Total Universal",Assumptions!$A$8:$A$46,0)))*((C$19+C$20)*INDEX(Assumptions!$E$78:$E$83,MATCH('Cash flow forecast'!$B25,Assumptions!$A$78:$A$83,0)))) -> 0 | D25: =(((INDEX(Assumptions!$B$8:$B$46,MATCH("Total Universal",Assumptions!$A$8:$A$46,0)))*((D$19+D$20)*INDEX(Assumptions!$E$78:$E$83,MATCH('Cash flow forecast'!$B25,Assumptions!$A$78:$A$83,0)))))*(1+Assumptions!$B$85) -> 0 | E25: =(((INDEX(Assumptions!$B$8:$B$46,MATCH("Total Universal",Assumptions!$A$8:$A$46,0)))*((E$19+E$20)*INDEX(Assumptions!$E$78:$E$83,MATCH('Cash flow forecast'!$B25,Assumptions!$A$78:$A$83,0)))))*(1+Assumptions!$B$85) -> 0 | F25: =(((INDEX(Assumptions!$B$8:$B$46,MATCH("Total Universal",Assumptions!$A$8:$A$46,0)))*((F$19+F$20)*INDEX(Assumptions!$E$78:$E$83,MATCH('Cash flow forecast'!$B25,Assumptions!$A$78:$A$83,0)))))*(1+Assumptions!$B$85) -> 0 | G25: =(((INDEX(Assumptions!$B$8:$B$46,MATCH("Total Universal",Assumptions!$A$8:$A$46,0)))*((G$19+G$20)*INDEX(Assumptions!$E$78:$E$83,MATCH('Cash flow forecast'!$B25,Assumptions!$A$78:$A$83,0)))))*(1+Assumptions!$B$85) -> 0 | H25: =(((INDEX(Assumptions!$B$8:$B$46,MATCH("Total Universal",Assumptions!$A$8:$A$46,0)))*((H$19+H$20)*INDEX(Assumptions!$E$78:$E$83,MATCH('Cash flow forecast'!$B25,Assumptions!$A$78:$A$83,0)))))*(1+Assumptions!$B$85) -> 0 | I25: =(((INDEX(Assumptions!$B$8:$B$46,MATCH("Total Universal",Assumptions!$A$8:$A$46,0)))*((I$19+I$20)*INDEX(Assumptions!$E$78:$E$83,MATCH('Cash flow forecast'!$B25,Assumptions!$A$78:$A$83,0)))))*(1+Assumptions!$B$85) -> 0 | J25: =(((INDEX(Assumptions!$B$8:$B$46,MATCH("Total Universal",Assumptions!$A$8:$A$46,0)))*((J$19+J$20)*INDEX(Assumptions!$E$78:$E$83,MATCH('Cash flow forecast'!$B25,Assumptions!$A$78:$A$83,0)))))*(1+Assumptions!$B$85) -> 0 | K25: =(((INDEX(Assumptions!$B$8:$B$46,MATCH("Total Universal",Assumptions!$A$8:$A$46,0)))*((K$19+K$20)*INDEX(Assumptions!$E$78:$E$83,MATCH('Cash flow forecast'!$B25,Assumptions!$A$78:$A$83,0)))))*(1+Assumptions!$B$85) -> 0 | ... Z25: =(((INDEX(Assumptions!$B$8:$B$46,MATCH("Total Universal",Assumptions!$A$8:$A$46,0)))*((Z$19+Z$20)*INDEX(Assumptions!$E$78:$E$83,MATCH('Cash flow forecast'!$B25,Assumptions!$A$78:$A$83,0)))))*(1+Assumptions!$B$85) -> 0 | AA25: =SUMIFS($C25:$N25,$C$6:$N$6,AA$5) -> 0 | AB25: =SUMIFS($C25:$N25,$C$6:$N$6,AB$5) -> 0 | AC25: =SUMIFS($C25:$N25,$C$6:$N$6,AC$5) -> 0 | AD25: =SUMIFS($C25:$N25,$C$6:$N$6,AD$5) -> 0 | AE25: =SUM($C25:$N25) -> 0 | AF25: =SUMIFS($O25:$Z25,$O$6:$Z$6,AF$5) -> 0 | AG25: =SUMIFS($O25:$Z25,$O$6:$Z$6,AG$5) -> 0 | AH25: =SUMIFS($O25:$Z25,$O$6:$Z$6,AH$5) -> 0 | AI25: =SUMIFS($O25:$Z25,$O$6:$Z$6,AI$5) -> 0 | AJ25: =SUM($O25:$Z25) -> 0 | AK25: =AVERAGE(AE25,AJ25)/AVERAGE($AE$58,$AJ$58) -> 0
B26: Total | C26: =SUM(C21:C25) -> 29280.375 | D26: =SUM(D21:D25) -> 0 | E26: =SUM(E21:E25) -> 26352.338 | F26: =SUM(F21:F25) -> 0 | G26: =SUM(G21:G25) -> 0 | H26: =SUM(H21:H25) -> 0 | I26: =SUM(I21:I25) -> 26352.338 | J26: =SUM(J21:J25) -> 0 | ... AD26: =SUM(AD21:AD25) -> 26352.338 | AE26: =SUM($C26:$N26) -> 108337.39 | AF26: =SUM(AF21:AF25) -> 26352.338 | AG26: =SUM(AG21:AG25) -> 26352.338 | AH26: =SUM(AH21:AH25) -> 26352.338 | AI26: =SUM(AI21:AI25) -> 26352.338 | AJ26: =SUM($O26:$Z26) -> 105409.35 | AK26: =AVERAGE(AE26,AJ26)/AVERAGE($AE$58,$AJ$58) -> 0.1547349
B27: Large Hotels
B28: # of New Hotels | C28: =SUMIFS(Formatting!$A$43:$A$47,Formatting!$E$43:$E$47,'Cash flow forecast'!C$5) -> 1 | D28: =SUMIFS(Formatting!$A$43:$A$47,Formatting!$E$43:$E$47,'Cash flow forecast'!D$5) -> 0 | E28: =SUMIFS(Formatting!$A$43:$A$47,Formatting!$E$43:$E$47,'Cash flow forecast'!E$5) -> 1 | F28: =SUMIFS(Formatting!$A$43:$A$47,Formatting!$E$43:$E$47,'Cash flow forecast'!F$5) -> 0 | G28: =SUMIFS(Formatting!$A$43:$A$47,Formatting!$E$43:$E$47,'Cash flow forecast'!G$5) -> 0 | H28: =SUMIFS(Formatting!$A$43:$A$47,Formatting!$E$43:$E$47,'Cash flow forecast'!H$5) -> 0 | I28: =SUMIFS(Formatting!$A$43:$A$47,Formatting!$E$43:$E$47,'Cash flow forecast'!I$5) -> 0 | J28: =SUMIFS(Formatting!$A$43:$A$47,Formatting!$E$43:$E$47,'Cash flow forecast'!J$5) -> 0 | ... Z28: =SUMIFS(Formatting!$A$43:$A$47,Formatting!$E$43:$E$47,'Cash flow forecast'!Z$5) -> 0
B29: # of Renew Orders | C29: =IFERROR(INDEX(Formatting!$F$44:$T$44,MATCH('Cash flow forecast'!C$5,Formatting!$F$43:$T$43,0)),0)+IFERROR(INDEX(Formatting!$F$46:$T$46,MATCH('Cash flow forecast'!C$5,Formatting!$F$45:$T$45,0)),0)+IFERROR(INDEX(Formatting!$F$48:$T$48,MATCH('Cash flow forecast'!C$5,Formatting!$F$47:$T$47,0)),0) -> 0 | D29: =IFERROR(INDEX(Formatting!$F$44:$T$44,MATCH('Cash flow forecast'!D$5,Formatting!$F$43:$T$43,0)),0)+IFERROR(INDEX(Formatting!$F$46:$T$46,MATCH('Cash flow forecast'!D$5,Formatting!$F$45:$T$45,0)),0)+IFERROR(INDEX(Formatting!$F$48:$T$48,MATCH('Cash flow forecast'!D$5,Formatting!$F$47:$T$47,0)),0) -> 0 | E29: =IFERROR(INDEX(Formatting!$F$44:$T$44,MATCH('Cash flow forecast'!E$5,Formatting!$F$43:$T$43,0)),0)+IFERROR(INDEX(Formatting!$F$46:$T$46,MATCH('Cash flow forecast'!E$5,Formatting!$F$45:$T$45,0)),0)+IFERROR(INDEX(Formatting!$F$48:$T$48,MATCH('Cash flow forecast'!E$5,Formatting!$F$47:$T$47,0)),0) -> 0 | F29: =IFERROR(INDEX(Formatting!$F$44:$T$44,MATCH('Cash flow forecast'!F$5,Formatting!$F$43:$T$43,0)),0)+IFERROR(INDEX(Formatting!$F$46:$T$46,MATCH('Cash flow forecast'!F$5,Formatting!$F$45:$T$45,0)),0)+IFERROR(INDEX(Formatting!$F$48:$T$48,MATCH('Cash flow forecast'!F$5,Formatting!$F$47:$T$47,0)),0) -> 0 | G29: =IFERROR(INDEX(Formatting!$F$44:$T$44,MATCH('Cash flow forecast'!G$5,Formatting!$F$43:$T$43,0)),0)+IFERROR(INDEX(Formatting!$F$46:$T$46,MATCH('Cash flow forecast'!G$5,Formatting!$F$45:$T$45,0)),0)+IFERROR(INDEX(Formatting!$F$48:$T$48,MATCH('Cash flow forecast'!G$5,Formatting!$F$47:$T$47,0)),0) -> 0 | H29: =IFERROR(INDEX(Formatting!$F$44:$T$44,MATCH('Cash flow forecast'!H$5,Formatting!$F$43:$T$43,0)),0)+IFERROR(INDEX(Formatting!$F$46:$T$46,MATCH('Cash flow forecast'!H$5,Formatting!$F$45:$T$45,0)),0)+IFERROR(INDEX(Formatting!$F$48:$T$48,MATCH('Cash flow forecast'!H$5,Formatting!$F$47:$T$47,0)),0) -> 0 | I29: =IFERROR(INDEX(Formatting!$F$44:$T$44,MATCH('Cash flow forecast'!I$5,Formatting!$F$43:$T$43,0)),0)+IFERROR(INDEX(Formatting!$F$46:$T$46,MATCH('Cash flow forecast'!I$5,Formatting!$F$45:$T$45,0)),0)+IFERROR(INDEX(Formatting!$F$48:$T$48,MATCH('Cash flow forecast'!I$5,Formatting!$F$47:$T$47,0)),0) -> 1 | J29: =IFERROR(INDEX(Formatting!$F$44:$T$44,MATCH('Cash flow forecast'!J$5,Formatting!$F$43:$T$43,0)),0)+IFERROR(INDEX(Formatting!$F$46:$T$46,MATCH('Cash flow forecast'!J$5,Formatting!$F$45:$T$45,0)),0)+IFERROR(INDEX(Formatting!$F$48:$T$48,MATCH('Cash flow forecast'!J$5,Formatting!$F$47:$T$47,0)),0) -> 0 | ... Z29: =IFERROR(INDEX(Formatting!$F$44:$T$44,MATCH('Cash flow forecast'!Z$5,Formatting!$F$43:$T$43,0)),0)+IFERROR(INDEX(Formatting!$F$46:$T$46,MATCH('Cash flow forecast'!Z$5,Formatting!$F$45:$T$45,0)),0)+IFERROR(INDEX(Formatting!$F$48:$T$48,MATCH('Cash flow forecast'!Z$5,Formatting!$F$47:$T$47,0)),0) -> 0
B30: Twin Package Orders | C30: =((INDEX(Assumptions!$B$8:$B$46,MATCH("Total Twin",Assumptions!$A$8:$A$46,0)))*((C$28+C$29)*INDEX(Assumptions!$E$96:$E$101,MATCH('Cash flow forecast'!$B30,Assumptions!$A$96:$A$101,0)))) -> 2055.375 | D30: =(((INDEX(Assumptions!$B$8:$B$46,MATCH("Total Twin",Assumptions!$A$8:$A$46,0)))*((D$28+D$29)*INDEX(Assumptions!$E$96:$E$101,MATCH('Cash flow forecast'!$B30,Assumptions!$A$96:$A$101,0))))*(1+Assumptions!$B$103)) -> 0 | E30: =(((INDEX(Assumptions!$B$8:$B$46,MATCH("Total Twin",Assumptions!$A$8:$A$46,0)))*((E$28+E$29)*INDEX(Assumptions!$E$96:$E$101,MATCH('Cash flow forecast'!$B30,Assumptions!$A$96:$A$101,0))))*(1+Assumptions!$B$103)) -> 1849.8375 | F30: =(((INDEX(Assumptions!$B$8:$B$46,MATCH("Total Twin",Assumptions!$A$8:$A$46,0)))*((F$28+F$29)*INDEX(Assumptions!$E$96:$E$101,MATCH('Cash flow forecast'!$B30,Assumptions!$A$96:$A$101,0))))*(1+Assumptions!$B$103)) -> 0 | G30: =(((INDEX(Assumptions!$B$8:$B$46,MATCH("Total Twin",Assumptions!$A$8:$A$46,0)))*((G$28+G$29)*INDEX(Assumptions!$E$96:$E$101,MATCH('Cash flow forecast'!$B30,Assumptions!$A$96:$A$101,0))))*(1+Assumptions!$B$103)) -> 0 | H30: =(((INDEX(Assumptions!$B$8:$B$46,MATCH("Total Twin",Assumptions!$A$8:$A$46,0)))*((H$28+H$29)*INDEX(Assumptions!$E$96:$E$101,MATCH('Cash flow forecast'!$B30,Assumptions!$A$96:$A$101,0))))*(1+Assumptions!$B$103)) -> 0 | I30: =(((INDEX(Assumptions!$B$8:$B$46,MATCH("Total Twin",Assumptions!$A$8:$A$46,0)))*((I$28+I$29)*INDEX(Assumptions!$E$96:$E$101,MATCH('Cash flow forecast'!$B30,Assumptions!$A$96:$A$101,0))))*(1+Assumptions!$B$103)) -> 1849.8375 | J30: =(((INDEX(Assumptions!$B$8:$B$46,MATCH("Total Twin",Assumptions!$A$8:$A$46,0)))*((J$28+J$29)*INDEX(Assumptions!$E$96:$E$101,MATCH('Cash flow forecast'!$B30,Assumptions!$A$96:$A$101,0))))*(1+Assumptions!$B$103)) -> 0 | K30: =(((INDEX(Assumptions!$B$8:$B$46,MATCH("Total Twin",Assumptions!$A$8:$A$46,0)))*((K$28+K$29)*INDEX(Assumptions!$E$96:$E$101,MATCH('Cash flow forecast'!$B30,Assumptions!$A$96:$A$101,0))))*(1+Assumptions!$B$103)) -> 1849.8375 | ... Z30: =(((INDEX(Assumptions!$B$8:$B$46,MATCH("Total Twin",Assumptions!$A$8:$A$46,0)))*((Z$28+Z$29)*INDEX(Assumptions!$E$96:$E$101,MATCH('Cash flow forecast'!$B30,Assumptions!$A$96:$A$101,0))))*(1+Assumptions!$B$103)) -> 0 | AA30: =SUMIFS($C30:$N30,$C$6:$N$6,AA$5) -> 2055.375 | AB30: =SUMIFS($C30:$N30,$C$6:$N$6,AB$5) -> 1849.8375 | AC30: =SUMIFS($C30:$N30,$C$6:$N$6,AC$5) -> 1849.8375 | AD30: =SUMIFS($C30:$N30,$C$6:$N$6,AD$5) -> 1849.8375 | AE30: =SUM($C30:$N30) -> 7604.8875 | AF30: =SUMIFS($O30:$Z30,$O$6:$Z$6,AF$5) -> 1849.8375 | AG30: =SUMIFS($O30:$Z30,$O$6:$Z$6,AG$5) -> 1849.8375 | AH30: =SUMIFS($O30:$Z30,$O$6:$Z$6,AH$5) -> 1849.8375 | AI30: =SUMIFS($O30:$Z30,$O$6:$Z$6,AI$5) -> 3699.675 | AJ30: =SUM($O30:$Z30) -> 9249.1875 | AK30: =AVERAGE(AE30,AJ30)/AVERAGE($AE$58,$AJ$58) -> 0.012200952
B31: Full Package Orders | C31: =((INDEX(Assumptions!$B$8:$B$46,MATCH("Total Full",Assumptions!$A$8:$A$46,0)))*((C$28+C$29)*INDEX(Assumptions!$E$96:$E$101,MATCH('Cash flow forecast'!$B31,Assumptions!$A$96:$A$101,0)))) -> 0 | D31: =(((INDEX(Assumptions!$B$8:$B$46,MATCH("Total Full",Assumptions!$A$8:$A$46,0)))*((D$28+D$29)*INDEX(Assumptions!$E$96:$E$101,MATCH('Cash flow forecast'!$B31,Assumptions!$A$96:$A$101,0)))))*(1+Assumptions!$B$103) -> 0 | E31: =(((INDEX(Assumptions!$B$8:$B$46,MATCH("Total Full",Assumptions!$A$8:$A$46,0)))*((E$28+E$29)*INDEX(Assumptions!$E$96:$E$101,MATCH('Cash flow forecast'!$B31,Assumptions!$A$96:$A$101,0)))))*(1+Assumptions!$B$103) -> 0 | F31: =(((INDEX(Assumptions!$B$8:$B$46,MATCH("Total Full",Assumptions!$A$8:$A$46,0)))*((F$28+F$29)*INDEX(Assumptions!$E$96:$E$101,MATCH('Cash flow forecast'!$B31,Assumptions!$A$96:$A$101,0)))))*(1+Assumptions!$B$103) -> 0 | G31: =(((INDEX(Assumptions!$B$8:$B$46,MATCH("Total Full",Assumptions!$A$8:$A$46,0)))*((G$28+G$29)*INDEX(Assumptions!$E$96:$E$101,MATCH('Cash flow forecast'!$B31,Assumptions!$A$96:$A$101,0)))))*(1+Assumptions!$B$103) -> 0 | H31: =(((INDEX(Assumptions!$B$8:$B$46,MATCH("Total Full",Assumptions!$A$8:$A$46,0)))*((H$28+H$29)*INDEX(Assumptions!$E$96:$E$101,MATCH('Cash flow forecast'!$B31,Assumptions!$A$96:$A$101,0)))))*(1+Assumptions!$B$103) -> 0 | I31: =(((INDEX(Assumptions!$B$8:$B$46,MATCH("Total Full",Assumptions!$A$8:$A$46,0)))*((I$28+I$29)*INDEX(Assumptions!$E$96:$E$101,MATCH('Cash flow forecast'!$B31,Assumptions!$A$96:$A$101,0)))))*(1+Assumptions!$B$103) -> 0 | J31: =(((INDEX(Assumptions!$B$8:$B$46,MATCH("Total Full",Assumptions!$A$8:$A$46,0)))*((J$28+J$29)*INDEX(Assumptions!$E$96:$E$101,MATCH('Cash flow forecast'!$B31,Assumptions!$A$96:$A$101,0)))))*(1+Assumptions!$B$103) -> 0 | K31: =(((INDEX(Assumptions!$B$8:$B$46,MATCH("Total Full",Assumptions!$A$8:$A$46,0)))*((K$28+K$29)*INDEX(Assumptions!$E$96:$E$101,MATCH('Cash flow forecast'!$B31,Assumptions!$A$96:$A$101,0)))))*(1+Assumptions!$B$103) -> 0 | ... Z31: =(((INDEX(Assumptions!$B$8:$B$46,MATCH("Total Full",Assumptions!$A$8:$A$46,0)))*((Z$28+Z$29)*INDEX(Assumptions!$E$96:$E$101,MATCH('Cash flow forecast'!$B31,Assumptions!$A$96:$A$101,0)))))*(1+Assumptions!$B$103) -> 0 | AA31: =SUMIFS($C31:$N31,$C$6:$N$6,AA$5) -> 0 | AB31: =SUMIFS($C31:$N31,$C$6:$N$6,AB$5) -> 0 | AC31: =SUMIFS($C31:$N31,$C$6:$N$6,AC$5) -> 0 | AD31: =SUMIFS($C31:$N31,$C$6:$N$6,AD$5) -> 0 | AE31: =SUM($C31:$N31) -> 0 | AF31: =SUMIFS($O31:$Z31,$O$6:$Z$6,AF$5) -> 0 | AG31: =SUMIFS($O31:$Z31,$O$6:$Z$6,AG$5) -> 0 | AH31: =SUMIFS($O31:$Z31,$O$6:$Z$6,AH$5) -> 0 | AI31: =SUMIFS($O31:$Z31,$O$6:$Z$6,AI$5) -> 0 | AJ31: =SUM($O31:$Z31) -> 0 | AK31: =AVERAGE(AE31,AJ31)/AVERAGE($AE$58,$AJ$58) -> 0
B32: Queen Package Orders | C32: =((INDEX(Assumptions!$B$8:$B$46,MATCH("Total Queen",Assumptions!$A$8:$A$46,0)))*((C$28+C$29)*INDEX(Assumptions!$E$96:$E$101,MATCH('Cash flow forecast'!$B32,Assumptions!$A$96:$A$101,0)))) -> 23400 | D32: =(((INDEX(Assumptions!$B$8:$B$46,MATCH("Total Queen",Assumptions!$A$8:$A$46,0)))*((D$28+D$29)*INDEX(Assumptions!$E$96:$E$101,MATCH('Cash flow forecast'!$B32,Assumptions!$A$96:$A$101,0)))))*(1+Assumptions!$B$103) -> 0 | E32: =(((INDEX(Assumptions!$B$8:$B$46,MATCH("Total Queen",Assumptions!$A$8:$A$46,0)))*((E$28+E$29)*INDEX(Assumptions!$E$96:$E$101,MATCH('Cash flow forecast'!$B32,Assumptions!$A$96:$A$101,0)))))*(1+Assumptions!$B$103) -> 21060 | F32: =(((INDEX(Assumptions!$B$8:$B$46,MATCH("Total Queen",Assumptions!$A$8:$A$46,0)))*((F$28+F$29)*INDEX(Assumptions!$E$96:$E$101,MATCH('Cash flow forecast'!$B32,Assumptions!$A$96:$A$101,0)))))*(1+Assumptions!$B$103) -> 0 | G32: =(((INDEX(Assumptions!$B$8:$B$46,MATCH("Total Queen",Assumptions!$A$8:$A$46,0)))*((G$28+G$29)*INDEX(Assumptions!$E$96:$E$101,MATCH('Cash flow forecast'!$B32,Assumptions!$A$96:$A$101,0)))))*(1+Assumptions!$B$103) -> 0 | H32: =(((INDEX(Assumptions!$B$8:$B$46,MATCH("Total Queen",Assumptions!$A$8:$A$46,0)))*((H$28+H$29)*INDEX(Assumptions!$E$96:$E$101,MATCH('Cash flow forecast'!$B32,Assumptions!$A$96:$A$101,0)))))*(1+Assumptions!$B$103) -> 0 | I32: =(((INDEX(Assumptions!$B$8:$B$46,MATCH("Total Queen",Assumptions!$A$8:$A$46,0)))*((I$28+I$29)*INDEX(Assumptions!$E$96:$E$101,MATCH('Cash flow forecast'!$B32,Assumptions!$A$96:$A$101,0)))))*(1+Assumptions!$B$103) -> 21060 | J32: =(((INDEX(Assumptions!$B$8:$B$46,MATCH("Total Queen",Assumptions!$A$8:$A$46,0)))*((J$28+J$29)*INDEX(Assumptions!$E$96:$E$101,MATCH('Cash flow forecast'!$B32,Assumptions!$A$96:$A$101,0)))))*(1+Assumptions!$B$103) -> 0 | K32: =(((INDEX(Assumptions!$B$8:$B$46,MATCH("Total Queen",Assumptions!$A$8:$A$46,0)))*((K$28+K$29)*INDEX(Assumptions!$E$96:$E$101,MATCH('Cash flow forecast'!$B32,Assumptions!$A$96:$A$101,0)))))*(1+Assumptions!$B$103) -> 21060 | ... Z32: =(((INDEX(Assumptions!$B$8:$B$46,MATCH("Total Queen",Assumptions!$A$8:$A$46,0)))*((Z$28+Z$29)*INDEX(Assumptions!$E$96:$E$101,MATCH('Cash flow forecast'!$B32,Assumptions!$A$96:$A$101,0)))))*(1+Assumptions!$B$103) -> 0 | AA32: =SUMIFS($C32:$N32,$C$6:$N$6,AA$5) -> 23400 | AB32: =SUMIFS($C32:$N32,$C$6:$N$6,AB$5) -> 21060 | AC32: =SUMIFS($C32:$N32,$C$6:$N$6,AC$5) -> 21060 | AD32: =SUMIFS($C32:$N32,$C$6:$N$6,AD$5) -> 21060 | AE32: =SUM($C32:$N32) -> 86580 | AF32: =SUMIFS($O32:$Z32,$O$6:$Z$6,AF$5) -> 21060 | AG32: =SUMIFS($O32:$Z32,$O$6:$Z$6,AG$5) -> 21060 | AH32: =SUMIFS($O32:$Z32,$O$6:$Z$6,AH$5) -> 21060 | AI32: =SUMIFS($O32:$Z32,$O$6:$Z$6,AI$5) -> 42120 | AJ32: =SUM($O32:$Z32) -> 105300 | AK32: =AVERAGE(AE32,AJ32)/AVERAGE($AE$58,$AJ$58) -> 0.1389052
B33: King Package Orders | C33: =((INDEX(Assumptions!$B$8:$B$46,MATCH("Total King",Assumptions!$A$8:$A$46,0)))*((C$28+C$29)*INDEX(Assumptions!$E$96:$E$101,MATCH('Cash flow forecast'!$B33,Assumptions!$A$96:$A$101,0)))) -> 3825 | D33: =(((INDEX(Assumptions!$B$8:$B$46,MATCH("Total King",Assumptions!$A$8:$A$46,0)))*((D$28+D$29)*INDEX(Assumptions!$E$96:$E$101,MATCH('Cash flow forecast'!$B33,Assumptions!$A$96:$A$101,0)))))*(1+Assumptions!$B$103) -> 0 | E33: =(((INDEX(Assumptions!$B$8:$B$46,MATCH("Total King",Assumptions!$A$8:$A$46,0)))*((E$28+E$29)*INDEX(Assumptions!$E$96:$E$101,MATCH('Cash flow forecast'!$B33,Assumptions!$A$96:$A$101,0)))))*(1+Assumptions!$B$103) -> 3442.5 | F33: =(((INDEX(Assumptions!$B$8:$B$46,MATCH("Total King",Assumptions!$A$8:$A$46,0)))*((F$28+F$29)*INDEX(Assumptions!$E$96:$E$101,MATCH('Cash flow forecast'!$B33,Assumptions!$A$96:$A$101,0)))))*(1+Assumptions!$B$103) -> 0 | G33: =(((INDEX(Assumptions!$B$8:$B$46,MATCH("Total King",Assumptions!$A$8:$A$46,0)))*((G$28+G$29)*INDEX(Assumptions!$E$96:$E$101,MATCH('Cash flow forecast'!$B33,Assumptions!$A$96:$A$101,0)))))*(1+Assumptions!$B$103) -> 0 | H33: =(((INDEX(Assumptions!$B$8:$B$46,MATCH("Total King",Assumptions!$A$8:$A$46,0)))*((H$28+H$29)*INDEX(Assumptions!$E$96:$E$101,MATCH('Cash flow forecast'!$B33,Assumptions!$A$96:$A$101,0)))))*(1+Assumptions!$B$103) -> 0 | I33: =(((INDEX(Assumptions!$B$8:$B$46,MATCH("Total King",Assumptions!$A$8:$A$46,0)))*((I$28+I$29)*INDEX(Assumptions!$E$96:$E$101,MATCH('Cash flow forecast'!$B33,Assumptions!$A$96:$A$101,0)))))*(1+Assumptions!$B$103) -> 3442.5 | J33: =(((INDEX(Assumptions!$B$8:$B$46,MATCH("Total King",Assumptions!$A$8:$A$46,0)))*((J$28+J$29)*INDEX(Assumptions!$E$96:$E$101,MATCH('Cash flow forecast'!$B33,Assumptions!$A$96:$A$101,0)))))*(1+Assumptions!$B$103) -> 0 | K33: =(((INDEX(Assumptions!$B$8:$B$46,MATCH("Total King",Assumptions!$A$8:$A$46,0)))*((K$28+K$29)*INDEX(Assumptions!$E$96:$E$101,MATCH('Cash flow forecast'!$B33,Assumptions!$A$96:$A$101,0)))))*(1+Assumptions!$B$103) -> 3442.5 | ... Z33: =(((INDEX(Assumptions!$B$8:$B$46,MATCH("Total King",Assumptions!$A$8:$A$46,0)))*((Z$28+Z$29)*INDEX(Assumptions!$E$96:$E$101,MATCH('Cash flow forecast'!$B33,Assumptions!$A$96:$A$101,0)))))*(1+Assumptions!$B$103) -> 0 | AA33: =SUMIFS($C33:$N33,$C$6:$N$6,AA$5) -> 3825 | AB33: =SUMIFS($C33:$N33,$C$6:$N$6,AB$5) -> 3442.5 | AC33: =SUMIFS($C33:$N33,$C$6:$N$6,AC$5) -> 3442.5 | AD33: =SUMIFS($C33:$N33,$C$6:$N$6,AD$5) -> 3442.5 | AE33: =SUM($C33:$N33) -> 14152.5 | AF33: =SUMIFS($O33:$Z33,$O$6:$Z$6,AF$5) -> 3442.5 | AG33: =SUMIFS($O33:$Z33,$O$6:$Z$6,AG$5) -> 3442.5 | AH33: =SUMIFS($O33:$Z33,$O$6:$Z$6,AH$5) -> 3442.5 | AI33: =SUMIFS($O33:$Z33,$O$6:$Z$6,AI$5) -> 6885 | AJ33: =SUM($O33:$Z33) -> 17212.5 | AK33: =AVERAGE(AE33,AJ33)/AVERAGE($AE$58,$AJ$58) -> 0.022705657
B34: Universal Package Orders | C34: =((INDEX(Assumptions!$B$8:$B$46,MATCH("Total Universal",Assumptions!$A$8:$A$46,0)))*((C$28+C$29)*INDEX(Assumptions!$E$96:$E$101,MATCH('Cash flow forecast'!$B34,Assumptions!$A$96:$A$101,0)))) -> 0 | D34: =(((INDEX(Assumptions!$B$8:$B$46,MATCH("Total Universal",Assumptions!$A$8:$A$46,0)))*((D$28+D$29)*INDEX(Assumptions!$E$96:$E$101,MATCH('Cash flow forecast'!$B34,Assumptions!$A$96:$A$101,0)))))*(1+Assumptions!$B$103) -> 0 | E34: =(((INDEX(Assumptions!$B$8:$B$46,MATCH("Total Universal",Assumptions!$A$8:$A$46,0)))*((E$28+E$29)*INDEX(Assumptions!$E$96:$E$101,MATCH('Cash flow forecast'!$B34,Assumptions!$A$96:$A$101,0)))))*(1+Assumptions!$B$103) -> 0 | F34: =(((INDEX(Assumptions!$B$8:$B$46,MATCH("Total Universal",Assumptions!$A$8:$A$46,0)))*((F$28+F$29)*INDEX(Assumptions!$E$96:$E$101,MATCH('Cash flow forecast'!$B34,Assumptions!$A$96:$A$101,0)))))*(1+Assumptions!$B$103) -> 0 | G34: =(((INDEX(Assumptions!$B$8:$B$46,MATCH("Total Universal",Assumptions!$A$8:$A$46,0)))*((G$28+G$29)*INDEX(Assumptions!$E$96:$E$101,MATCH('Cash flow forecast'!$B34,Assumptions!$A$96:$A$101,0)))))*(1+Assumptions!$B$103) -> 0 | H34: =(((INDEX(Assumptions!$B$8:$B$46,MATCH("Total Universal",Assumptions!$A$8:$A$46,0)))*((H$28+H$29)*INDEX(Assumptions!$E$96:$E$101,MATCH('Cash flow forecast'!$B34,Assumptions!$A$96:$A$101,0)))))*(1+Assumptions!$B$103) -> 0 | I34: =(((INDEX(Assumptions!$B$8:$B$46,MATCH("Total Universal",Assumptions!$A$8:$A$46,0)))*((I$28+I$29)*INDEX(Assumptions!$E$96:$E$101,MATCH('Cash flow forecast'!$B34,Assumptions!$A$96:$A$101,0)))))*(1+Assumptions!$B$103) -> 0 | J34: =(((INDEX(Assumptions!$B$8:$B$46,MATCH("Total Universal",Assumptions!$A$8:$A$46,0)))*((J$28+J$29)*INDEX(Assumptions!$E$96:$E$101,MATCH('Cash flow forecast'!$B34,Assumptions!$A$96:$A$101,0)))))*(1+Assumptions!$B$103) -> 0 | K34: =(((INDEX(Assumptions!$B$8:$B$46,MATCH("Total Universal",Assumptions!$A$8:$A$46,0)))*((K$28+K$29)*INDEX(Assumptions!$E$96:$E$101,MATCH('Cash flow forecast'!$B34,Assumptions!$A$96:$A$101,0)))))*(1+Assumptions!$B$103) -> 0 | ... Z34: =(((INDEX(Assumptions!$B$8:$B$46,MATCH("Total Universal",Assumptions!$A$8:$A$46,0)))*((Z$28+Z$29)*INDEX(Assumptions!$E$96:$E$101,MATCH('Cash flow forecast'!$B34,Assumptions!$A$96:$A$101,0)))))*(1+Assumptions!$B$103) -> 0 | AA34: =SUMIFS($C34:$N34,$C$6:$N$6,AA$5) -> 0 | AB34: =SUMIFS($C34:$N34,$C$6:$N$6,AB$5) -> 0 | AC34: =SUMIFS($C34:$N34,$C$6:$N$6,AC$5) -> 0 | AD34: =SUMIFS($C34:$N34,$C$6:$N$6,AD$5) -> 0 | AE34: =SUM($C34:$N34) -> 0 | AF34: =SUMIFS($O34:$Z34,$O$6:$Z$6,AF$5) -> 0 | AG34: =SUMIFS($O34:$Z34,$O$6:$Z$6,AG$5) -> 0 | AH34: =SUMIFS($O34:$Z34,$O$6:$Z$6,AH$5) -> 0 | AI34: =SUMIFS($O34:$Z34,$O$6:$Z$6,AI$5) -> 0 | AJ34: =SUM($O34:$Z34) -> 0 | AK34: =AVERAGE(AE34,AJ34)/AVERAGE($AE$58,$AJ$58) -> 0
B35: Total | C35: =SUM(C30:C34) -> 29280.375 | D35: =SUM(D30:D34) -> 0 | E35: =SUM(E30:E34) -> 26352.338 | F35: =SUM(F30:F34) -> 0 | G35: =SUM(G30:G34) -> 0 | H35: =SUM(H30:H34) -> 0 | I35: =SUM(I30:I34) -> 26352.338 | J35: =SUM(J30:J34) -> 0 | ... AD35: =SUM(AD30:AD34) -> 26352.338 | AE35: =SUM($C35:$N35) -> 108337.39 | AF35: =SUM(AF30:AF34) -> 26352.338 | AG35: =SUM(AG30:AG34) -> 26352.338 | AH35: =SUM(AH30:AH34) -> 26352.338 | AI35: =SUM(AI30:AI34) -> 52704.675 | AJ35: =SUM($O35:$Z35) -> 131761.69 | AK35: =AVERAGE(AE35,AJ35)/AVERAGE($AE$58,$AJ$58) -> 0.1738118
B37: Total Wholesale Revenue | C37: =C17+C26+C35 -> 204962.62 | D37: =D17+D26+D35 -> 0 | E37: =E17+E26+E35 -> 105409.35 | F37: =F17+F26+F35 -> 0 | G37: =G17+G26+G35 -> 0 | H37: =H17+H26+H35 -> 0 | I37: =I17+I26+I35 -> 184466.36 | J37: =J17+J26+J35 -> 0 | ... AJ37: =AJ17+AJ26+AJ35 -> 737865.45 | AK37: =AVERAGE(AE37,AJ37)/AVERAGE($AE$58,$AJ$58) -> 0.96868286
B38: Retail Revenue:
B39: Twin Package Orders | C39: =IF(C$5<Assumptions!$B$106,0,INDEX(Assumptions!$B$108:$B$112,MATCH('Cash flow forecast'!$B39,Assumptions!$A$108:$A$112,0))*(INDEX(Assumptions!$C$4:$C$46,MATCH("Total Twin",Assumptions!$A$4:$A$46,0))*(1+INDEX(Assumptions!$E$108:$E$112,MATCH('Cash flow forecast'!$B39,Assumptions!$A$108:$A$112,0))))) -> 0 | D39: =IF(D$5<Assumptions!$B$106,0,IF('Cash flow forecast'!D$5=Assumptions!$B$106,INDEX(Assumptions!$B$108:$B$112,MATCH('Cash flow forecast'!$B39,Assumptions!$A$108:$A$112,0))*(INDEX(Assumptions!$C$4:$C$46,MATCH("Total Twin",Assumptions!$A$4:$A$46,0))*(1+INDEX(Assumptions!$E$108:$E$112,MATCH('Cash flow forecast'!$B39,Assumptions!$A$108:$A$112,0)))),(C39*(1+INDEX(Assumptions!$C$108:$C$112,MATCH('Cash flow forecast'!$B39,Assumptions!$A$108:$A$112,0))/12))*(1+INDEX(Assumptions!$D$108:$D$112,MATCH('Cash flow forecast'!$B39,Assumptions!$A$108:$A$112,0))/12))) -> 0 | E39: =IF(E$5<Assumptions!$B$106,0,IF('Cash flow forecast'!E$5=Assumptions!$B$106,INDEX(Assumptions!$B$108:$B$112,MATCH('Cash flow forecast'!$B39,Assumptions!$A$108:$A$112,0))*(INDEX(Assumptions!$C$4:$C$46,MATCH("Total Twin",Assumptions!$A$4:$A$46,0))*(1+INDEX(Assumptions!$E$108:$E$112,MATCH('Cash flow forecast'!$B39,Assumptions!$A$108:$A$112,0)))),(D39*(1+INDEX(Assumptions!$C$108:$C$112,MATCH('Cash flow forecast'!$B39,Assumptions!$A$108:$A$112,0))/12))*(1+INDEX(Assumptions!$D$108:$D$112,MATCH('Cash flow forecast'!$B39,Assumptions!$A$108:$A$112,0))/12))) -> 0 | F39: =IF(F$5<Assumptions!$B$106,0,IF('Cash flow forecast'!F$5=Assumptions!$B$106,INDEX(Assumptions!$B$108:$B$112,MATCH('Cash flow forecast'!$B39,Assumptions!$A$108:$A$112,0))*(INDEX(Assumptions!$C$4:$C$46,MATCH("Total Twin",Assumptions!$A$4:$A$46,0))*(1+INDEX(Assumptions!$E$108:$E$112,MATCH('Cash flow forecast'!$B39,Assumptions!$A$108:$A$112,0)))),(E39*(1+INDEX(Assumptions!$C$108:$C$112,MATCH('Cash flow forecast'!$B39,Assumptions!$A$108:$A$112,0))/12))*(1+INDEX(Assumptions!$D$108:$D$112,MATCH('Cash flow forecast'!$B39,Assumptions!$A$108:$A$112,0))/12))) -> 164.43 | G39: =IF(G$5<Assumptions!$B$106,0,IF('Cash flow forecast'!G$5=Assumptions!$B$106,INDEX(Assumptions!$B$108:$B$112,MATCH('Cash flow forecast'!$B39,Assumptions!$A$108:$A$112,0))*(INDEX(Assumptions!$C$4:$C$46,MATCH("Total Twin",Assumptions!$A$4:$A$46,0))*(1+INDEX(Assumptions!$E$108:$E$112,MATCH('Cash flow forecast'!$B39,Assumptions!$A$108:$A$112,0)))),(F39*(1+INDEX(Assumptions!$C$108:$C$112,MATCH('Cash flow forecast'!$B39,Assumptions!$A$108:$A$112,0))/12))*(1+INDEX(Assumptions!$D$108:$D$112,MATCH('Cash flow forecast'!$B39,Assumptions!$A$108:$A$112,0))/12))) -> 165.52392 | H39: =IF(H$5<Assumptions!$B$106,0,IF('Cash flow forecast'!H$5=Assumptions!$B$106,INDEX(Assumptions!$B$108:$B$112,MATCH('Cash flow forecast'!$B39,Assumptions!$A$108:$A$112,0))*(INDEX(Assumptions!$C$4:$C$46,MATCH("Total Twin",Assumptions!$A$4:$A$46,0))*(1+INDEX(Assumptions!$E$108:$E$112,MATCH('Cash flow forecast'!$B39,Assumptions!$A$108:$A$112,0)))),(G39*(1+INDEX(Assumptions!$C$108:$C$112,MATCH('Cash flow forecast'!$B39,Assumptions!$A$108:$A$112,0))/12))*(1+INDEX(Assumptions!$D$108:$D$112,MATCH('Cash flow forecast'!$B39,Assumptions!$A$108:$A$112,0))/12))) -> 166.62511 | I39: =IF(I$5<Assumptions!$B$106,0,IF('Cash flow forecast'!I$5=Assumptions!$B$106,INDEX(Assumptions!$B$108:$B$112,MATCH('Cash flow forecast'!$B39,Assumptions!$A$108:$A$112,0))*(INDEX(Assumptions!$C$4:$C$46,MATCH("Total Twin",Assumptions!$A$4:$A$46,0))*(1+INDEX(Assumptions!$E$108:$E$112,MATCH('Cash flow forecast'!$B39,Assumptions!$A$108:$A$112,0)))),(H39*(1+INDEX(Assumptions!$C$108:$C$112,MATCH('Cash flow forecast'!$B39,Assumptions!$A$108:$A$112,0))/12))*(1+INDEX(Assumptions!$D$108:$D$112,MATCH('Cash flow forecast'!$B39,Assumptions!$A$108:$A$112,0))/12))) -> 167.73363 | J39: =IF(J$5<Assumptions!$B$106,0,IF('Cash flow forecast'!J$5=Assumptions!$B$106,INDEX(Assumptions!$B$108:$B$112,MATCH('Cash flow forecast'!$B39,Assumptions!$A$108:$A$112,0))*(INDEX(Assumptions!$C$4:$C$46,MATCH("Total Twin",Assumptions!$A$4:$A$46,0))*(1+INDEX(Assumptions!$E$108:$E$112,MATCH('Cash flow forecast'!$B39,Assumptions!$A$108:$A$112,0)))),(I39*(1+INDEX(Assumptions!$C$108:$C$112,MATCH('Cash flow forecast'!$B39,Assumptions!$A$108:$A$112,0))/12))*(1+INDEX(Assumptions!$D$108:$D$112,MATCH('Cash flow forecast'!$B39,Assumptions!$A$108:$A$112,0))/12))) -> 168.84952 | K39: =IF(K$5<Assumptions!$B$106,0,IF('Cash flow forecast'!K$5=Assumptions!$B$106,INDEX(Assumptions!$B$108:$B$112,MATCH('Cash flow forecast'!$B39,Assumptions!$A$108:$A$112,0))*(INDEX(Assumptions!$C$4:$C$46,MATCH("Total Twin",Assumptions!$A$4:$A$46,0))*(1+INDEX(Assumptions!$E$108:$E$112,MATCH('Cash flow forecast'!$B39,Assumptions!$A$108:$A$112,0)))),(J39*(1+INDEX(Assumptions!$C$108:$C$112,MATCH('Cash flow forecast'!$B39,Assumptions!$A$108:$A$112,0))/12))*(1+INDEX(Assumptions!$D$108:$D$112,MATCH('Cash flow forecast'!$B39,Assumptions!$A$108:$A$112,0))/12))) -> 169.97284 | ... Z39: =IF(Z$5<Assumptions!$B$106,0,IF('Cash flow forecast'!Z$5=Assumptions!$B$106,INDEX(Assumptions!$B$108:$B$112,MATCH('Cash flow forecast'!$B39,Assumptions!$A$108:$A$112,0))*(INDEX(Assumptions!$C$4:$C$46,MATCH("Total Twin",Assumptions!$A$4:$A$46,0))*(1+INDEX(Assumptions!$E$108:$E$112,MATCH('Cash flow forecast'!$B39,Assumptions!$A$108:$A$112,0)))),(Y39*(1+INDEX(Assumptions!$C$108:$C$112,MATCH('Cash flow forecast'!$B39,Assumptions!$A$108:$A$112,0))/12))*(1+INDEX(Assumptions!$D$108:$D$112,MATCH('Cash flow forecast'!$B39,Assumptions!$A$108:$A$112,0))/12))) -> 187.74785 | AA39: =SUMIFS($C39:$N39,$C$6:$N$6,AA$5) -> 345.62979 | AB39: =SUMIFS($C39:$N39,$C$6:$N$6,AB$5) -> 164.43 | AC39: =SUMIFS($C39:$N39,$C$6:$N$6,AC$5) -> 499.88266 | AD39: =SUMIFS($C39:$N39,$C$6:$N$6,AD$5) -> 509.926 | AE39: =SUM($C39:$N39) -> 1519.8684 | AF39: =SUMIFS($O39:$Z39,$O$6:$Z$6,AF$5) -> 548.79627 | AG39: =SUMIFS($O39:$Z39,$O$6:$Z$6,AG$5) -> 530.6221 | AH39: =SUMIFS($O39:$Z39,$O$6:$Z$6,AH$5) -> 541.28305 | AI39: =SUMIFS($O39:$Z39,$O$6:$Z$6,AI$5) -> 552.15818 | AJ39: =SUM($O39:$Z39) -> 2172.8596 | AK39: =AVERAGE(AE39,AJ39)/AVERAGE($AE$58,$AJ$58) -> 0.0026732286
B40: Full Package Orders | C40: =IF(C$5<Assumptions!$B$106,0,INDEX(Assumptions!$B$108:$B$112,MATCH('Cash flow forecast'!$B40,Assumptions!$A$108:$A$112,0))*(INDEX(Assumptions!$C$4:$C$46,MATCH("Total Full",Assumptions!$A$4:$A$46,0))*(1+INDEX(Assumptions!$E$108:$E$112,MATCH('Cash flow forecast'!$B40,Assumptions!$A$108:$A$112,0))))) -> 0 | D40: =IF(D$5<Assumptions!$B$106,0,IF('Cash flow forecast'!D$5=Assumptions!$B$106,INDEX(Assumptions!$B$108:$B$112,MATCH('Cash flow forecast'!$B40,Assumptions!$A$108:$A$112,0))*(INDEX(Assumptions!$C$4:$C$46,MATCH("Total Full",Assumptions!$A$4:$A$46,0))*(1+INDEX(Assumptions!$E$108:$E$112,MATCH('Cash flow forecast'!$B40,Assumptions!$A$108:$A$112,0)))),(C40*(1+INDEX(Assumptions!$C$108:$C$112,MATCH('Cash flow forecast'!$B40,Assumptions!$A$108:$A$112,0))/12))*(1+INDEX(Assumptions!$D$108:$D$112,MATCH('Cash flow forecast'!$B40,Assumptions!$A$108:$A$112,0))/12))) -> 0 | E40: =IF(E$5<Assumptions!$B$106,0,IF('Cash flow forecast'!E$5=Assumptions!$B$106,INDEX(Assumptions!$B$108:$B$112,MATCH('Cash flow forecast'!$B40,Assumptions!$A$108:$A$112,0))*(INDEX(Assumptions!$C$4:$C$46,MATCH("Total Full",Assumptions!$A$4:$A$46,0))*(1+INDEX(Assumptions!$E$108:$E$112,MATCH('Cash flow forecast'!$B40,Assumptions!$A$108:$A$112,0)))),(D40*(1+INDEX(Assumptions!$C$108:$C$112,MATCH('Cash flow forecast'!$B40,Assumptions!$A$108:$A$112,0))/12))*(1+INDEX(Assumptions!$D$108:$D$112,MATCH('Cash flow forecast'!$B40,Assumptions!$A$108:$A$112,0))/12))) -> 0 | F40: =IF(F$5<Assumptions!$B$106,0,IF('Cash flow forecast'!F$5=Assumptions!$B$106,INDEX(Assumptions!$B$108:$B$112,MATCH('Cash flow forecast'!$B40,Assumptions!$A$108:$A$112,0))*(INDEX(Assumptions!$C$4:$C$46,MATCH("Total Full",Assumptions!$A$4:$A$46,0))*(1+INDEX(Assumptions!$E$108:$E$112,MATCH('Cash flow forecast'!$B40,Assumptions!$A$108:$A$112,0)))),(E40*(1+INDEX(Assumptions!$C$108:$C$112,MATCH('Cash flow forecast'!$B40,Assumptions!$A$108:$A$112,0))/12))*(1+INDEX(Assumptions!$D$108:$D$112,MATCH('Cash flow forecast'!$B40,Assumptions!$A$108:$A$112,0))/12))) -> 136.26 | G40: =IF(G$5<Assumptions!$B$106,0,IF('Cash flow forecast'!G$5=Assumptions!$B$106,INDEX(Assumptions!$B$108:$B$112,MATCH('Cash flow forecast'!$B40,Assumptions!$A$108:$A$112,0))*(INDEX(Assumptions!$C$4:$C$46,MATCH("Total Full",Assumptions!$A$4:$A$46,0))*(1+INDEX(Assumptions!$E$108:$E$112,MATCH('Cash flow forecast'!$B40,Assumptions!$A$108:$A$112,0)))),(F40*(1+INDEX(Assumptions!$C$108:$C$112,MATCH('Cash flow forecast'!$B40,Assumptions!$A$108:$A$112,0))/12))*(1+INDEX(Assumptions!$D$108:$D$112,MATCH('Cash flow forecast'!$B40,Assumptions!$A$108:$A$112,0))/12))) -> 136.5997 | H40: =IF(H$5<Assumptions!$B$106,0,IF('Cash flow forecast'!H$5=Assumptions!$B$106,INDEX(Assumptions!$B$108:$B$112,MATCH('Cash flow forecast'!$B40,Assumptions!$A$108:$A$112,0))*(INDEX(Assumptions!$C$4:$C$46,MATCH("Total Full",Assumptions!$A$4:$A$46,0))*(1+INDEX(Assumptions!$E$108:$E$112,MATCH('Cash flow forecast'!$B40,Assumptions!$A$108:$A$112,0)))),(G40*(1+INDEX(Assumptions!$C$108:$C$112,MATCH('Cash flow forecast'!$B40,Assumptions!$A$108:$A$112,0))/12))*(1+INDEX(Assumptions!$D$108:$D$112,MATCH('Cash flow forecast'!$B40,Assumptions!$A$108:$A$112,0))/12))) -> 136.94025 | I40: =IF(I$5<Assumptions!$B$106,0,IF('Cash flow forecast'!I$5=Assumptions!$B$106,INDEX(Assumptions!$B$108:$B$112,MATCH('Cash flow forecast'!$B40,Assumptions!$A$108:$A$112,0))*(INDEX(Assumptions!$C$4:$C$46,MATCH("Total Full",Assumptions!$A$4:$A$46,0))*(1+INDEX(Assumptions!$E$108:$E$112,MATCH('Cash flow forecast'!$B40,Assumptions!$A$108:$A$112,0)))),(H40*(1+INDEX(Assumptions!$C$108:$C$112,MATCH('Cash flow forecast'!$B40,Assumptions!$A$108:$A$112,0))/12))*(1+INDEX(Assumptions!$D$108:$D$112,MATCH('Cash flow forecast'!$B40,Assumptions!$A$108:$A$112,0))/12))) -> 137.28165 | J40: =IF(J$5<Assumptions!$B$106,0,IF('Cash flow forecast'!J$5=Assumptions!$B$106,INDEX(Assumptions!$B$108:$B$112,MATCH('Cash flow forecast'!$B40,Assumptions!$A$108:$A$112,0))*(INDEX(Assumptions!$C$4:$C$46,MATCH("Total Full",Assumptions!$A$4:$A$46,0))*(1+INDEX(Assumptions!$E$108:$E$112,MATCH('Cash flow forecast'!$B40,Assumptions!$A$108:$A$112,0)))),(I40*(1+INDEX(Assumptions!$C$108:$C$112,MATCH('Cash flow forecast'!$B40,Assumptions!$A$108:$A$112,0))/12))*(1+INDEX(Assumptions!$D$108:$D$112,MATCH('Cash flow forecast'!$B40,Assumptions!$A$108:$A$112,0))/12))) -> 137.6239 | K40: =IF(K$5<Assumptions!$B$106,0,IF('Cash flow forecast'!K$5=Assumptions!$B$106,INDEX(Assumptions!$B$108:$B$112,MATCH('Cash flow forecast'!$B40,Assumptions!$A$108:$A$112,0))*(INDEX(Assumptions!$C$4:$C$46,MATCH("Total Full",Assumptions!$A$4:$A$46,0))*(1+INDEX(Assumptions!$E$108:$E$112,MATCH('Cash flow forecast'!$B40,Assumptions!$A$108:$A$112,0)))),(J40*(1+INDEX(Assumptions!$C$108:$C$112,MATCH('Cash flow forecast'!$B40,Assumptions!$A$108:$A$112,0))/12))*(1+INDEX(Assumptions!$D$108:$D$112,MATCH('Cash flow forecast'!$B40,Assumptions!$A$108:$A$112,0))/12))) -> 137.96701 | ... Z40: =IF(Z$5<Assumptions!$B$106,0,IF('Cash flow forecast'!Z$5=Assumptions!$B$106,INDEX(Assumptions!$B$108:$B$112,MATCH('Cash flow forecast'!$B40,Assumptions!$A$108:$A$112,0))*(INDEX(Assumptions!$C$4:$C$46,MATCH("Total Full",Assumptions!$A$4:$A$46,0))*(1+INDEX(Assumptions!$E$108:$E$112,MATCH('Cash flow forecast'!$B40,Assumptions!$A$108:$A$112,0)))),(Y40*(1+INDEX(Assumptions!$C$108:$C$112,MATCH('Cash flow forecast'!$B40,Assumptions!$A$108:$A$112,0))/12))*(1+INDEX(Assumptions!$D$108:$D$112,MATCH('Cash flow forecast'!$B40,Assumptions!$A$108:$A$112,0))/12))) -> 143.21742 | AA40: =SUMIFS($C40:$N40,$C$6:$N$6,AA$5) -> 277.65725 | AB40: =SUMIFS($C40:$N40,$C$6:$N$6,AB$5) -> 136.26 | AC40: =SUMIFS($C40:$N40,$C$6:$N$6,AC$5) -> 410.82161 | AD40: =SUMIFS($C40:$N40,$C$6:$N$6,AD$5) -> 413.90188 | AE40: =SUM($C40:$N40) -> 1238.6407 | AF40: =SUMIFS($O40:$Z40,$O$6:$Z$6,AF$5) -> 425.42668 | AG40: =SUMIFS($O40:$Z40,$O$6:$Z$6,AG$5) -> 420.13188 | AH40: =SUMIFS($O40:$Z40,$O$6:$Z$6,AH$5) -> 423.28196 | AI40: =SUMIFS($O40:$Z40,$O$6:$Z$6,AI$5) -> 426.45565 | AJ40: =SUM($O40:$Z40) -> 1695.2962 | AK40: =AVERAGE(AE40,AJ40)/AVERAGE($AE$58,$AJ$58) -> 0.0021239268
B41: Queen Package Orders | C41: =IF(C$5<Assumptions!$B$106,0,INDEX(Assumptions!$B$108:$B$112,MATCH('Cash flow forecast'!$B41,Assumptions!$A$108:$A$112,0))*(INDEX(Assumptions!$C$4:$C$46,MATCH("Total Queen",Assumptions!$A$4:$A$46,0))*(1+INDEX(Assumptions!$E$108:$E$112,MATCH('Cash flow forecast'!$B41,Assumptions!$A$108:$A$112,0))))) -> 0 | D41: =IF(D$5<Assumptions!$B$106,0,IF('Cash flow forecast'!D$5=Assumptions!$B$106,INDEX(Assumptions!$B$108:$B$112,MATCH('Cash flow forecast'!$B41,Assumptions!$A$108:$A$112,0))*(INDEX(Assumptions!$C$4:$C$46,MATCH("Total Queen",Assumptions!$A$4:$A$46,0))*(1+INDEX(Assumptions!$E$108:$E$112,MATCH('Cash flow forecast'!$B41,Assumptions!$A$108:$A$112,0)))),(C41*(1+INDEX(Assumptions!$C$108:$C$112,MATCH('Cash flow forecast'!$B41,Assumptions!$A$108:$A$112,0))/12))*(1+INDEX(Assumptions!$D$108:$D$112,MATCH('Cash flow forecast'!$B41,Assumptions!$A$108:$A$112,0))/12))) -> 0 | E41: =IF(E$5<Assumptions!$B$106,0,IF('Cash flow forecast'!E$5=Assumptions!$B$106,INDEX(Assumptions!$B$108:$B$112,MATCH('Cash flow forecast'!$B41,Assumptions!$A$108:$A$112,0))*(INDEX(Assumptions!$C$4:$C$46,MATCH("Total Queen",Assumptions!$A$4:$A$46,0))*(1+INDEX(Assumptions!$E$108:$E$112,MATCH('Cash flow forecast'!$B41,Assumptions!$A$108:$A$112,0)))),(D41*(1+INDEX(Assumptions!$C$108:$C$112,MATCH('Cash flow forecast'!$B41,Assumptions!$A$108:$A$112,0))/12))*(1+INDEX(Assumptions!$D$108:$D$112,MATCH('Cash flow forecast'!$B41,Assumptions!$A$108:$A$112,0))/12))) -> 0 | F41: =IF(F$5<Assumptions!$B$106,0,IF('Cash flow forecast'!F$5=Assumptions!$B$106,INDEX(Assumptions!$B$108:$B$112,MATCH('Cash flow forecast'!$B41,Assumptions!$A$108:$A$112,0))*(INDEX(Assumptions!$C$4:$C$46,MATCH("Total Queen",Assumptions!$A$4:$A$46,0))*(1+INDEX(Assumptions!$E$108:$E$112,MATCH('Cash flow forecast'!$B41,Assumptions!$A$108:$A$112,0)))),(E41*(1+INDEX(Assumptions!$C$108:$C$112,MATCH('Cash flow forecast'!$B41,Assumptions!$A$108:$A$112,0))/12))*(1+INDEX(Assumptions!$D$108:$D$112,MATCH('Cash flow forecast'!$B41,Assumptions!$A$108:$A$112,0))/12))) -> 234 | G41: =IF(G$5<Assumptions!$B$106,0,IF('Cash flow forecast'!G$5=Assumptions!$B$106,INDEX(Assumptions!$B$108:$B$112,MATCH('Cash flow forecast'!$B41,Assumptions!$A$108:$A$112,0))*(INDEX(Assumptions!$C$4:$C$46,MATCH("Total Queen",Assumptions!$A$4:$A$46,0))*(1+INDEX(Assumptions!$E$108:$E$112,MATCH('Cash flow forecast'!$B41,Assumptions!$A$108:$A$112,0)))),(F41*(1+INDEX(Assumptions!$C$108:$C$112,MATCH('Cash flow forecast'!$B41,Assumptions!$A$108:$A$112,0))/12))*(1+INDEX(Assumptions!$D$108:$D$112,MATCH('Cash flow forecast'!$B41,Assumptions!$A$108:$A$112,0))/12))) -> 234.58338 | H41: =IF(H$5<Assumptions!$B$106,0,IF('Cash flow forecast'!H$5=Assumptions!$B$106,INDEX(Assumptions!$B$108:$B$112,MATCH('Cash flow forecast'!$B41,Assumptions!$A$108:$A$112,0))*(INDEX(Assumptions!$C$4:$C$46,MATCH("Total Queen",Assumptions!$A$4:$A$46,0))*(1+INDEX(Assumptions!$E$108:$E$112,MATCH('Cash flow forecast'!$B41,Assumptions!$A$108:$A$112,0)))),(G41*(1+INDEX(Assumptions!$C$108:$C$112,MATCH('Cash flow forecast'!$B41,Assumptions!$A$108:$A$112,0))/12))*(1+INDEX(Assumptions!$D$108:$D$112,MATCH('Cash flow forecast'!$B41,Assumptions!$A$108:$A$112,0))/12))) -> 235.1682 | I41: =IF(I$5<Assumptions!$B$106,0,IF('Cash flow forecast'!I$5=Assumptions!$B$106,INDEX(Assumptions!$B$108:$B$112,MATCH('Cash flow forecast'!$B41,Assumptions!$A$108:$A$112,0))*(INDEX(Assumptions!$C$4:$C$46,MATCH("Total Queen",Assumptions!$A$4:$A$46,0))*(1+INDEX(Assumptions!$E$108:$E$112,MATCH('Cash flow forecast'!$B41,Assumptions!$A$108:$A$112,0)))),(H41*(1+INDEX(Assumptions!$C$108:$C$112,MATCH('Cash flow forecast'!$B41,Assumptions!$A$108:$A$112,0))/12))*(1+INDEX(Assumptions!$D$108:$D$112,MATCH('Cash flow forecast'!$B41,Assumptions!$A$108:$A$112,0))/12))) -> 235.75449 | J41: =IF(J$5<Assumptions!$B$106,0,IF('Cash flow forecast'!J$5=Assumptions!$B$106,INDEX(Assumptions!$B$108:$B$112,MATCH('Cash flow forecast'!$B41,Assumptions!$A$108:$A$112,0))*(INDEX(Assumptions!$C$4:$C$46,MATCH("Total Queen",Assumptions!$A$4:$A$46,0))*(1+INDEX(Assumptions!$E$108:$E$112,MATCH('Cash flow forecast'!$B41,Assumptions!$A$108:$A$112,0)))),(I41*(1+INDEX(Assumptions!$C$108:$C$112,MATCH('Cash flow forecast'!$B41,Assumptions!$A$108:$A$112,0))/12))*(1+INDEX(Assumptions!$D$108:$D$112,MATCH('Cash flow forecast'!$B41,Assumptions!$A$108:$A$112,0))/12))) -> 236.34224 | K41: =IF(K$5<Assumptions!$B$106,0,IF('Cash flow forecast'!K$5=Assumptions!$B$106,INDEX(Assumptions!$B$108:$B$112,MATCH('Cash flow forecast'!$B41,Assumptions!$A$108:$A$112,0))*(INDEX(Assumptions!$C$4:$C$46,MATCH("Total Queen",Assumptions!$A$4:$A$46,0))*(1+INDEX(Assumptions!$E$108:$E$112,MATCH('Cash flow forecast'!$B41,Assumptions!$A$108:$A$112,0)))),(J41*(1+INDEX(Assumptions!$C$108:$C$112,MATCH('Cash flow forecast'!$B41,Assumptions!$A$108:$A$112,0))/12))*(1+INDEX(Assumptions!$D$108:$D$112,MATCH('Cash flow forecast'!$B41,Assumptions!$A$108:$A$112,0))/12))) -> 236.93146 | ... Z41: =IF(Z$5<Assumptions!$B$106,0,IF('Cash flow forecast'!Z$5=Assumptions!$B$106,INDEX(Assumptions!$B$108:$B$112,MATCH('Cash flow forecast'!$B41,Assumptions!$A$108:$A$112,0))*(INDEX(Assumptions!$C$4:$C$46,MATCH("Total Queen",Assumptions!$A$4:$A$46,0))*(1+INDEX(Assumptions!$E$108:$E$112,MATCH('Cash flow forecast'!$B41,Assumptions!$A$108:$A$112,0)))),(Y41*(1+INDEX(Assumptions!$C$108:$C$112,MATCH('Cash flow forecast'!$B41,Assumptions!$A$108:$A$112,0))/12))*(1+INDEX(Assumptions!$D$108:$D$112,MATCH('Cash flow forecast'!$B41,Assumptions!$A$108:$A$112,0))/12))) -> 245.94801 | AA41: =SUMIFS($C41:$N41,$C$6:$N$6,AA$5) -> 476.82222 | AB41: =SUMIFS($C41:$N41,$C$6:$N$6,AB$5) -> 234 | AC41: =SUMIFS($C41:$N41,$C$6:$N$6,AC$5) -> 705.50607 | AD41: =SUMIFS($C41:$N41,$C$6:$N$6,AD$5) -> 710.79583 | AE41: =SUM($C41:$N41) -> 2127.1241 | AF41: =SUMIFS($O41:$Z41,$O$6:$Z$6,AF$5) -> 730.58742 | AG41: =SUMIFS($O41:$Z41,$O$6:$Z$6,AG$5) -> 721.49464 | AH41: =SUMIFS($O41:$Z41,$O$6:$Z$6,AH$5) -> 726.90429 | AI41: =SUMIFS($O41:$Z41,$O$6:$Z$6,AI$5) -> 732.35449 | AJ41: =SUM($O41:$Z41) -> 2911.3408 | AK41: =AVERAGE(AE41,AJ41)/AVERAGE($AE$58,$AJ$58) -> 0.0036474305
B42: King Package Orders | C42: =IF(C$5<Assumptions!$B$106,0,INDEX(Assumptions!$B$108:$B$112,MATCH('Cash flow forecast'!$B42,Assumptions!$A$108:$A$112,0))*(INDEX(Assumptions!$C$4:$C$46,MATCH("Total King",Assumptions!$A$4:$A$46,0))*(1+INDEX(Assumptions!$E$108:$E$112,MATCH('Cash flow forecast'!$B42,Assumptions!$A$108:$A$112,0))))) -> 0 | D42: =IF(D$5<Assumptions!$B$106,0,IF('Cash flow forecast'!D$5=Assumptions!$B$106,INDEX(Assumptions!$B$108:$B$112,MATCH('Cash flow forecast'!$B42,Assumptions!$A$108:$A$112,0))*(INDEX(Assumptions!$C$4:$C$46,MATCH("Total King",Assumptions!$A$4:$A$46,0))*(1+INDEX(Assumptions!$E$108:$E$112,MATCH('Cash flow forecast'!$B42,Assumptions!$A$108:$A$112,0)))),(C42*(1+INDEX(Assumptions!$C$108:$C$112,MATCH('Cash flow forecast'!$B42,Assumptions!$A$108:$A$112,0))/12))*(1+INDEX(Assumptions!$D$108:$D$112,MATCH('Cash flow forecast'!$B42,Assumptions!$A$108:$A$112,0))/12))) -> 0 | E42: =IF(E$5<Assumptions!$B$106,0,IF('Cash flow forecast'!E$5=Assumptions!$B$106,INDEX(Assumptions!$B$108:$B$112,MATCH('Cash flow forecast'!$B42,Assumptions!$A$108:$A$112,0))*(INDEX(Assumptions!$C$4:$C$46,MATCH("Total King",Assumptions!$A$4:$A$46,0))*(1+INDEX(Assumptions!$E$108:$E$112,MATCH('Cash flow forecast'!$B42,Assumptions!$A$108:$A$112,0)))),(D42*(1+INDEX(Assumptions!$C$108:$C$112,MATCH('Cash flow forecast'!$B42,Assumptions!$A$108:$A$112,0))/12))*(1+INDEX(Assumptions!$D$108:$D$112,MATCH('Cash flow forecast'!$B42,Assumptions!$A$108:$A$112,0))/12))) -> 0 | F42: =IF(F$5<Assumptions!$B$106,0,IF('Cash flow forecast'!F$5=Assumptions!$B$106,INDEX(Assumptions!$B$108:$B$112,MATCH('Cash flow forecast'!$B42,Assumptions!$A$108:$A$112,0))*(INDEX(Assumptions!$C$4:$C$46,MATCH("Total King",Assumptions!$A$4:$A$46,0))*(1+INDEX(Assumptions!$E$108:$E$112,MATCH('Cash flow forecast'!$B42,Assumptions!$A$108:$A$112,0)))),(E42*(1+INDEX(Assumptions!$C$108:$C$112,MATCH('Cash flow forecast'!$B42,Assumptions!$A$108:$A$112,0))/12))*(1+INDEX(Assumptions!$D$108:$D$112,MATCH('Cash flow forecast'!$B42,Assumptions!$A$108:$A$112,0))/12))) -> 306 | G42: =IF(G$5<Assumptions!$B$106,0,IF('Cash flow forecast'!G$5=Assumptions!$B$106,INDEX(Assumptions!$B$108:$B$112,MATCH('Cash flow forecast'!$B42,Assumptions!$A$108:$A$112,0))*(INDEX(Assumptions!$C$4:$C$46,MATCH("Total King",Assumptions!$A$4:$A$46,0))*(1+INDEX(Assumptions!$E$108:$E$112,MATCH('Cash flow forecast'!$B42,Assumptions!$A$108:$A$112,0)))),(F42*(1+INDEX(Assumptions!$C$108:$C$112,MATCH('Cash flow forecast'!$B42,Assumptions!$A$108:$A$112,0))/12))*(1+INDEX(Assumptions!$D$108:$D$112,MATCH('Cash flow forecast'!$B42,Assumptions!$A$108:$A$112,0))/12))) -> 306.76287 | H42: =IF(H$5<Assumptions!$B$106,0,IF('Cash flow forecast'!H$5=Assumptions!$B$106,INDEX(Assumptions!$B$108:$B$112,MATCH('Cash flow forecast'!$B42,Assumptions!$A$108:$A$112,0))*(INDEX(Assumptions!$C$4:$C$46,MATCH("Total King",Assumptions!$A$4:$A$46,0))*(1+INDEX(Assumptions!$E$108:$E$112,MATCH('Cash flow forecast'!$B42,Assumptions!$A$108:$A$112,0)))),(G42*(1+INDEX(Assumptions!$C$108:$C$112,MATCH('Cash flow forecast'!$B42,Assumptions!$A$108:$A$112,0))/12))*(1+INDEX(Assumptions!$D$108:$D$112,MATCH('Cash flow forecast'!$B42,Assumptions!$A$108:$A$112,0))/12))) -> 307.52765 | I42: =IF(I$5<Assumptions!$B$106,0,IF('Cash flow forecast'!I$5=Assumptions!$B$106,INDEX(Assumptions!$B$108:$B$112,MATCH('Cash flow forecast'!$B42,Assumptions!$A$108:$A$112,0))*(INDEX(Assumptions!$C$4:$C$46,MATCH("Total King",Assumptions!$A$4:$A$46,0))*(1+INDEX(Assumptions!$E$108:$E$112,MATCH('Cash flow forecast'!$B42,Assumptions!$A$108:$A$112,0)))),(H42*(1+INDEX(Assumptions!$C$108:$C$112,MATCH('Cash flow forecast'!$B42,Assumptions!$A$108:$A$112,0))/12))*(1+INDEX(Assumptions!$D$108:$D$112,MATCH('Cash flow forecast'!$B42,Assumptions!$A$108:$A$112,0))/12))) -> 308.29434 | J42: =IF(J$5<Assumptions!$B$106,0,IF('Cash flow forecast'!J$5=Assumptions!$B$106,INDEX(Assumptions!$B$108:$B$112,MATCH('Cash flow forecast'!$B42,Assumptions!$A$108:$A$112,0))*(INDEX(Assumptions!$C$4:$C$46,MATCH("Total King",Assumptions!$A$4:$A$46,0))*(1+INDEX(Assumptions!$E$108:$E$112,MATCH('Cash flow forecast'!$B42,Assumptions!$A$108:$A$112,0)))),(I42*(1+INDEX(Assumptions!$C$108:$C$112,MATCH('Cash flow forecast'!$B42,Assumptions!$A$108:$A$112,0))/12))*(1+INDEX(Assumptions!$D$108:$D$112,MATCH('Cash flow forecast'!$B42,Assumptions!$A$108:$A$112,0))/12))) -> 309.06293 | K42: =IF(K$5<Assumptions!$B$106,0,IF('Cash flow forecast'!K$5=Assumptions!$B$106,INDEX(Assumptions!$B$108:$B$112,MATCH('Cash flow forecast'!$B42,Assumptions!$A$108:$A$112,0))*(INDEX(Assumptions!$C$4:$C$46,MATCH("Total King",Assumptions!$A$4:$A$46,0))*(1+INDEX(Assumptions!$E$108:$E$112,MATCH('Cash flow forecast'!$B42,Assumptions!$A$108:$A$112,0)))),(J42*(1+INDEX(Assumptions!$C$108:$C$112,MATCH('Cash flow forecast'!$B42,Assumptions!$A$108:$A$112,0))/12))*(1+INDEX(Assumptions!$D$108:$D$112,MATCH('Cash flow forecast'!$B42,Assumptions!$A$108:$A$112,0))/12))) -> 309.83344 | ... Z42: =IF(Z$5<Assumptions!$B$106,0,IF('Cash flow forecast'!Z$5=Assumptions!$B$106,INDEX(Assumptions!$B$108:$B$112,MATCH('Cash flow forecast'!$B42,Assumptions!$A$108:$A$112,0))*(INDEX(Assumptions!$C$4:$C$46,MATCH("Total King",Assumptions!$A$4:$A$46,0))*(1+INDEX(Assumptions!$E$108:$E$112,MATCH('Cash flow forecast'!$B42,Assumptions!$A$108:$A$112,0)))),(Y42*(1+INDEX(Assumptions!$C$108:$C$112,MATCH('Cash flow forecast'!$B42,Assumptions!$A$108:$A$112,0))/12))*(1+INDEX(Assumptions!$D$108:$D$112,MATCH('Cash flow forecast'!$B42,Assumptions!$A$108:$A$112,0))/12))) -> 321.62432 | AA42: =SUMIFS($C42:$N42,$C$6:$N$6,AA$5) -> 623.53675 | AB42: =SUMIFS($C42:$N42,$C$6:$N$6,AB$5) -> 306 | AC42: =SUMIFS($C42:$N42,$C$6:$N$6,AC$5) -> 922.58486 | AD42: =SUMIFS($C42:$N42,$C$6:$N$6,AD$5) -> 929.50225 | AE42: =SUM($C42:$N42) -> 2781.6239 | AF42: =SUMIFS($O42:$Z42,$O$6:$Z$6,AF$5) -> 955.38355 | AG42: =SUMIFS($O42:$Z42,$O$6:$Z$6,AG$5) -> 943.493 | AH42: =SUMIFS($O42:$Z42,$O$6:$Z$6,AH$5) -> 950.56714 | AI42: =SUMIFS($O42:$Z42,$O$6:$Z$6,AI$5) -> 957.69433 | AJ42: =SUM($O42:$Z42) -> 3807.138 | AK42: =AVERAGE(AE42,AJ42)/AVERAGE($AE$58,$AJ$58) -> 0.0047697168
B43: Universal Package Orders | C43: =IF(C$5<Assumptions!$B$106,0,INDEX(Assumptions!$B$108:$B$112,MATCH('Cash flow forecast'!$B43,Assumptions!$A$108:$A$112,0))*(INDEX(Assumptions!$C$4:$C$46,MATCH("Total Universal",Assumptions!$A$4:$A$46,0))*(1+INDEX(Assumptions!$E$108:$E$112,MATCH('Cash flow forecast'!$B43,Assumptions!$A$108:$A$112,0))))) -> 0 | D43: =IF(D$5<Assumptions!$B$106,0,IF('Cash flow forecast'!D$5=Assumptions!$B$106,INDEX(Assumptions!$B$108:$B$112,MATCH('Cash flow forecast'!$B43,Assumptions!$A$108:$A$112,0))*(INDEX(Assumptions!$C$4:$C$46,MATCH("Total Universal",Assumptions!$A$4:$A$46,0))*(1+INDEX(Assumptions!$E$108:$E$112,MATCH('Cash flow forecast'!$B43,Assumptions!$A$108:$A$112,0)))),(C43*(1+INDEX(Assumptions!$C$108:$C$112,MATCH('Cash flow forecast'!$B43,Assumptions!$A$108:$A$112,0))/12))*(1+INDEX(Assumptions!$D$108:$D$112,MATCH('Cash flow forecast'!$B43,Assumptions!$A$108:$A$112,0))/12))) -> 0 | E43: =IF(E$5<Assumptions!$B$106,0,IF('Cash flow forecast'!E$5=Assumptions!$B$106,INDEX(Assumptions!$B$108:$B$112,MATCH('Cash flow forecast'!$B43,Assumptions!$A$108:$A$112,0))*(INDEX(Assumptions!$C$4:$C$46,MATCH("Total Universal",Assumptions!$A$4:$A$46,0))*(1+INDEX(Assumptions!$E$108:$E$112,MATCH('Cash flow forecast'!$B43,Assumptions!$A$108:$A$112,0)))),(D43*(1+INDEX(Assumptions!$C$108:$C$112,MATCH('Cash flow forecast'!$B43,Assumptions!$A$108:$A$112,0))/12))*(1+INDEX(Assumptions!$D$108:$D$112,MATCH('Cash flow forecast'!$B43,Assumptions!$A$108:$A$112,0))/12))) -> 0 | F43: =IF(F$5<Assumptions!$B$106,0,IF('Cash flow forecast'!F$5=Assumptions!$B$106,INDEX(Assumptions!$B$108:$B$112,MATCH('Cash flow forecast'!$B43,Assumptions!$A$108:$A$112,0))*(INDEX(Assumptions!$C$4:$C$46,MATCH("Total Universal",Assumptions!$A$4:$A$46,0))*(1+INDEX(Assumptions!$E$108:$E$112,MATCH('Cash flow forecast'!$B43,Assumptions!$A$108:$A$112,0)))),(E43*(1+INDEX(Assumptions!$C$108:$C$112,MATCH('Cash flow forecast'!$B43,Assumptions!$A$108:$A$112,0))/12))*(1+INDEX(Assumptions!$D$108:$D$112,MATCH('Cash flow forecast'!$B43,Assumptions!$A$108:$A$112,0))/12))) -> 78.39 | G43: =IF(G$5<Assumptions!$B$106,0,IF('Cash flow forecast'!G$5=Assumptions!$B$106,INDEX(Assumptions!$B$108:$B$112,MATCH('Cash flow forecast'!$B43,Assumptions!$A$108:$A$112,0))*(INDEX(Assumptions!$C$4:$C$46,MATCH("Total Universal",Assumptions!$A$4:$A$46,0))*(1+INDEX(Assumptions!$E$108:$E$112,MATCH('Cash flow forecast'!$B43,Assumptions!$A$108:$A$112,0)))),(F43*(1+INDEX(Assumptions!$C$108:$C$112,MATCH('Cash flow forecast'!$B43,Assumptions!$A$108:$A$112,0))/12))*(1+INDEX(Assumptions!$D$108:$D$112,MATCH('Cash flow forecast'!$B43,Assumptions!$A$108:$A$112,0))/12))) -> 78.585431 | H43: =IF(H$5<Assumptions!$B$106,0,IF('Cash flow forecast'!H$5=Assumptions!$B$106,INDEX(Assumptions!$B$108:$B$112,MATCH('Cash flow forecast'!$B43,Assumptions!$A$108:$A$112,0))*(INDEX(Assumptions!$C$4:$C$46,MATCH("Total Universal",Assumptions!$A$4:$A$46,0))*(1+INDEX(Assumptions!$E$108:$E$112,MATCH('Cash flow forecast'!$B43,Assumptions!$A$108:$A$112,0)))),(G43*(1+INDEX(Assumptions!$C$108:$C$112,MATCH('Cash flow forecast'!$B43,Assumptions!$A$108:$A$112,0))/12))*(1+INDEX(Assumptions!$D$108:$D$112,MATCH('Cash flow forecast'!$B43,Assumptions!$A$108:$A$112,0))/12))) -> 78.781348 | I43: =IF(I$5<Assumptions!$B$106,0,IF('Cash flow forecast'!I$5=Assumptions!$B$106,INDEX(Assumptions!$B$108:$B$112,MATCH('Cash flow forecast'!$B43,Assumptions!$A$108:$A$112,0))*(INDEX(Assumptions!$C$4:$C$46,MATCH("Total Universal",Assumptions!$A$4:$A$46,0))*(1+INDEX(Assumptions!$E$108:$E$112,MATCH('Cash flow forecast'!$B43,Assumptions!$A$108:$A$112,0)))),(H43*(1+INDEX(Assumptions!$C$108:$C$112,MATCH('Cash flow forecast'!$B43,Assumptions!$A$108:$A$112,0))/12))*(1+INDEX(Assumptions!$D$108:$D$112,MATCH('Cash flow forecast'!$B43,Assumptions!$A$108:$A$112,0))/12))) -> 78.977755 | J43: =IF(J$5<Assumptions!$B$106,0,IF('Cash flow forecast'!J$5=Assumptions!$B$106,INDEX(Assumptions!$B$108:$B$112,MATCH('Cash flow forecast'!$B43,Assumptions!$A$108:$A$112,0))*(INDEX(Assumptions!$C$4:$C$46,MATCH("Total Universal",Assumptions!$A$4:$A$46,0))*(1+INDEX(Assumptions!$E$108:$E$112,MATCH('Cash flow forecast'!$B43,Assumptions!$A$108:$A$112,0)))),(I43*(1+INDEX(Assumptions!$C$108:$C$112,MATCH('Cash flow forecast'!$B43,Assumptions!$A$108:$A$112,0))/12))*(1+INDEX(Assumptions!$D$108:$D$112,MATCH('Cash flow forecast'!$B43,Assumptions!$A$108:$A$112,0))/12))) -> 79.174651 | K43: =IF(K$5<Assumptions!$B$106,0,IF('Cash flow forecast'!K$5=Assumptions!$B$106,INDEX(Assumptions!$B$108:$B$112,MATCH('Cash flow forecast'!$B43,Assumptions!$A$108:$A$112,0))*(INDEX(Assumptions!$C$4:$C$46,MATCH("Total Universal",Assumptions!$A$4:$A$46,0))*(1+INDEX(Assumptions!$E$108:$E$112,MATCH('Cash flow forecast'!$B43,Assumptions!$A$108:$A$112,0)))),(J43*(1+INDEX(Assumptions!$C$108:$C$112,MATCH('Cash flow forecast'!$B43,Assumptions!$A$108:$A$112,0))/12))*(1+INDEX(Assumptions!$D$108:$D$112,MATCH('Cash flow forecast'!$B43,Assumptions!$A$108:$A$112,0))/12))) -> 79.372037 | ... Z43: =IF(Z$5<Assumptions!$B$106,0,IF('Cash flow forecast'!Z$5=Assumptions!$B$106,INDEX(Assumptions!$B$108:$B$112,MATCH('Cash flow forecast'!$B43,Assumptions!$A$108:$A$112,0))*(INDEX(Assumptions!$C$4:$C$46,MATCH("Total Universal",Assumptions!$A$4:$A$46,0))*(1+INDEX(Assumptions!$E$108:$E$112,MATCH('Cash flow forecast'!$B43,Assumptions!$A$108:$A$112,0)))),(Y43*(1+INDEX(Assumptions!$C$108:$C$112,MATCH('Cash flow forecast'!$B43,Assumptions!$A$108:$A$112,0))/12))*(1+INDEX(Assumptions!$D$108:$D$112,MATCH('Cash flow forecast'!$B43,Assumptions!$A$108:$A$112,0))/12))) -> 82.392584 | AA43: =SUMIFS($C43:$N43,$C$6:$N$6,AA$5) -> 159.73544 | AB43: =SUMIFS($C43:$N43,$C$6:$N$6,AB$5) -> 78.39 | AC43: =SUMIFS($C43:$N43,$C$6:$N$6,AC$5) -> 236.34453 | AD43: =SUMIFS($C43:$N43,$C$6:$N$6,AD$5) -> 238.1166 | AE43: =SUM($C43:$N43) -> 712.58658 | AF43: =SUMIFS($O43:$Z43,$O$6:$Z$6,AF$5) -> 244.74679 | AG43: =SUMIFS($O43:$Z43,$O$6:$Z$6,AG$5) -> 241.70071 | AH43: =SUMIFS($O43:$Z43,$O$6:$Z$6,AH$5) -> 243.51294 | AI43: =SUMIFS($O43:$Z43,$O$6:$Z$6,AI$5) -> 245.33875 | AJ43: =SUM($O43:$Z43) -> 975.29918 | AK43: =AVERAGE(AE43,AJ43)/AVERAGE($AE$58,$AJ$58) -> 0.0012218892
B44: Total Retail Revenue | C44: =SUM(C39:C43) -> 0 | D44: =SUM(D39:D43) -> 0 | E44: =SUM(E39:E43) -> 0 | F44: =SUM(F39:F43) -> 919.08 | G44: =SUM(G39:G43) -> 922.0553 | H44: =SUM(H39:H43) -> 925.04257 | I44: =SUM(I39:I43) -> 928.04187 | J44: =SUM(J39:J43) -> 931.05325 | ... AD44: =SUM(AD39:AD43) -> 2802.2426 | AE44: =SUM($C44:$N44) -> 8379.8438 | AF44: =SUM(AF39:AF43) -> 2904.9407 | AG44: =SUM(AG39:AG43) -> 2857.4423 | AH44: =SUM(AH39:AH43) -> 2885.5494 | AI44: =SUM(AI39:AI43) -> 2914.0014 | AJ44: =SUM($O44:$Z44) -> 11561.934 | AK44: =AVERAGE(AE44,AJ44)/AVERAGE($AE$58,$AJ$58) -> 0.014436192
B45: Licensing Revenue:
B46: Exclusive:
B47: Initial Fee | C47: =IF(C$5<Assumptions!$B$118,0,IF(C$5=Assumptions!$B$118,Assumptions!$B$120*Assumptions!$B$123,IF(C$5=EDATE(Assumptions!$B$118,12),Assumptions!$B$120*Assumptions!$B$123,0))) -> 10000 | D47: =IF(D$5<Assumptions!$B$118,0,IF(D$5=Assumptions!$B$118,Assumptions!$B$120*Assumptions!$B$123,IF(D$5=EDATE(Assumptions!$B$118,12),Assumptions!$B$120*Assumptions!$B$123,0))) -> 0 | E47: =IF(E$5<Assumptions!$B$118,0,IF(E$5=Assumptions!$B$118,Assumptions!$B$120*Assumptions!$B$123,IF(E$5=EDATE(Assumptions!$B$118,12),Assumptions!$B$120*Assumptions!$B$123,0))) -> 0 | F47: =IF(F$5<Assumptions!$B$118,0,IF(F$5=Assumptions!$B$118,Assumptions!$B$120*Assumptions!$B$123,IF(F$5=EDATE(Assumptions!$B$118,12),Assumptions!$B$120*Assumptions!$B$123,0))) -> 0 | G47: =IF(G$5<Assumptions!$B$118,0,IF(G$5=Assumptions!$B$118,Assumptions!$B$120*Assumptions!$B$123,IF(G$5=EDATE(Assumptions!$B$118,12),Assumptions!$B$120*Assumptions!$B$123,0))) -> 0 | H47: =IF(H$5<Assumptions!$B$118,0,IF(H$5=Assumptions!$B$118,Assumptions!$B$120*Assumptions!$B$123,IF(H$5=EDATE(Assumptions!$B$118,12),Assumptions!$B$120*Assumptions!$B$123,0))) -> 0 | I47: =IF(I$5<Assumptions!$B$118,0,IF(I$5=Assumptions!$B$118,Assumptions!$B$120*Assumptions!$B$123,IF(I$5=EDATE(Assumptions!$B$118,12),Assumptions!$B$120*Assumptions!$B$123,0))) -> 0 | J47: =IF(J$5<Assumptions!$B$118,0,IF(J$5=Assumptions!$B$118,Assumptions!$B$120*Assumptions!$B$123,IF(J$5=EDATE(Assumptions!$B$118,12),Assumptions!$B$120*Assumptions!$B$123,0))) -> 0 | ... Z47: =IF(Z$5<Assumptions!$B$118,0,IF(Z$5=Assumptions!$B$118,Assumptions!$B$120*Assumptions!$B$123,IF(Z$5=EDATE(Assumptions!$B$118,12),Assumptions!$B$120*Assumptions!$B$123,0))) -> 0 | AA47: =SUMIFS($C47:$N47,$C$6:$N$6,AA$5) -> 10000 | AB47: =SUMIFS($C47:$N47,$C$6:$N$6,AB$5) -> 0 | AC47: =SUMIFS($C47:$N47,$C$6:$N$6,AC$5) -> 0 | AD47: =SUMIFS($C47:$N47,$C$6:$N$6,AD$5) -> 0 | AE47: =SUM($C47:$N47) -> 10000 | AF47: =SUMIFS($C47:$N47,$C$6:$N$6,AF$5) -> 10000 | AG47: =SUMIFS($C47:$N47,$C$6:$N$6,AG$5) -> 0 | AH47: =SUMIFS($C47:$N47,$C$6:$N$6,AH$5) -> 0 | AI47: =SUMIFS($C47:$N47,$C$6:$N$6,AI$5) -> 0 | AJ47: =SUM($C47:$N47) -> 10000 | AK47: =AVERAGE(AE47,AJ47)/AVERAGE($AE$58,$AJ$58) -> 0.01447834
B48: Rev. Share | C48: =C49*AVERAGE(Assumptions!$B$14,Assumptions!$B$22,Assumptions!$B$30,Assumptions!$B$38,Assumptions!$B$46)*Assumptions!$B$121 -> 63.825 | D48: =D49*AVERAGE(Assumptions!$B$14,Assumptions!$B$22,Assumptions!$B$30,Assumptions!$B$38,Assumptions!$B$46)*Assumptions!$B$121 -> 63.825 | E48: =E49*AVERAGE(Assumptions!$B$14,Assumptions!$B$22,Assumptions!$B$30,Assumptions!$B$38,Assumptions!$B$46)*Assumptions!$B$121 -> 63.825 | F48: =F49*AVERAGE(Assumptions!$B$14,Assumptions!$B$22,Assumptions!$B$30,Assumptions!$B$38,Assumptions!$B$46)*Assumptions!$B$121 -> 63.825 | G48: =G49*AVERAGE(Assumptions!$B$14,Assumptions!$B$22,Assumptions!$B$30,Assumptions!$B$38,Assumptions!$B$46)*Assumptions!$B$121 -> 63.825 | H48: =H49*AVERAGE(Assumptions!$B$14,Assumptions!$B$22,Assumptions!$B$30,Assumptions!$B$38,Assumptions!$B$46)*Assumptions!$B$121 -> 63.825 | I48: =I49*AVERAGE(Assumptions!$B$14,Assumptions!$B$22,Assumptions!$B$30,Assumptions!$B$38,Assumptions!$B$46)*Assumptions!$B$121 -> 63.825 | J48: =J49*AVERAGE(Assumptions!$B$14,Assumptions!$B$22,Assumptions!$B$30,Assumptions!$B$38,Assumptions!$B$46)*Assumptions!$B$121 -> 63.825 | ... Z48: =Z49*AVERAGE(Assumptions!$B$14,Assumptions!$B$22,Assumptions!$B$30,Assumptions!$B$38,Assumptions!$B$46)*Assumptions!$B$121 -> 63.825 | AA48: =SUMIFS($C48:$N48,$C$6:$N$6,AA$5) -> 191.475 | AB48: =SUMIFS($C48:$N48,$C$6:$N$6,AB$5) -> 191.475 | AC48: =SUMIFS($C48:$N48,$C$6:$N$6,AC$5) -> 191.475 | AD48: =SUMIFS($C48:$N48,$C$6:$N$6,AD$5) -> 191.475 | AE48: =SUM($C48:$N48) -> 765.9 | AF48: =SUMIFS($C48:$N48,$C$6:$N$6,AF$5) -> 191.475 | AG48: =SUMIFS($C48:$N48,$C$6:$N$6,AG$5) -> 191.475 | AH48: =SUMIFS($C48:$N48,$C$6:$N$6,AH$5) -> 191.475 | AI48: =SUMIFS($C48:$N48,$C$6:$N$6,AI$5) -> 191.475 | AJ48: =SUM($C48:$N48) -> 765.9 | AK48: =AVERAGE(AE48,AJ48)/AVERAGE($AE$58,$AJ$58) -> 0.0011088961
B49: Units | C49: =IF(C$5<Assumptions!$B$118,0,(Assumptions!$B$122/12)*Assumptions!$B$123) -> 41.666667 | D49: =IF(D$5<Assumptions!$B$118,0,(Assumptions!$B$122/12)*Assumptions!$B$123) -> 41.666667 | E49: =IF(E$5<Assumptions!$B$118,0,(Assumptions!$B$122/12)*Assumptions!$B$123) -> 41.666667 | F49: =IF(F$5<Assumptions!$B$118,0,(Assumptions!$B$122/12)*Assumptions!$B$123) -> 41.666667 | G49: =IF(G$5<Assumptions!$B$118,0,(Assumptions!$B$122/12)*Assumptions!$B$123) -> 41.666667 | H49: =IF(H$5<Assumptions!$B$118,0,(Assumptions!$B$122/12)*Assumptions!$B$123) -> 41.666667 | I49: =IF(I$5<Assumptions!$B$118,0,(Assumptions!$B$122/12)*Assumptions!$B$123) -> 41.666667 | J49: =IF(J$5<Assumptions!$B$118,0,(Assumptions!$B$122/12)*Assumptions!$B$123) -> 41.666667 | ... Z49: =IF(Z$5<Assumptions!$B$118,0,(Assumptions!$B$122/12)*Assumptions!$B$123) -> 41.666667 | AA49: =SUMIFS($C49:$N49,$C$6:$N$6,AA$5) -> 125 | AB49: =SUMIFS($C49:$N49,$C$6:$N$6,AB$5) -> 125 | AC49: =SUMIFS($C49:$N49,$C$6:$N$6,AC$5) -> 125 | AD49: =SUMIFS($C49:$N49,$C$6:$N$6,AD$5) -> 125 | AE49: =SUM($C49:$N49) -> 500 | AF49: =SUMIFS($C49:$N49,$C$6:$N$6,AF$5) -> 125 | AG49: =SUMIFS($C49:$N49,$C$6:$N$6,AG$5) -> 125 | AH49: =SUMIFS($C49:$N49,$C$6:$N$6,AH$5) -> 125 | AI49: =SUMIFS($C49:$N49,$C$6:$N$6,AI$5) -> 125 | AJ49: =SUM($C49:$N49) -> 500
B50: Total Exclusive Revenue | C50: =C48+C47 -> 10063.825 | D50: =D48+D47 -> 63.825 | E50: =E48+E47 -> 63.825 | F50: =F48+F47 -> 63.825 | G50: =G48+G47 -> 63.825 | H50: =H48+H47 -> 63.825 | I50: =I48+I47 -> 63.825 | J50: =J48+J47 -> 63.825 | ... AJ50: =AJ48+AJ47 -> 10765.9 | AK50: =AVERAGE(AE50,AJ50)/AVERAGE($AE$58,$AJ$58) -> 0.015587236
B51: Non-Exclusive:
B52: Rev. Share | C52: =C53*AVERAGE(Assumptions!$B$14,Assumptions!$B$22,Assumptions!$B$30,Assumptions!$B$38,Assumptions!$B$46)*Assumptions!$B$127 -> 0 | D52: =D53*AVERAGE(Assumptions!$B$14,Assumptions!$B$22,Assumptions!$B$30,Assumptions!$B$38,Assumptions!$B$46)*Assumptions!$B$127 -> 0 | E52: =E53*AVERAGE(Assumptions!$B$14,Assumptions!$B$22,Assumptions!$B$30,Assumptions!$B$38,Assumptions!$B$46)*Assumptions!$B$127 -> 0 | F52: =F53*AVERAGE(Assumptions!$B$14,Assumptions!$B$22,Assumptions!$B$30,Assumptions!$B$38,Assumptions!$B$46)*Assumptions!$B$127 -> 0 | G52: =G53*AVERAGE(Assumptions!$B$14,Assumptions!$B$22,Assumptions!$B$30,Assumptions!$B$38,Assumptions!$B$46)*Assumptions!$B$127 -> 0 | H52: =H53*AVERAGE(Assumptions!$B$14,Assumptions!$B$22,Assumptions!$B$30,Assumptions!$B$38,Assumptions!$B$46)*Assumptions!$B$127 -> 127.65 | I52: =I53*AVERAGE(Assumptions!$B$14,Assumptions!$B$22,Assumptions!$B$30,Assumptions!$B$38,Assumptions!$B$46)*Assumptions!$B$127 -> 127.65 | J52: =J53*AVERAGE(Assumptions!$B$14,Assumptions!$B$22,Assumptions!$B$30,Assumptions!$B$38,Assumptions!$B$46)*Assumptions!$B$127 -> 127.65 | ... Z52: =Z53*AVERAGE(Assumptions!$B$14,Assumptions!$B$22,Assumptions!$B$30,Assumptions!$B$38,Assumptions!$B$46)*Assumptions!$B$127 -> 127.65 | AA52: =SUMIFS($C52:$N52,$C$6:$N$6,AA$5) -> 255.3 | AB52: =SUMIFS($C52:$N52,$C$6:$N$6,AB$5) -> 0 | AC52: =SUMIFS($C52:$N52,$C$6:$N$6,AC$5) -> 255.3 | AD52: =SUMIFS($C52:$N52,$C$6:$N$6,AD$5) -> 382.95 | AE52: =SUM($C52:$N52) -> 893.55 | AF52: =SUMIFS($C52:$N52,$C$6:$N$6,AF$5) -> 255.3 | AG52: =SUMIFS($C52:$N52,$C$6:$N$6,AG$5) -> 0 | AH52: =SUMIFS($C52:$N52,$C$6:$N$6,AH$5) -> 255.3 | AI52: =SUMIFS($C52:$N52,$C$6:$N$6,AI$5) -> 382.95 | AJ52: =SUM($C52:$N52) -> 893.55 | AK52: =AVERAGE(AE52,AJ52)/AVERAGE($AE$58,$AJ$58) -> 0.0012937121
B53: Units | C53: =IF(C$5<Assumptions!$B$125,0,(Assumptions!$B$128/12)*Assumptions!$B$129) -> 0 | D53: =IF(D$5<Assumptions!$B$125,0,(Assumptions!$B$128/12)*Assumptions!$B$129) -> 0 | E53: =IF(E$5<Assumptions!$B$125,0,(Assumptions!$B$128/12)*Assumptions!$B$129) -> 0 | F53: =IF(F$5<Assumptions!$B$125,0,(Assumptions!$B$128/12)*Assumptions!$B$129) -> 0 | G53: =IF(G$5<Assumptions!$B$125,0,(Assumptions!$B$128/12)*Assumptions!$B$129) -> 0 | H53: =IF(H$5<Assumptions!$B$125,0,(Assumptions!$B$128/12)*Assumptions!$B$129) -> 83.333333 | I53: =IF(I$5<Assumptions!$B$125,0,(Assumptions!$B$128/12)*Assumptions!$B$129) -> 83.333333 | J53: =IF(J$5<Assumptions!$B$125,0,(Assumptions!$B$128/12)*Assumptions!$B$129) -> 83.333333 | ... Z53: =IF(Z$5<Assumptions!$B$125,0,(Assumptions!$B$128/12)*Assumptions!$B$129) -> 83.333333 | AA53: =SUMIFS($C53:$N53,$C$6:$N$6,AA$5) -> 166.66667 | AB53: =SUMIFS($C53:$N53,$C$6:$N$6,AB$5) -> 0 | AC53: =SUMIFS($C53:$N53,$C$6:$N$6,AC$5) -> 166.66667 | AD53: =SUMIFS($C53:$N53,$C$6:$N$6,AD$5) -> 250 | AE53: =SUM($C53:$N53) -> 583.33333 | AF53: =SUMIFS($C53:$N53,$C$6:$N$6,AF$5) -> 166.66667 | AG53: =SUMIFS($C53:$N53,$C$6:$N$6,AG$5) -> 0 | AH53: =SUMIFS($C53:$N53,$C$6:$N$6,AH$5) -> 166.66667 | AI53: =SUMIFS($C53:$N53,$C$6:$N$6,AI$5) -> 250 | AJ53: =SUM($C53:$N53) -> 583.33333
B54: Total Non-Exclusive Revenue | C54: =C52 -> 0 | D54: =D52 -> 0 | E54: =E52 -> 0 | F54: =F52 -> 0 | G54: =G52 -> 0 | H54: =H52 -> 127.65 | I54: =I52 -> 127.65 | J54: =J52 -> 127.65 | ... Z54: =Z52 -> 127.65 | AA54: =AA52+AA51 -> 255.3 | AB54: =AB52+AB51 -> 0 | AC54: =AC52+AC51 -> 255.3 | AD54: =AD52+AD51 -> 382.95 | AE54: =AE52+AE51 -> 893.55 | AF54: =AF52+AF51 -> 255.3 | AG54: =AG52+AG51 -> 0 | AH54: =AH52+AH51 -> 255.3 | ... AJ54: =AJ52+AJ51 -> 893.55 | AK54: =AVERAGE(AE54,AJ54)/AVERAGE($AE$58,$AJ$58) -> 0.0012937121
B56: Total Licensing Revenue | C56: =SUM(C54,C50) -> 10063.825 | D56: =SUM(D54,D50) -> 63.825 | E56: =SUM(E54,E50) -> 63.825 | F56: =SUM(F54,F50) -> 63.825 | G56: =SUM(G54,G50) -> 63.825 | H56: =SUM(H54,H50) -> 191.475 | I56: =SUM(I54,I50) -> 191.475 | J56: =SUM(J54,J50) -> 191.475 | ... AJ56: =SUM(AJ54,AJ50) -> 11659.45 | AK56: =AVERAGE(AE56,AJ56)/AVERAGE($AE$58,$AJ$58) -> 0.016880948
B58: Total Revenue | C58: =C37+C44+C56 -> 215026.45 | D58: =D37+D44+D56 -> 63.825 | E58: =E37+E44+E56 -> 105473.18 | F58: =F37+F44+F56 -> 982.905 | G58: =G37+G44+G56 -> 985.8803 | H58: =H37+H44+H56 -> 1116.5176 | I58: =I37+I44+I56 -> 185585.88 | J58: =J37+J44+J56 -> 1122.5283 | ... AJ58: =AJ37+AJ44+AJ56 -> 761086.83
B60: Operating Costs
B62: Wholesale Costs: | AK62: Annual % of Opex
B63: Small Hotels
B64: Twin Package Orders | C64: =((INDEX(Assumptions!$C$8:$C$46,MATCH("Total Twin",Assumptions!$A$8:$A$46,0)))*((C$10+C$11)*INDEX(Assumptions!$E$60:$E$65,MATCH('Cash flow forecast'!$B64,Assumptions!$A$60:$A$65,0)))) -> 6851.25 | D64: =((INDEX(Assumptions!$C$8:$C$46,MATCH("Total Twin",Assumptions!$A$8:$A$46,0)))*((D$10+D$11)*INDEX(Assumptions!$E$60:$E$65,MATCH('Cash flow forecast'!$B64,Assumptions!$A$60:$A$65,0)))) -> 0 | E64: =((INDEX(Assumptions!$C$8:$C$46,MATCH("Total Twin",Assumptions!$A$8:$A$46,0)))*((E$10+E$11)*INDEX(Assumptions!$E$60:$E$65,MATCH('Cash flow forecast'!$B64,Assumptions!$A$60:$A$65,0)))) -> 2740.5 | F64: =((INDEX(Assumptions!$C$8:$C$46,MATCH("Total Twin",Assumptions!$A$8:$A$46,0)))*((F$10+F$11)*INDEX(Assumptions!$E$60:$E$65,MATCH('Cash flow forecast'!$B64,Assumptions!$A$60:$A$65,0)))) -> 0 | G64: =((INDEX(Assumptions!$C$8:$C$46,MATCH("Total Twin",Assumptions!$A$8:$A$46,0)))*((G$10+G$11)*INDEX(Assumptions!$E$60:$E$65,MATCH('Cash flow forecast'!$B64,Assumptions!$A$60:$A$65,0)))) -> 0 | H64: =((INDEX(Assumptions!$C$8:$C$46,MATCH("Total Twin",Assumptions!$A$8:$A$46,0)))*((H$10+H$11)*INDEX(Assumptions!$E$60:$E$65,MATCH('Cash flow forecast'!$B64,Assumptions!$A$60:$A$65,0)))) -> 0 | I64: =((INDEX(Assumptions!$C$8:$C$46,MATCH("Total Twin",Assumptions!$A$8:$A$46,0)))*((I$10+I$11)*INDEX(Assumptions!$E$60:$E$65,MATCH('Cash flow forecast'!$B64,Assumptions!$A$60:$A$65,0)))) -> 6851.25 | J64: =((INDEX(Assumptions!$C$8:$C$46,MATCH("Total Twin",Assumptions!$A$8:$A$46,0)))*((J$10+J$11)*INDEX(Assumptions!$E$60:$E$65,MATCH('Cash flow forecast'!$B64,Assumptions!$A$60:$A$65,0)))) -> 0 | ... Z64: =((INDEX(Assumptions!$C$8:$C$46,MATCH("Total Twin",Assumptions!$A$8:$A$46,0)))*((Z$10+Z$11)*INDEX(Assumptions!$E$60:$E$65,MATCH('Cash flow forecast'!$B64,Assumptions!$A$60:$A$65,0)))) -> 0 | AA64: =SUMIFS($C64:$N64,$C$6:$N$6,AA$5) -> 6851.25 | AB64: =SUMIFS($C64:$N64,$C$6:$N$6,AB$5) -> 2740.5 | AC64: =SUMIFS($C64:$N64,$C$6:$N$6,AC$5) -> 6851.25 | AD64: =SUMIFS($C64:$N64,$C$6:$N$6,AD$5) -> 2740.5 | AE64: =SUM($C64:$N64) -> 19183.5 | AF64: =SUMIFS($O64:$Z64,$O$6:$Z$6,AF$5) -> 6851.25 | AG64: =SUMIFS($O64:$Z64,$O$6:$Z$6,AG$5) -> 2740.5 | AH64: =SUMIFS($O64:$Z64,$O$6:$Z$6,AH$5) -> 6851.25 | AI64: =SUMIFS($O64:$Z64,$O$6:$Z$6,AI$5) -> 9591.75 | AJ64: =SUM($O64:$Z64) -> 26034.75 | AK64: =AVERAGE(AE64,AJ64)/AVERAGE($AE$106,$AJ$106) -> 0.045809594
B65: Full Package Orders | C65: =((INDEX(Assumptions!$C$8:$C$46,MATCH("Total Full",Assumptions!$A$8:$A$46,0)))*((C$10+C$11)*INDEX(Assumptions!$E$60:$E$65,MATCH('Cash flow forecast'!$B65,Assumptions!$A$60:$A$65,0)))) -> 0 | D65: =((INDEX(Assumptions!$C$8:$C$46,MATCH("Total Full",Assumptions!$A$8:$A$46,0)))*((D$10+D$11)*INDEX(Assumptions!$E$60:$E$65,MATCH('Cash flow forecast'!$B65,Assumptions!$A$60:$A$65,0)))) -> 0 | E65: =((INDEX(Assumptions!$C$8:$C$46,MATCH("Total Full",Assumptions!$A$8:$A$46,0)))*((E$10+E$11)*INDEX(Assumptions!$E$60:$E$65,MATCH('Cash flow forecast'!$B65,Assumptions!$A$60:$A$65,0)))) -> 0 | F65: =((INDEX(Assumptions!$C$8:$C$46,MATCH("Total Full",Assumptions!$A$8:$A$46,0)))*((F$10+F$11)*INDEX(Assumptions!$E$60:$E$65,MATCH('Cash flow forecast'!$B65,Assumptions!$A$60:$A$65,0)))) -> 0 | G65: =((INDEX(Assumptions!$C$8:$C$46,MATCH("Total Full",Assumptions!$A$8:$A$46,0)))*((G$10+G$11)*INDEX(Assumptions!$E$60:$E$65,MATCH('Cash flow forecast'!$B65,Assumptions!$A$60:$A$65,0)))) -> 0 | H65: =((INDEX(Assumptions!$C$8:$C$46,MATCH("Total Full",Assumptions!$A$8:$A$46,0)))*((H$10+H$11)*INDEX(Assumptions!$E$60:$E$65,MATCH('Cash flow forecast'!$B65,Assumptions!$A$60:$A$65,0)))) -> 0 | I65: =((INDEX(Assumptions!$C$8:$C$46,MATCH("Total Full",Assumptions!$A$8:$A$46,0)))*((I$10+I$11)*INDEX(Assumptions!$E$60:$E$65,MATCH('Cash flow forecast'!$B65,Assumptions!$A$60:$A$65,0)))) -> 0 | J65: =((INDEX(Assumptions!$C$8:$C$46,MATCH("Total Full",Assumptions!$A$8:$A$46,0)))*((J$10+J$11)*INDEX(Assumptions!$E$60:$E$65,MATCH('Cash flow forecast'!$B65,Assumptions!$A$60:$A$65,0)))) -> 0 | ... Z65: =((INDEX(Assumptions!$C$8:$C$46,MATCH("Total Full",Assumptions!$A$8:$A$46,0)))*((Z$10+Z$11)*INDEX(Assumptions!$E$60:$E$65,MATCH('Cash flow forecast'!$B65,Assumptions!$A$60:$A$65,0)))) -> 0 | AA65: =SUMIFS($C65:$N65,$C$6:$N$6,AA$5) -> 0 | AB65: =SUMIFS($C65:$N65,$C$6:$N$6,AB$5) -> 0 | AC65: =SUMIFS($C65:$N65,$C$6:$N$6,AC$5) -> 0 | AD65: =SUMIFS($C65:$N65,$C$6:$N$6,AD$5) -> 0 | AE65: =SUM($C65:$N65) -> 0 | AF65: =SUMIFS($O65:$Z65,$O$6:$Z$6,AF$5) -> 0 | AG65: =SUMIFS($O65:$Z65,$O$6:$Z$6,AG$5) -> 0 | AH65: =SUMIFS($O65:$Z65,$O$6:$Z$6,AH$5) -> 0 | AI65: =SUMIFS($O65:$Z65,$O$6:$Z$6,AI$5) -> 0 | AJ65: =SUM($O65:$Z65) -> 0 | AK65: =AVERAGE(AE65,AJ65)/AVERAGE($AE$106,$AJ$106) -> 0
B66: Queen Package Orders | C66: =((INDEX(Assumptions!$C$8:$C$46,MATCH("Total Queen",Assumptions!$A$8:$A$46,0)))*((C$10+C$11)*INDEX(Assumptions!$E$60:$E$65,MATCH('Cash flow forecast'!$B66,Assumptions!$A$60:$A$65,0)))) -> 78000 | D66: =((INDEX(Assumptions!$C$8:$C$46,MATCH("Total Queen",Assumptions!$A$8:$A$46,0)))*((D$10+D$11)*INDEX(Assumptions!$E$60:$E$65,MATCH('Cash flow forecast'!$B66,Assumptions!$A$60:$A$65,0)))) -> 0 | E66: =((INDEX(Assumptions!$C$8:$C$46,MATCH("Total Queen",Assumptions!$A$8:$A$46,0)))*((E$10+E$11)*INDEX(Assumptions!$E$60:$E$65,MATCH('Cash flow forecast'!$B66,Assumptions!$A$60:$A$65,0)))) -> 31200 | F66: =((INDEX(Assumptions!$C$8:$C$46,MATCH("Total Queen",Assumptions!$A$8:$A$46,0)))*((F$10+F$11)*INDEX(Assumptions!$E$60:$E$65,MATCH('Cash flow forecast'!$B66,Assumptions!$A$60:$A$65,0)))) -> 0 | G66: =((INDEX(Assumptions!$C$8:$C$46,MATCH("Total Queen",Assumptions!$A$8:$A$46,0)))*((G$10+G$11)*INDEX(Assumptions!$E$60:$E$65,MATCH('Cash flow forecast'!$B66,Assumptions!$A$60:$A$65,0)))) -> 0 | H66: =((INDEX(Assumptions!$C$8:$C$46,MATCH("Total Queen",Assumptions!$A$8:$A$46,0)))*((H$10+H$11)*INDEX(Assumptions!$E$60:$E$65,MATCH('Cash flow forecast'!$B66,Assumptions!$A$60:$A$65,0)))) -> 0 | I66: =((INDEX(Assumptions!$C$8:$C$46,MATCH("Total Queen",Assumptions!$A$8:$A$46,0)))*((I$10+I$11)*INDEX(Assumptions!$E$60:$E$65,MATCH('Cash flow forecast'!$B66,Assumptions!$A$60:$A$65,0)))) -> 78000 | J66: =((INDEX(Assumptions!$C$8:$C$46,MATCH("Total Queen",Assumptions!$A$8:$A$46,0)))*((J$10+J$11)*INDEX(Assumptions!$E$60:$E$65,MATCH('Cash flow forecast'!$B66,Assumptions!$A$60:$A$65,0)))) -> 0 | ... Z66: =((INDEX(Assumptions!$C$8:$C$46,MATCH("Total Queen",Assumptions!$A$8:$A$46,0)))*((Z$10+Z$11)*INDEX(Assumptions!$E$60:$E$65,MATCH('Cash flow forecast'!$B66,Assumptions!$A$60:$A$65,0)))) -> 0 | AA66: =SUMIFS($C66:$N66,$C$6:$N$6,AA$5) -> 78000 | AB66: =SUMIFS($C66:$N66,$C$6:$N$6,AB$5) -> 31200 | AC66: =SUMIFS($C66:$N66,$C$6:$N$6,AC$5) -> 78000 | AD66: =SUMIFS($C66:$N66,$C$6:$N$6,AD$5) -> 31200 | AE66: =SUM($C66:$N66) -> 218400 | AF66: =SUMIFS($O66:$Z66,$O$6:$Z$6,AF$5) -> 78000 | AG66: =SUMIFS($O66:$Z66,$O$6:$Z$6,AG$5) -> 31200 | AH66: =SUMIFS($O66:$Z66,$O$6:$Z$6,AH$5) -> 78000 | AI66: =SUMIFS($O66:$Z66,$O$6:$Z$6,AI$5) -> 109200 | AJ66: =SUM($O66:$Z66) -> 296400 | AK66: =AVERAGE(AE66,AJ66)/AVERAGE($AE$106,$AJ$106) -> 0.52153232
B67: King Package Orders | C67: =((INDEX(Assumptions!$C$8:$C$46,MATCH("Total King",Assumptions!$A$8:$A$46,0)))*((C$10+C$11)*INDEX(Assumptions!$E$60:$E$65,MATCH('Cash flow forecast'!$B67,Assumptions!$A$60:$A$65,0)))) -> 12750 | D67: =((INDEX(Assumptions!$C$8:$C$46,MATCH("Total King",Assumptions!$A$8:$A$46,0)))*((D$10+D$11)*INDEX(Assumptions!$E$60:$E$65,MATCH('Cash flow forecast'!$B67,Assumptions!$A$60:$A$65,0)))) -> 0 | E67: =((INDEX(Assumptions!$C$8:$C$46,MATCH("Total King",Assumptions!$A$8:$A$46,0)))*((E$10+E$11)*INDEX(Assumptions!$E$60:$E$65,MATCH('Cash flow forecast'!$B67,Assumptions!$A$60:$A$65,0)))) -> 5100 | F67: =((INDEX(Assumptions!$C$8:$C$46,MATCH("Total King",Assumptions!$A$8:$A$46,0)))*((F$10+F$11)*INDEX(Assumptions!$E$60:$E$65,MATCH('Cash flow forecast'!$B67,Assumptions!$A$60:$A$65,0)))) -> 0 | G67: =((INDEX(Assumptions!$C$8:$C$46,MATCH("Total King",Assumptions!$A$8:$A$46,0)))*((G$10+G$11)*INDEX(Assumptions!$E$60:$E$65,MATCH('Cash flow forecast'!$B67,Assumptions!$A$60:$A$65,0)))) -> 0 | H67: =((INDEX(Assumptions!$C$8:$C$46,MATCH("Total King",Assumptions!$A$8:$A$46,0)))*((H$10+H$11)*INDEX(Assumptions!$E$60:$E$65,MATCH('Cash flow forecast'!$B67,Assumptions!$A$60:$A$65,0)))) -> 0 | I67: =((INDEX(Assumptions!$C$8:$C$46,MATCH("Total King",Assumptions!$A$8:$A$46,0)))*((I$10+I$11)*INDEX(Assumptions!$E$60:$E$65,MATCH('Cash flow forecast'!$B67,Assumptions!$A$60:$A$65,0)))) -> 12750 | J67: =((INDEX(Assumptions!$C$8:$C$46,MATCH("Total King",Assumptions!$A$8:$A$46,0)))*((J$10+J$11)*INDEX(Assumptions!$E$60:$E$65,MATCH('Cash flow forecast'!$B67,Assumptions!$A$60:$A$65,0)))) -> 0 | ... Z67: =((INDEX(Assumptions!$C$8:$C$46,MATCH("Total King",Assumptions!$A$8:$A$46,0)))*((Z$10+Z$11)*INDEX(Assumptions!$E$60:$E$65,MATCH('Cash flow forecast'!$B67,Assumptions!$A$60:$A$65,0)))) -> 0 | AA67: =SUMIFS($C67:$N67,$C$6:$N$6,AA$5) -> 12750 | AB67: =SUMIFS($C67:$N67,$C$6:$N$6,AB$5) -> 5100 | AC67: =SUMIFS($C67:$N67,$C$6:$N$6,AC$5) -> 12750 | AD67: =SUMIFS($C67:$N67,$C$6:$N$6,AD$5) -> 5100 | AE67: =SUM($C67:$N67) -> 35700 | AF67: =SUMIFS($O67:$Z67,$O$6:$Z$6,AF$5) -> 12750 | AG67: =SUMIFS($O67:$Z67,$O$6:$Z$6,AG$5) -> 5100 | AH67: =SUMIFS($O67:$Z67,$O$6:$Z$6,AH$5) -> 12750 | AI67: =SUMIFS($O67:$Z67,$O$6:$Z$6,AI$5) -> 17850 | AJ67: =SUM($O67:$Z67) -> 48450 | AK67: =AVERAGE(AE67,AJ67)/AVERAGE($AE$106,$AJ$106) -> 0.085250476
B68: Universal Package Orders | C68: =((INDEX(Assumptions!$C$8:$C$46,MATCH("Total Universal",Assumptions!$A$8:$A$46,0)))*((C$10+C$11)*INDEX(Assumptions!$E$60:$E$65,MATCH('Cash flow forecast'!$B68,Assumptions!$A$60:$A$65,0)))) -> 0 | D68: =((INDEX(Assumptions!$C$8:$C$46,MATCH("Total Universal",Assumptions!$A$8:$A$46,0)))*((D$10+D$11)*INDEX(Assumptions!$E$60:$E$65,MATCH('Cash flow forecast'!$B68,Assumptions!$A$60:$A$65,0)))) -> 0 | E68: =((INDEX(Assumptions!$C$8:$C$46,MATCH("Total Universal",Assumptions!$A$8:$A$46,0)))*((E$10+E$11)*INDEX(Assumptions!$E$60:$E$65,MATCH('Cash flow forecast'!$B68,Assumptions!$A$60:$A$65,0)))) -> 0 | F68: =((INDEX(Assumptions!$C$8:$C$46,MATCH("Total Universal",Assumptions!$A$8:$A$46,0)))*((F$10+F$11)*INDEX(Assumptions!$E$60:$E$65,MATCH('Cash flow forecast'!$B68,Assumptions!$A$60:$A$65,0)))) -> 0 | G68: =((INDEX(Assumptions!$C$8:$C$46,MATCH("Total Universal",Assumptions!$A$8:$A$46,0)))*((G$10+G$11)*INDEX(Assumptions!$E$60:$E$65,MATCH('Cash flow forecast'!$B68,Assumptions!$A$60:$A$65,0)))) -> 0 | H68: =((INDEX(Assumptions!$C$8:$C$46,MATCH("Total Universal",Assumptions!$A$8:$A$46,0)))*((H$10+H$11)*INDEX(Assumptions!$E$60:$E$65,MATCH('Cash flow forecast'!$B68,Assumptions!$A$60:$A$65,0)))) -> 0 | I68: =((INDEX(Assumptions!$C$8:$C$46,MATCH("Total Universal",Assumptions!$A$8:$A$46,0)))*((I$10+I$11)*INDEX(Assumptions!$E$60:$E$65,MATCH('Cash flow forecast'!$B68,Assumptions!$A$60:$A$65,0)))) -> 0 | J68: =((INDEX(Assumptions!$C$8:$C$46,MATCH("Total Universal",Assumptions!$A$8:$A$46,0)))*((J$10+J$11)*INDEX(Assumptions!$E$60:$E$65,MATCH('Cash flow forecast'!$B68,Assumptions!$A$60:$A$65,0)))) -> 0 | ... Z68: =((INDEX(Assumptions!$C$8:$C$46,MATCH("Total Universal",Assumptions!$A$8:$A$46,0)))*((Z$10+Z$11)*INDEX(Assumptions!$E$60:$E$65,MATCH('Cash flow forecast'!$B68,Assumptions!$A$60:$A$65,0)))) -> 0 | AA68: =SUMIFS($C68:$N68,$C$6:$N$6,AA$5) -> 0 | AB68: =SUMIFS($C68:$N68,$C$6:$N$6,AB$5) -> 0 | AC68: =SUMIFS($C68:$N68,$C$6:$N$6,AC$5) -> 0 | AD68: =SUMIFS($C68:$N68,$C$6:$N$6,AD$5) -> 0 | AE68: =SUM($C68:$N68) -> 0 | AF68: =SUMIFS($O68:$Z68,$O$6:$Z$6,AF$5) -> 0 | AG68: =SUMIFS($O68:$Z68,$O$6:$Z$6,AG$5) -> 0 | AH68: =SUMIFS($O68:$Z68,$O$6:$Z$6,AH$5) -> 0 | AI68: =SUMIFS($O68:$Z68,$O$6:$Z$6,AI$5) -> 0 | AJ68: =SUM($O68:$Z68) -> 0 | AK68: =AVERAGE(AE68,AJ68)/AVERAGE($AE$106,$AJ$106) -> 0
B69: Total | C69: =SUM(C64:C68) -> 97601.25 | D69: =SUM(D64:D68) -> 0 | E69: =SUM(E64:E68) -> 39040.5 | F69: =SUM(F64:F68) -> 0 | G69: =SUM(G64:G68) -> 0 | H69: =SUM(H64:H68) -> 0 | I69: =SUM(I64:I68) -> 97601.25 | J69: =SUM(J64:J68) -> 0 | ... AD69: =SUM(AD64:AD68) -> 39040.5 | AE69: =SUM($C69:$N69) -> 273283.5 | AF69: =SUM(AF64:AF68) -> 97601.25 | AG69: =SUM(AG64:AG68) -> 39040.5 | AH69: =SUM(AH64:AH68) -> 97601.25 | AI69: =SUM(AI64:AI68) -> 136641.75 | AJ69: =SUM($O69:$Z69) -> 370884.75 | AK69: =AVERAGE(AE69,AJ69)/AVERAGE($AE$106,$AJ$106) -> 0.65259239
B70: Medium Hotels
B71: Twin Package Orders | C71: =((INDEX(Assumptions!$C$8:$C$46,MATCH("Total Twin",Assumptions!$A$8:$A$46,0)))*((C$19+C$20)*INDEX(Assumptions!$E$78:$E$83,MATCH('Cash flow forecast'!$B71,Assumptions!$A$78:$A$83,0)))) -> 1370.25 | D71: =((INDEX(Assumptions!$C$8:$C$46,MATCH("Total Twin",Assumptions!$A$8:$A$46,0)))*((D$19+D$20)*INDEX(Assumptions!$E$78:$E$83,MATCH('Cash flow forecast'!$B71,Assumptions!$A$78:$A$83,0)))) -> 0 | E71: =((INDEX(Assumptions!$C$8:$C$46,MATCH("Total Twin",Assumptions!$A$8:$A$46,0)))*((E$19+E$20)*INDEX(Assumptions!$E$78:$E$83,MATCH('Cash flow forecast'!$B71,Assumptions!$A$78:$A$83,0)))) -> 1370.25 | F71: =((INDEX(Assumptions!$C$8:$C$46,MATCH("Total Twin",Assumptions!$A$8:$A$46,0)))*((F$19+F$20)*INDEX(Assumptions!$E$78:$E$83,MATCH('Cash flow forecast'!$B71,Assumptions!$A$78:$A$83,0)))) -> 0 | G71: =((INDEX(Assumptions!$C$8:$C$46,MATCH("Total Twin",Assumptions!$A$8:$A$46,0)))*((G$19+G$20)*INDEX(Assumptions!$E$78:$E$83,MATCH('Cash flow forecast'!$B71,Assumptions!$A$78:$A$83,0)))) -> 0 | H71: =((INDEX(Assumptions!$C$8:$C$46,MATCH("Total Twin",Assumptions!$A$8:$A$46,0)))*((H$19+H$20)*INDEX(Assumptions!$E$78:$E$83,MATCH('Cash flow forecast'!$B71,Assumptions!$A$78:$A$83,0)))) -> 0 | I71: =((INDEX(Assumptions!$C$8:$C$46,MATCH("Total Twin",Assumptions!$A$8:$A$46,0)))*((I$19+I$20)*INDEX(Assumptions!$E$78:$E$83,MATCH('Cash flow forecast'!$B71,Assumptions!$A$78:$A$83,0)))) -> 1370.25 | J71: =((INDEX(Assumptions!$C$8:$C$46,MATCH("Total Twin",Assumptions!$A$8:$A$46,0)))*((J$19+J$20)*INDEX(Assumptions!$E$78:$E$83,MATCH('Cash flow forecast'!$B71,Assumptions!$A$78:$A$83,0)))) -> 0 | ... Z71: =((INDEX(Assumptions!$C$8:$C$46,MATCH("Total Twin",Assumptions!$A$8:$A$46,0)))*((Z$19+Z$20)*INDEX(Assumptions!$E$78:$E$83,MATCH('Cash flow forecast'!$B71,Assumptions!$A$78:$A$83,0)))) -> 0 | AA71: =SUMIFS($C71:$N71,$C$6:$N$6,AA$5) -> 1370.25 | AB71: =SUMIFS($C71:$N71,$C$6:$N$6,AB$5) -> 1370.25 | AC71: =SUMIFS($C71:$N71,$C$6:$N$6,AC$5) -> 1370.25 | AD71: =SUMIFS($C71:$N71,$C$6:$N$6,AD$5) -> 1370.25 | AE71: =SUM($C71:$N71) -> 5481 | AF71: =SUMIFS($O71:$Z71,$O$6:$Z$6,AF$5) -> 1370.25 | AG71: =SUMIFS($O71:$Z71,$O$6:$Z$6,AG$5) -> 1370.25 | AH71: =SUMIFS($O71:$Z71,$O$6:$Z$6,AH$5) -> 1370.25 | AI71: =SUMIFS($O71:$Z71,$O$6:$Z$6,AI$5) -> 1370.25 | AJ71: =SUM($O71:$Z71) -> 5481 | AK71: =AVERAGE(AE71,AJ71)/AVERAGE($AE$106,$AJ$106) -> 0.011105356
B72: Full Package Orders | C72: =((INDEX(Assumptions!$C$8:$C$46,MATCH("Total Full",Assumptions!$A$8:$A$46,0)))*((C$19+C$20)*INDEX(Assumptions!$E$78:$E$83,MATCH('Cash flow forecast'!$B72,Assumptions!$A$78:$A$83,0)))) -> 0 | D72: =((INDEX(Assumptions!$C$8:$C$46,MATCH("Total Full",Assumptions!$A$8:$A$46,0)))*((D$19+D$20)*INDEX(Assumptions!$E$78:$E$83,MATCH('Cash flow forecast'!$B72,Assumptions!$A$78:$A$83,0)))) -> 0 | E72: =((INDEX(Assumptions!$C$8:$C$46,MATCH("Total Full",Assumptions!$A$8:$A$46,0)))*((E$19+E$20)*INDEX(Assumptions!$E$78:$E$83,MATCH('Cash flow forecast'!$B72,Assumptions!$A$78:$A$83,0)))) -> 0 | F72: =((INDEX(Assumptions!$C$8:$C$46,MATCH("Total Full",Assumptions!$A$8:$A$46,0)))*((F$19+F$20)*INDEX(Assumptions!$E$78:$E$83,MATCH('Cash flow forecast'!$B72,Assumptions!$A$78:$A$83,0)))) -> 0 | G72: =((INDEX(Assumptions!$C$8:$C$46,MATCH("Total Full",Assumptions!$A$8:$A$46,0)))*((G$19+G$20)*INDEX(Assumptions!$E$78:$E$83,MATCH('Cash flow forecast'!$B72,Assumptions!$A$78:$A$83,0)))) -> 0 | H72: =((INDEX(Assumptions!$C$8:$C$46,MATCH("Total Full",Assumptions!$A$8:$A$46,0)))*((H$19+H$20)*INDEX(Assumptions!$E$78:$E$83,MATCH('Cash flow forecast'!$B72,Assumptions!$A$78:$A$83,0)))) -> 0 | I72: =((INDEX(Assumptions!$C$8:$C$46,MATCH("Total Full",Assumptions!$A$8:$A$46,0)))*((I$19+I$20)*INDEX(Assumptions!$E$78:$E$83,MATCH('Cash flow forecast'!$B72,Assumptions!$A$78:$A$83,0)))) -> 0 | J72: =((INDEX(Assumptions!$C$8:$C$46,MATCH("Total Full",Assumptions!$A$8:$A$46,0)))*((J$19+J$20)*INDEX(Assumptions!$E$78:$E$83,MATCH('Cash flow forecast'!$B72,Assumptions!$A$78:$A$83,0)))) -> 0 | ... Z72: =((INDEX(Assumptions!$C$8:$C$46,MATCH("Total Full",Assumptions!$A$8:$A$46,0)))*((Z$19+Z$20)*INDEX(Assumptions!$E$78:$E$83,MATCH('Cash flow forecast'!$B72,Assumptions!$A$78:$A$83,0)))) -> 0 | AA72: =SUMIFS($C72:$N72,$C$6:$N$6,AA$5) -> 0 | AB72: =SUMIFS($C72:$N72,$C$6:$N$6,AB$5) -> 0 | AC72: =SUMIFS($C72:$N72,$C$6:$N$6,AC$5) -> 0 | AD72: =SUMIFS($C72:$N72,$C$6:$N$6,AD$5) -> 0 | AE72: =SUM($C72:$N72) -> 0 | AF72: =SUMIFS($O72:$Z72,$O$6:$Z$6,AF$5) -> 0 | AG72: =SUMIFS($O72:$Z72,$O$6:$Z$6,AG$5) -> 0 | AH72: =SUMIFS($O72:$Z72,$O$6:$Z$6,AH$5) -> 0 | AI72: =SUMIFS($O72:$Z72,$O$6:$Z$6,AI$5) -> 0 | AJ72: =SUM($O72:$Z72) -> 0 | AK72: =AVERAGE(AE72,AJ72)/AVERAGE($AE$106,$AJ$106) -> 0
B73: Queen Package Orders | C73: =((INDEX(Assumptions!$C$8:$C$46,MATCH("Total Queen",Assumptions!$A$8:$A$46,0)))*((C$19+C$20)*INDEX(Assumptions!$E$78:$E$83,MATCH('Cash flow forecast'!$B73,Assumptions!$A$78:$A$83,0)))) -> 15600 | D73: =((INDEX(Assumptions!$C$8:$C$46,MATCH("Total Queen",Assumptions!$A$8:$A$46,0)))*((D$19+D$20)*INDEX(Assumptions!$E$78:$E$83,MATCH('Cash flow forecast'!$B73,Assumptions!$A$78:$A$83,0)))) -> 0 | E73: =((INDEX(Assumptions!$C$8:$C$46,MATCH("Total Queen",Assumptions!$A$8:$A$46,0)))*((E$19+E$20)*INDEX(Assumptions!$E$78:$E$83,MATCH('Cash flow forecast'!$B73,Assumptions!$A$78:$A$83,0)))) -> 15600 | F73: =((INDEX(Assumptions!$C$8:$C$46,MATCH("Total Queen",Assumptions!$A$8:$A$46,0)))*((F$19+F$20)*INDEX(Assumptions!$E$78:$E$83,MATCH('Cash flow forecast'!$B73,Assumptions!$A$78:$A$83,0)))) -> 0 | G73: =((INDEX(Assumptions!$C$8:$C$46,MATCH("Total Queen",Assumptions!$A$8:$A$46,0)))*((G$19+G$20)*INDEX(Assumptions!$E$78:$E$83,MATCH('Cash flow forecast'!$B73,Assumptions!$A$78:$A$83,0)))) -> 0 | H73: =((INDEX(Assumptions!$C$8:$C$46,MATCH("Total Queen",Assumptions!$A$8:$A$46,0)))*((H$19+H$20)*INDEX(Assumptions!$E$78:$E$83,MATCH('Cash flow forecast'!$B73,Assumptions!$A$78:$A$83,0)))) -> 0 | I73: =((INDEX(Assumptions!$C$8:$C$46,MATCH("Total Queen",Assumptions!$A$8:$A$46,0)))*((I$19+I$20)*INDEX(Assumptions!$E$78:$E$83,MATCH('Cash flow forecast'!$B73,Assumptions!$A$78:$A$83,0)))) -> 15600 | J73: =((INDEX(Assumptions!$C$8:$C$46,MATCH("Total Queen",Assumptions!$A$8:$A$46,0)))*((J$19+J$20)*INDEX(Assumptions!$E$78:$E$83,MATCH('Cash flow forecast'!$B73,Assumptions!$A$78:$A$83,0)))) -> 0 | ... Z73: =((INDEX(Assumptions!$C$8:$C$46,MATCH("Total Queen",Assumptions!$A$8:$A$46,0)))*((Z$19+Z$20)*INDEX(Assumptions!$E$78:$E$83,MATCH('Cash flow forecast'!$B73,Assumptions!$A$78:$A$83,0)))) -> 0 | AA73: =SUMIFS($C73:$N73,$C$6:$N$6,AA$5) -> 15600 | AB73: =SUMIFS($C73:$N73,$C$6:$N$6,AB$5) -> 15600 | AC73: =SUMIFS($C73:$N73,$C$6:$N$6,AC$5) -> 15600 | AD73: =SUMIFS($C73:$N73,$C$6:$N$6,AD$5) -> 15600 | AE73: =SUM($C73:$N73) -> 62400 | AF73: =SUMIFS($O73:$Z73,$O$6:$Z$6,AF$5) -> 15600 | AG73: =SUMIFS($O73:$Z73,$O$6:$Z$6,AG$5) -> 15600 | AH73: =SUMIFS($O73:$Z73,$O$6:$Z$6,AH$5) -> 15600 | AI73: =SUMIFS($O73:$Z73,$O$6:$Z$6,AI$5) -> 15600 | AJ73: =SUM($O73:$Z73) -> 62400 | AK73: =AVERAGE(AE73,AJ73)/AVERAGE($AE$106,$AJ$106) -> 0.12643208
B74: King Package Orders | C74: =((INDEX(Assumptions!$C$8:$C$46,MATCH("Total King",Assumptions!$A$8:$A$46,0)))*((C$19+C$20)*INDEX(Assumptions!$E$78:$E$83,MATCH('Cash flow forecast'!$B74,Assumptions!$A$78:$A$83,0)))) -> 2550 | D74: =((INDEX(Assumptions!$C$8:$C$46,MATCH("Total King",Assumptions!$A$8:$A$46,0)))*((D$19+D$20)*INDEX(Assumptions!$E$78:$E$83,MATCH('Cash flow forecast'!$B74,Assumptions!$A$78:$A$83,0)))) -> 0 | E74: =((INDEX(Assumptions!$C$8:$C$46,MATCH("Total King",Assumptions!$A$8:$A$46,0)))*((E$19+E$20)*INDEX(Assumptions!$E$78:$E$83,MATCH('Cash flow forecast'!$B74,Assumptions!$A$78:$A$83,0)))) -> 2550 | F74: =((INDEX(Assumptions!$C$8:$C$46,MATCH("Total King",Assumptions!$A$8:$A$46,0)))*((F$19+F$20)*INDEX(Assumptions!$E$78:$E$83,MATCH('Cash flow forecast'!$B74,Assumptions!$A$78:$A$83,0)))) -> 0 | G74: =((INDEX(Assumptions!$C$8:$C$46,MATCH("Total King",Assumptions!$A$8:$A$46,0)))*((G$19+G$20)*INDEX(Assumptions!$E$78:$E$83,MATCH('Cash flow forecast'!$B74,Assumptions!$A$78:$A$83,0)))) -> 0 | H74: =((INDEX(Assumptions!$C$8:$C$46,MATCH("Total King",Assumptions!$A$8:$A$46,0)))*((H$19+H$20)*INDEX(Assumptions!$E$78:$E$83,MATCH('Cash flow forecast'!$B74,Assumptions!$A$78:$A$83,0)))) -> 0 | I74: =((INDEX(Assumptions!$C$8:$C$46,MATCH("Total King",Assumptions!$A$8:$A$46,0)))*((I$19+I$20)*INDEX(Assumptions!$E$78:$E$83,MATCH('Cash flow forecast'!$B74,Assumptions!$A$78:$A$83,0)))) -> 2550 | J74: =((INDEX(Assumptions!$C$8:$C$46,MATCH("Total King",Assumptions!$A$8:$A$46,0)))*((J$19+J$20)*INDEX(Assumptions!$E$78:$E$83,MATCH('Cash flow forecast'!$B74,Assumptions!$A$78:$A$83,0)))) -> 0 | ... Z74: =((INDEX(Assumptions!$C$8:$C$46,MATCH("Total King",Assumptions!$A$8:$A$46,0)))*((Z$19+Z$20)*INDEX(Assumptions!$E$78:$E$83,MATCH('Cash flow forecast'!$B74,Assumptions!$A$78:$A$83,0)))) -> 0 | AA74: =SUMIFS($C74:$N74,$C$6:$N$6,AA$5) -> 2550 | AB74: =SUMIFS($C74:$N74,$C$6:$N$6,AB$5) -> 2550 | AC74: =SUMIFS($C74:$N74,$C$6:$N$6,AC$5) -> 2550 | AD74: =SUMIFS($C74:$N74,$C$6:$N$6,AD$5) -> 2550 | AE74: =SUM($C74:$N74) -> 10200 | AF74: =SUMIFS($O74:$Z74,$O$6:$Z$6,AF$5) -> 2550 | AG74: =SUMIFS($O74:$Z74,$O$6:$Z$6,AG$5) -> 2550 | AH74: =SUMIFS($O74:$Z74,$O$6:$Z$6,AH$5) -> 2550 | AI74: =SUMIFS($O74:$Z74,$O$6:$Z$6,AI$5) -> 2550 | AJ74: =SUM($O74:$Z74) -> 10200 | AK74: =AVERAGE(AE74,AJ74)/AVERAGE($AE$106,$AJ$106) -> 0.020666782
B75: Universal Package Orders | C75: =((INDEX(Assumptions!$C$8:$C$46,MATCH("Total Universal",Assumptions!$A$8:$A$46,0)))*((C$19+C$20)*INDEX(Assumptions!$E$78:$E$83,MATCH('Cash flow forecast'!$B75,Assumptions!$A$78:$A$83,0)))) -> 0 | D75: =((INDEX(Assumptions!$C$8:$C$46,MATCH("Total Universal",Assumptions!$A$8:$A$46,0)))*((D$19+D$20)*INDEX(Assumptions!$E$78:$E$83,MATCH('Cash flow forecast'!$B75,Assumptions!$A$78:$A$83,0)))) -> 0 | E75: =((INDEX(Assumptions!$C$8:$C$46,MATCH("Total Universal",Assumptions!$A$8:$A$46,0)))*((E$19+E$20)*INDEX(Assumptions!$E$78:$E$83,MATCH('Cash flow forecast'!$B75,Assumptions!$A$78:$A$83,0)))) -> 0 | F75: =((INDEX(Assumptions!$C$8:$C$46,MATCH("Total Universal",Assumptions!$A$8:$A$46,0)))*((F$19+F$20)*INDEX(Assumptions!$E$78:$E$83,MATCH('Cash flow forecast'!$B75,Assumptions!$A$78:$A$83,0)))) -> 0 | G75: =((INDEX(Assumptions!$C$8:$C$46,MATCH("Total Universal",Assumptions!$A$8:$A$46,0)))*((G$19+G$20)*INDEX(Assumptions!$E$78:$E$83,MATCH('Cash flow forecast'!$B75,Assumptions!$A$78:$A$83,0)))) -> 0 | H75: =((INDEX(Assumptions!$C$8:$C$46,MATCH("Total Universal",Assumptions!$A$8:$A$46,0)))*((H$19+H$20)*INDEX(Assumptions!$E$78:$E$83,MATCH('Cash flow forecast'!$B75,Assumptions!$A$78:$A$83,0)))) -> 0 | I75: =((INDEX(Assumptions!$C$8:$C$46,MATCH("Total Universal",Assumptions!$A$8:$A$46,0)))*((I$19+I$20)*INDEX(Assumptions!$E$78:$E$83,MATCH('Cash flow forecast'!$B75,Assumptions!$A$78:$A$83,0)))) -> 0 | J75: =((INDEX(Assumptions!$C$8:$C$46,MATCH("Total Universal",Assumptions!$A$8:$A$46,0)))*((J$19+J$20)*INDEX(Assumptions!$E$78:$E$83,MATCH('Cash flow forecast'!$B75,Assumptions!$A$78:$A$83,0)))) -> 0 | ... Z75: =((INDEX(Assumptions!$C$8:$C$46,MATCH("Total Universal",Assumptions!$A$8:$A$46,0)))*((Z$19+Z$20)*INDEX(Assumptions!$E$78:$E$83,MATCH('Cash flow forecast'!$B75,Assumptions!$A$78:$A$83,0)))) -> 0 | AA75: =SUMIFS($C75:$N75,$C$6:$N$6,AA$5) -> 0 | AB75: =SUMIFS($C75:$N75,$C$6:$N$6,AB$5) -> 0 | AC75: =SUMIFS($C75:$N75,$C$6:$N$6,AC$5) -> 0 | AD75: =SUMIFS($C75:$N75,$C$6:$N$6,AD$5) -> 0 | AE75: =SUM($C75:$N75) -> 0 | AF75: =SUMIFS($O75:$Z75,$O$6:$Z$6,AF$5) -> 0 | AG75: =SUMIFS($O75:$Z75,$O$6:$Z$6,AG$5) -> 0 | AH75: =SUMIFS($O75:$Z75,$O$6:$Z$6,AH$5) -> 0 | AI75: =SUMIFS($O75:$Z75,$O$6:$Z$6,AI$5) -> 0 | AJ75: =SUM($O75:$Z75) -> 0 | AK75: =AVERAGE(AE75,AJ75)/AVERAGE($AE$106,$AJ$106) -> 0
B76: Total | C76: =SUM(C71:C75) -> 19520.25 | D76: =SUM(D71:D75) -> 0 | E76: =SUM(E71:E75) -> 19520.25 | F76: =SUM(F71:F75) -> 0 | G76: =SUM(G71:G75) -> 0 | H76: =SUM(H71:H75) -> 0 | I76: =SUM(I71:I75) -> 19520.25 | J76: =SUM(J71:J75) -> 0 | ... AD76: =SUM(AD71:AD75) -> 19520.25 | AE76: =SUM($C76:$N76) -> 78081 | AF76: =SUM(AF71:AF75) -> 19520.25 | AG76: =SUM(AG71:AG75) -> 19520.25 | AH76: =SUM(AH71:AH75) -> 19520.25 | AI76: =SUM(AI71:AI75) -> 19520.25 | AJ76: =SUM($O76:$Z76) -> 78081 | AK76: =AVERAGE(AE76,AJ76)/AVERAGE($AE$106,$AJ$106) -> 0.15820422
B77: Large Hotels
B78: Twin Package Orders | C78: =((INDEX(Assumptions!$C$8:$C$46,MATCH("Total Twin",Assumptions!$A$8:$A$46,0)))*((C$28+C$29)*INDEX(Assumptions!$E$96:$E$101,MATCH('Cash flow forecast'!$B78,Assumptions!$A$96:$A$101,0)))) -> 1370.25 | D78: =((INDEX(Assumptions!$C$8:$C$46,MATCH("Total Twin",Assumptions!$A$8:$A$46,0)))*((D$28+D$29)*INDEX(Assumptions!$E$96:$E$101,MATCH('Cash flow forecast'!$B78,Assumptions!$A$96:$A$101,0)))) -> 0 | E78: =((INDEX(Assumptions!$C$8:$C$46,MATCH("Total Twin",Assumptions!$A$8:$A$46,0)))*((E$28+E$29)*INDEX(Assumptions!$E$96:$E$101,MATCH('Cash flow forecast'!$B78,Assumptions!$A$96:$A$101,0)))) -> 1370.25 | F78: =((INDEX(Assumptions!$C$8:$C$46,MATCH("Total Twin",Assumptions!$A$8:$A$46,0)))*((F$28+F$29)*INDEX(Assumptions!$E$96:$E$101,MATCH('Cash flow forecast'!$B78,Assumptions!$A$96:$A$101,0)))) -> 0 | G78: =((INDEX(Assumptions!$C$8:$C$46,MATCH("Total Twin",Assumptions!$A$8:$A$46,0)))*((G$28+G$29)*INDEX(Assumptions!$E$96:$E$101,MATCH('Cash flow forecast'!$B78,Assumptions!$A$96:$A$101,0)))) -> 0 | H78: =((INDEX(Assumptions!$C$8:$C$46,MATCH("Total Twin",Assumptions!$A$8:$A$46,0)))*((H$28+H$29)*INDEX(Assumptions!$E$96:$E$101,MATCH('Cash flow forecast'!$B78,Assumptions!$A$96:$A$101,0)))) -> 0 | I78: =((INDEX(Assumptions!$C$8:$C$46,MATCH("Total Twin",Assumptions!$A$8:$A$46,0)))*((I$28+I$29)*INDEX(Assumptions!$E$96:$E$101,MATCH('Cash flow forecast'!$B78,Assumptions!$A$96:$A$101,0)))) -> 1370.25 | J78: =((INDEX(Assumptions!$C$8:$C$46,MATCH("Total Twin",Assumptions!$A$8:$A$46,0)))*((J$28+J$29)*INDEX(Assumptions!$E$96:$E$101,MATCH('Cash flow forecast'!$B78,Assumptions!$A$96:$A$101,0)))) -> 0 | ... Z78: =((INDEX(Assumptions!$C$8:$C$46,MATCH("Total Twin",Assumptions!$A$8:$A$46,0)))*((Z$28+Z$29)*INDEX(Assumptions!$E$96:$E$101,MATCH('Cash flow forecast'!$B78,Assumptions!$A$96:$A$101,0)))) -> 0 | AA78: =SUMIFS($C78:$N78,$C$6:$N$6,AA$5) -> 1370.25 | AB78: =SUMIFS($C78:$N78,$C$6:$N$6,AB$5) -> 1370.25 | AC78: =SUMIFS($C78:$N78,$C$6:$N$6,AC$5) -> 1370.25 | AD78: =SUMIFS($C78:$N78,$C$6:$N$6,AD$5) -> 1370.25 | AE78: =SUM($C78:$N78) -> 5481 | AF78: =SUMIFS($O78:$Z78,$O$6:$Z$6,AF$5) -> 1370.25 | AG78: =SUMIFS($O78:$Z78,$O$6:$Z$6,AG$5) -> 1370.25 | AH78: =SUMIFS($O78:$Z78,$O$6:$Z$6,AH$5) -> 1370.25 | AI78: =SUMIFS($O78:$Z78,$O$6:$Z$6,AI$5) -> 2740.5 | AJ78: =SUM($O78:$Z78) -> 6851.25 | AK78: =AVERAGE(AE78,AJ78)/AVERAGE($AE$106,$AJ$106) -> 0.012493526
B79: Full Package Orders | C79: =((INDEX(Assumptions!$C$8:$C$46,MATCH("Total Full",Assumptions!$A$8:$A$46,0)))*((C$28+C$29)*INDEX(Assumptions!$E$96:$E$101,MATCH('Cash flow forecast'!$B79,Assumptions!$A$96:$A$101,0)))) -> 0 | D79: =((INDEX(Assumptions!$C$8:$C$46,MATCH("Total Full",Assumptions!$A$8:$A$46,0)))*((D$28+D$29)*INDEX(Assumptions!$E$96:$E$101,MATCH('Cash flow forecast'!$B79,Assumptions!$A$96:$A$101,0)))) -> 0 | E79: =((INDEX(Assumptions!$C$8:$C$46,MATCH("Total Full",Assumptions!$A$8:$A$46,0)))*((E$28+E$29)*INDEX(Assumptions!$E$96:$E$101,MATCH('Cash flow forecast'!$B79,Assumptions!$A$96:$A$101,0)))) -> 0 | F79: =((INDEX(Assumptions!$C$8:$C$46,MATCH("Total Full",Assumptions!$A$8:$A$46,0)))*((F$28+F$29)*INDEX(Assumptions!$E$96:$E$101,MATCH('Cash flow forecast'!$B79,Assumptions!$A$96:$A$101,0)))) -> 0 | G79: =((INDEX(Assumptions!$C$8:$C$46,MATCH("Total Full",Assumptions!$A$8:$A$46,0)))*((G$28+G$29)*INDEX(Assumptions!$E$96:$E$101,MATCH('Cash flow forecast'!$B79,Assumptions!$A$96:$A$101,0)))) -> 0 | H79: =((INDEX(Assumptions!$C$8:$C$46,MATCH("Total Full",Assumptions!$A$8:$A$46,0)))*((H$28+H$29)*INDEX(Assumptions!$E$96:$E$101,MATCH('Cash flow forecast'!$B79,Assumptions!$A$96:$A$101,0)))) -> 0 | I79: =((INDEX(Assumptions!$C$8:$C$46,MATCH("Total Full",Assumptions!$A$8:$A$46,0)))*((I$28+I$29)*INDEX(Assumptions!$E$96:$E$101,MATCH('Cash flow forecast'!$B79,Assumptions!$A$96:$A$101,0)))) -> 0 | J79: =((INDEX(Assumptions!$C$8:$C$46,MATCH("Total Full",Assumptions!$A$8:$A$46,0)))*((J$28+J$29)*INDEX(Assumptions!$E$96:$E$101,MATCH('Cash flow forecast'!$B79,Assumptions!$A$96:$A$101,0)))) -> 0 | ... Z79: =((INDEX(Assumptions!$C$8:$C$46,MATCH("Total Full",Assumptions!$A$8:$A$46,0)))*((Z$28+Z$29)*INDEX(Assumptions!$E$96:$E$101,MATCH('Cash flow forecast'!$B79,Assumptions!$A$96:$A$101,0)))) -> 0 | AA79: =SUMIFS($C79:$N79,$C$6:$N$6,AA$5) -> 0 | AB79: =SUMIFS($C79:$N79,$C$6:$N$6,AB$5) -> 0 | AC79: =SUMIFS($C79:$N79,$C$6:$N$6,AC$5) -> 0 | AD79: =SUMIFS($C79:$N79,$C$6:$N$6,AD$5) -> 0 | AE79: =SUM($C79:$N79) -> 0 | AF79: =SUMIFS($O79:$Z79,$O$6:$Z$6,AF$5) -> 0 | AG79: =SUMIFS($O79:$Z79,$O$6:$Z$6,AG$5) -> 0 | AH79: =SUMIFS($O79:$Z79,$O$6:$Z$6,AH$5) -> 0 | AI79: =SUMIFS($O79:$Z79,$O$6:$Z$6,AI$5) -> 0 | AJ79: =SUM($O79:$Z79) -> 0 | AK79: =AVERAGE(AE79,AJ79)/AVERAGE($AE$106,$AJ$106) -> 0
B80: Queen Package Orders | C80: =((INDEX(Assumptions!$C$8:$C$46,MATCH("Total Queen",Assumptions!$A$8:$A$46,0)))*((C$28+C$29)*INDEX(Assumptions!$E$96:$E$101,MATCH('Cash flow forecast'!$B80,Assumptions!$A$96:$A$101,0)))) -> 15600 | D80: =((INDEX(Assumptions!$C$8:$C$46,MATCH("Total Queen",Assumptions!$A$8:$A$46,0)))*((D$28+D$29)*INDEX(Assumptions!$E$96:$E$101,MATCH('Cash flow forecast'!$B80,Assumptions!$A$96:$A$101,0)))) -> 0 | E80: =((INDEX(Assumptions!$C$8:$C$46,MATCH("Total Queen",Assumptions!$A$8:$A$46,0)))*((E$28+E$29)*INDEX(Assumptions!$E$96:$E$101,MATCH('Cash flow forecast'!$B80,Assumptions!$A$96:$A$101,0)))) -> 15600 | F80: =((INDEX(Assumptions!$C$8:$C$46,MATCH("Total Queen",Assumptions!$A$8:$A$46,0)))*((F$28+F$29)*INDEX(Assumptions!$E$96:$E$101,MATCH('Cash flow forecast'!$B80,Assumptions!$A$96:$A$101,0)))) -> 0 | G80: =((INDEX(Assumptions!$C$8:$C$46,MATCH("Total Queen",Assumptions!$A$8:$A$46,0)))*((G$28+G$29)*INDEX(Assumptions!$E$96:$E$101,MATCH('Cash flow forecast'!$B80,Assumptions!$A$96:$A$101,0)))) -> 0 | H80: =((INDEX(Assumptions!$C$8:$C$46,MATCH("Total Queen",Assumptions!$A$8:$A$46,0)))*((H$28+H$29)*INDEX(Assumptions!$E$96:$E$101,MATCH('Cash flow forecast'!$B80,Assumptions!$A$96:$A$101,0)))) -> 0 | I80: =((INDEX(Assumptions!$C$8:$C$46,MATCH("Total Queen",Assumptions!$A$8:$A$46,0)))*((I$28+I$29)*INDEX(Assumptions!$E$96:$E$101,MATCH('Cash flow forecast'!$B80,Assumptions!$A$96:$A$101,0)))) -> 15600 | J80: =((INDEX(Assumptions!$C$8:$C$46,MATCH("Total Queen",Assumptions!$A$8:$A$46,0)))*((J$28+J$29)*INDEX(Assumptions!$E$96:$E$101,MATCH('Cash flow forecast'!$B80,Assumptions!$A$96:$A$101,0)))) -> 0 | ... Z80: =((INDEX(Assumptions!$C$8:$C$46,MATCH("Total Queen",Assumptions!$A$8:$A$46,0)))*((Z$28+Z$29)*INDEX(Assumptions!$E$96:$E$101,MATCH('Cash flow forecast'!$B80,Assumptions!$A$96:$A$101,0)))) -> 0 | AA80: =SUMIFS($C80:$N80,$C$6:$N$6,AA$5) -> 15600 | AB80: =SUMIFS($C80:$N80,$C$6:$N$6,AB$5) -> 15600 | AC80: =SUMIFS($C80:$N80,$C$6:$N$6,AC$5) -> 15600 | AD80: =SUMIFS($C80:$N80,$C$6:$N$6,AD$5) -> 15600 | AE80: =SUM($C80:$N80) -> 62400 | AF80: =SUMIFS($O80:$Z80,$O$6:$Z$6,AF$5) -> 15600 | AG80: =SUMIFS($O80:$Z80,$O$6:$Z$6,AG$5) -> 15600 | AH80: =SUMIFS($O80:$Z80,$O$6:$Z$6,AH$5) -> 15600 | AI80: =SUMIFS($O80:$Z80,$O$6:$Z$6,AI$5) -> 31200 | AJ80: =SUM($O80:$Z80) -> 78000 | AK80: =AVERAGE(AE80,AJ80)/AVERAGE($AE$106,$AJ$106) -> 0.14223609
B81: King Package Orders | C81: =((INDEX(Assumptions!$C$8:$C$46,MATCH("Total King",Assumptions!$A$8:$A$46,0)))*((C$28+C$29)*INDEX(Assumptions!$E$96:$E$101,MATCH('Cash flow forecast'!$B81,Assumptions!$A$96:$A$101,0)))) -> 2550 | D81: =((INDEX(Assumptions!$C$8:$C$46,MATCH("Total King",Assumptions!$A$8:$A$46,0)))*((D$28+D$29)*INDEX(Assumptions!$E$96:$E$101,MATCH('Cash flow forecast'!$B81,Assumptions!$A$96:$A$101,0)))) -> 0 | E81: =((INDEX(Assumptions!$C$8:$C$46,MATCH("Total King",Assumptions!$A$8:$A$46,0)))*((E$28+E$29)*INDEX(Assumptions!$E$96:$E$101,MATCH('Cash flow forecast'!$B81,Assumptions!$A$96:$A$101,0)))) -> 2550 | F81: =((INDEX(Assumptions!$C$8:$C$46,MATCH("Total King",Assumptions!$A$8:$A$46,0)))*((F$28+F$29)*INDEX(Assumptions!$E$96:$E$101,MATCH('Cash flow forecast'!$B81,Assumptions!$A$96:$A$101,0)))) -> 0 | G81: =((INDEX(Assumptions!$C$8:$C$46,MATCH("Total King",Assumptions!$A$8:$A$46,0)))*((G$28+G$29)*INDEX(Assumptions!$E$96:$E$101,MATCH('Cash flow forecast'!$B81,Assumptions!$A$96:$A$101,0)))) -> 0 | H81: =((INDEX(Assumptions!$C$8:$C$46,MATCH("Total King",Assumptions!$A$8:$A$46,0)))*((H$28+H$29)*INDEX(Assumptions!$E$96:$E$101,MATCH('Cash flow forecast'!$B81,Assumptions!$A$96:$A$101,0)))) -> 0 | I81: =((INDEX(Assumptions!$C$8:$C$46,MATCH("Total King",Assumptions!$A$8:$A$46,0)))*((I$28+I$29)*INDEX(Assumptions!$E$96:$E$101,MATCH('Cash flow forecast'!$B81,Assumptions!$A$96:$A$101,0)))) -> 2550 | J81: =((INDEX(Assumptions!$C$8:$C$46,MATCH("Total King",Assumptions!$A$8:$A$46,0)))*((J$28+J$29)*INDEX(Assumptions!$E$96:$E$101,MATCH('Cash flow forecast'!$B81,Assumptions!$A$96:$A$101,0)))) -> 0 | ... Z81: =((INDEX(Assumptions!$C$8:$C$46,MATCH("Total King",Assumptions!$A$8:$A$46,0)))*((Z$28+Z$29)*INDEX(Assumptions!$E$96:$E$101,MATCH('Cash flow forecast'!$B81,Assumptions!$A$96:$A$101,0)))) -> 0 | AA81: =SUMIFS($C81:$N81,$C$6:$N$6,AA$5) -> 2550 | AB81: =SUMIFS($C81:$N81,$C$6:$N$6,AB$5) -> 2550 | AC81: =SUMIFS($C81:$N81,$C$6:$N$6,AC$5) -> 2550 | AD81: =SUMIFS($C81:$N81,$C$6:$N$6,AD$5) -> 2550 | AE81: =SUM($C81:$N81) -> 10200 | AF81: =SUMIFS($O81:$Z81,$O$6:$Z$6,AF$5) -> 2550 | AG81: =SUMIFS($O81:$Z81,$O$6:$Z$6,AG$5) -> 2550 | AH81: =SUMIFS($O81:$Z81,$O$6:$Z$6,AH$5) -> 2550 | AI81: =SUMIFS($O81:$Z81,$O$6:$Z$6,AI$5) -> 5100 | AJ81: =SUM($O81:$Z81) -> 12750 | AK81: =AVERAGE(AE81,AJ81)/AVERAGE($AE$106,$AJ$106) -> 0.02325013
B82: Universal Package Orders | C82: =((INDEX(Assumptions!$C$8:$C$46,MATCH("Total Universal",Assumptions!$A$8:$A$46,0)))*((C$28+C$29)*INDEX(Assumptions!$E$96:$E$101,MATCH('Cash flow forecast'!$B82,Assumptions!$A$96:$A$101,0)))) -> 0 | D82: =((INDEX(Assumptions!$C$8:$C$46,MATCH("Total Universal",Assumptions!$A$8:$A$46,0)))*((D$28+D$29)*INDEX(Assumptions!$E$96:$E$101,MATCH('Cash flow forecast'!$B82,Assumptions!$A$96:$A$101,0)))) -> 0 | E82: =((INDEX(Assumptions!$C$8:$C$46,MATCH("Total Universal",Assumptions!$A$8:$A$46,0)))*((E$28+E$29)*INDEX(Assumptions!$E$96:$E$101,MATCH('Cash flow forecast'!$B82,Assumptions!$A$96:$A$101,0)))) -> 0 | F82: =((INDEX(Assumptions!$C$8:$C$46,MATCH("Total Universal",Assumptions!$A$8:$A$46,0)))*((F$28+F$29)*INDEX(Assumptions!$E$96:$E$101,MATCH('Cash flow forecast'!$B82,Assumptions!$A$96:$A$101,0)))) -> 0 | G82: =((INDEX(Assumptions!$C$8:$C$46,MATCH("Total Universal",Assumptions!$A$8:$A$46,0)))*((G$28+G$29)*INDEX(Assumptions!$E$96:$E$101,MATCH('Cash flow forecast'!$B82,Assumptions!$A$96:$A$101,0)))) -> 0 | H82: =((INDEX(Assumptions!$C$8:$C$46,MATCH("Total Universal",Assumptions!$A$8:$A$46,0)))*((H$28+H$29)*INDEX(Assumptions!$E$96:$E$101,MATCH('Cash flow forecast'!$B82,Assumptions!$A$96:$A$101,0)))) -> 0 | I82: =((INDEX(Assumptions!$C$8:$C$46,MATCH("Total Universal",Assumptions!$A$8:$A$46,0)))*((I$28+I$29)*INDEX(Assumptions!$E$96:$E$101,MATCH('Cash flow forecast'!$B82,Assumptions!$A$96:$A$101,0)))) -> 0 | J82: =((INDEX(Assumptions!$C$8:$C$46,MATCH("Total Universal",Assumptions!$A$8:$A$46,0)))*((J$28+J$29)*INDEX(Assumptions!$E$96:$E$101,MATCH('Cash flow forecast'!$B82,Assumptions!$A$96:$A$101,0)))) -> 0 | ... Z82: =((INDEX(Assumptions!$C$8:$C$46,MATCH("Total Universal",Assumptions!$A$8:$A$46,0)))*((Z$28+Z$29)*INDEX(Assumptions!$E$96:$E$101,MATCH('Cash flow forecast'!$B82,Assumptions!$A$96:$A$101,0)))) -> 0 | AA82: =SUMIFS($C82:$N82,$C$6:$N$6,AA$5) -> 0 | AB82: =SUMIFS($C82:$N82,$C$6:$N$6,AB$5) -> 0 | AC82: =SUMIFS($C82:$N82,$C$6:$N$6,AC$5) -> 0 | AD82: =SUMIFS($C82:$N82,$C$6:$N$6,AD$5) -> 0 | AE82: =SUM($C82:$N82) -> 0 | AF82: =SUMIFS($O82:$Z82,$O$6:$Z$6,AF$5) -> 0 | AG82: =SUMIFS($O82:$Z82,$O$6:$Z$6,AG$5) -> 0 | AH82: =SUMIFS($O82:$Z82,$O$6:$Z$6,AH$5) -> 0 | AI82: =SUMIFS($O82:$Z82,$O$6:$Z$6,AI$5) -> 0 | AJ82: =SUM($O82:$Z82) -> 0 | AK82: =AVERAGE(AE82,AJ82)/AVERAGE($AE$106,$AJ$106) -> 0
B83: Total | C83: =SUM(C78:C82) -> 19520.25 | D83: =SUM(D78:D82) -> 0 | E83: =SUM(E78:E82) -> 19520.25 | F83: =SUM(F78:F82) -> 0 | G83: =SUM(G78:G82) -> 0 | H83: =SUM(H78:H82) -> 0 | I83: =SUM(I78:I82) -> 19520.25 | J83: =SUM(J78:J82) -> 0 | ... AD83: =SUM(AD78:AD82) -> 19520.25 | AE83: =SUM($C83:$N83) -> 78081 | AF83: =SUM(AF78:AF82) -> 19520.25 | AG83: =SUM(AG78:AG82) -> 19520.25 | AH83: =SUM(AH78:AH82) -> 19520.25 | AI83: =SUM(AI78:AI82) -> 39040.5 | AJ83: =SUM($O83:$Z83) -> 97601.25 | AK83: =AVERAGE(AE83,AJ83)/AVERAGE($AE$106,$AJ$106) -> 0.17797974
B85: Total Wholesale Costs | C85: =C69+C76+C83 -> 136641.75 | D85: =D69+D76+D83 -> 0 | E85: =E69+E76+E83 -> 78081 | F85: =F69+F76+F83 -> 0 | G85: =G69+G76+G83 -> 0 | H85: =H69+H76+H83 -> 0 | I85: =I69+I76+I83 -> 136641.75 | J85: =J69+J76+J83 -> 0 | ... AJ85: =AJ69+AJ76+AJ83 -> 546567 | AK85: =AVERAGE(AE85,AJ85)/AVERAGE($AE$106,$AJ$106) -> 0.98877635
B86: Retail Costs:
B87: Twin Package Orders | C87: =IF(C$5<Assumptions!$B$106,0,INDEX(Assumptions!$B$108:$B$112,MATCH('Cash flow forecast'!$B87,Assumptions!$A$108:$A$112,0))*(INDEX(Assumptions!$C$4:$C$46,MATCH("Total Twin",Assumptions!$A$4:$A$46,0)))) -> 0 | D87: =IF(D$5<Assumptions!$B$106,0,IF('Cash flow forecast'!D$5=Assumptions!$B$106,INDEX(Assumptions!$B$108:$B$112,MATCH('Cash flow forecast'!$B87,Assumptions!$A$108:$A$112,0))*(INDEX(Assumptions!$C$4:$C$46,MATCH("Total Twin",Assumptions!$A$4:$A$46,0))),(C87*(1+INDEX(Assumptions!$C$108:$C$112,MATCH('Cash flow forecast'!$B87,Assumptions!$A$108:$A$112,0))/12))*(1+INDEX(Assumptions!$D$108:$D$112,MATCH('Cash flow forecast'!$B87,Assumptions!$A$108:$A$112,0))/12))) -> 0 | E87: =IF(E$5<Assumptions!$B$106,0,IF('Cash flow forecast'!E$5=Assumptions!$B$106,INDEX(Assumptions!$B$108:$B$112,MATCH('Cash flow forecast'!$B87,Assumptions!$A$108:$A$112,0))*(INDEX(Assumptions!$C$4:$C$46,MATCH("Total Twin",Assumptions!$A$4:$A$46,0))),(D87*(1+INDEX(Assumptions!$C$108:$C$112,MATCH('Cash flow forecast'!$B87,Assumptions!$A$108:$A$112,0))/12))*(1+INDEX(Assumptions!$D$108:$D$112,MATCH('Cash flow forecast'!$B87,Assumptions!$A$108:$A$112,0))/12))) -> 0 | F87: =IF(F$5<Assumptions!$B$106,0,IF('Cash flow forecast'!F$5=Assumptions!$B$106,INDEX(Assumptions!$B$108:$B$112,MATCH('Cash flow forecast'!$B87,Assumptions!$A$108:$A$112,0))*(INDEX(Assumptions!$C$4:$C$46,MATCH("Total Twin",Assumptions!$A$4:$A$46,0))),(E87*(1+INDEX(Assumptions!$C$108:$C$112,MATCH('Cash flow forecast'!$B87,Assumptions!$A$108:$A$112,0))/12))*(1+INDEX(Assumptions!$D$108:$D$112,MATCH('Cash flow forecast'!$B87,Assumptions!$A$108:$A$112,0))/12))) -> 91.35 | G87: =IF(G$5<Assumptions!$B$106,0,IF('Cash flow forecast'!G$5=Assumptions!$B$106,INDEX(Assumptions!$B$108:$B$112,MATCH('Cash flow forecast'!$B87,Assumptions!$A$108:$A$112,0))*(INDEX(Assumptions!$C$4:$C$46,MATCH("Total Twin",Assumptions!$A$4:$A$46,0))),(F87*(1+INDEX(Assumptions!$C$108:$C$112,MATCH('Cash flow forecast'!$B87,Assumptions!$A$108:$A$112,0))/12))*(1+INDEX(Assumptions!$D$108:$D$112,MATCH('Cash flow forecast'!$B87,Assumptions!$A$108:$A$112,0))/12))) -> 91.957731 | H87: =IF(H$5<Assumptions!$B$106,0,IF('Cash flow forecast'!H$5=Assumptions!$B$106,INDEX(Assumptions!$B$108:$B$112,MATCH('Cash flow forecast'!$B87,Assumptions!$A$108:$A$112,0))*(INDEX(Assumptions!$C$4:$C$46,MATCH("Total Twin",Assumptions!$A$4:$A$46,0))),(G87*(1+INDEX(Assumptions!$C$108:$C$112,MATCH('Cash flow forecast'!$B87,Assumptions!$A$108:$A$112,0))/12))*(1+INDEX(Assumptions!$D$108:$D$112,MATCH('Cash flow forecast'!$B87,Assumptions!$A$108:$A$112,0))/12))) -> 92.569506 | I87: =IF(I$5<Assumptions!$B$106,0,IF('Cash flow forecast'!I$5=Assumptions!$B$106,INDEX(Assumptions!$B$108:$B$112,MATCH('Cash flow forecast'!$B87,Assumptions!$A$108:$A$112,0))*(INDEX(Assumptions!$C$4:$C$46,MATCH("Total Twin",Assumptions!$A$4:$A$46,0))),(H87*(1+INDEX(Assumptions!$C$108:$C$112,MATCH('Cash flow forecast'!$B87,Assumptions!$A$108:$A$112,0))/12))*(1+INDEX(Assumptions!$D$108:$D$112,MATCH('Cash flow forecast'!$B87,Assumptions!$A$108:$A$112,0))/12))) -> 93.18535 | J87: =IF(J$5<Assumptions!$B$106,0,IF('Cash flow forecast'!J$5=Assumptions!$B$106,INDEX(Assumptions!$B$108:$B$112,MATCH('Cash flow forecast'!$B87,Assumptions!$A$108:$A$112,0))*(INDEX(Assumptions!$C$4:$C$46,MATCH("Total Twin",Assumptions!$A$4:$A$46,0))),(I87*(1+INDEX(Assumptions!$C$108:$C$112,MATCH('Cash flow forecast'!$B87,Assumptions!$A$108:$A$112,0))/12))*(1+INDEX(Assumptions!$D$108:$D$112,MATCH('Cash flow forecast'!$B87,Assumptions!$A$108:$A$112,0))/12))) -> 93.805291 | K87: =IF(K$5<Assumptions!$B$106,0,IF('Cash flow forecast'!K$5=Assumptions!$B$106,INDEX(Assumptions!$B$108:$B$112,MATCH('Cash flow forecast'!$B87,Assumptions!$A$108:$A$112,0))*(INDEX(Assumptions!$C$4:$C$46,MATCH("Total Twin",Assumptions!$A$4:$A$46,0))),(J87*(1+INDEX(Assumptions!$C$108:$C$112,MATCH('Cash flow forecast'!$B87,Assumptions!$A$108:$A$112,0))/12))*(1+INDEX(Assumptions!$D$108:$D$112,MATCH('Cash flow forecast'!$B87,Assumptions!$A$108:$A$112,0))/12))) -> 94.429357 | ... Z87: =IF(Z$5<Assumptions!$B$106,0,IF('Cash flow forecast'!Z$5=Assumptions!$B$106,INDEX(Assumptions!$B$108:$B$112,MATCH('Cash flow forecast'!$B87,Assumptions!$A$108:$A$112,0))*(INDEX(Assumptions!$C$4:$C$46,MATCH("Total Twin",Assumptions!$A$4:$A$46,0))),(Y87*(1+INDEX(Assumptions!$C$108:$C$112,MATCH('Cash flow forecast'!$B87,Assumptions!$A$108:$A$112,0))/12))*(1+INDEX(Assumptions!$D$108:$D$112,MATCH('Cash flow forecast'!$B87,Assumptions!$A$108:$A$112,0))/12))) -> 104.30436 | AA87: =SUMIFS($C87:$N87,$C$6:$N$6,AA$5) -> 192.01655 | AB87: =SUMIFS($C87:$N87,$C$6:$N$6,AB$5) -> 91.35 | AC87: =SUMIFS($C87:$N87,$C$6:$N$6,AC$5) -> 277.71259 | AD87: =SUMIFS($C87:$N87,$C$6:$N$6,AD$5) -> 283.29222 | AE87: =SUM($C87:$N87) -> 844.37136 | AF87: =SUMIFS($O87:$Z87,$O$6:$Z$6,AF$5) -> 304.88681 | AG87: =SUMIFS($O87:$Z87,$O$6:$Z$6,AG$5) -> 294.79006 | AH87: =SUMIFS($O87:$Z87,$O$6:$Z$6,AH$5) -> 300.7128 | AI87: =SUMIFS($O87:$Z87,$O$6:$Z$6,AI$5) -> 306.75455 | AJ87: =SUM($O87:$Z87) -> 1207.1442 | AK87: =AVERAGE(AE87,AJ87)/AVERAGE($AE$106,$AJ$106) -> 0.0020783444
B88: Full Package Orders | C88: =IF(C$5<Assumptions!$B$106,0,INDEX(Assumptions!$B$108:$B$112,MATCH('Cash flow forecast'!$B88,Assumptions!$A$108:$A$112,0))*(INDEX(Assumptions!$C$4:$C$46,MATCH("Total Full",Assumptions!$A$4:$A$46,0)))) -> 0 | D88: =IF(D$5<Assumptions!$B$106,0,IF('Cash flow forecast'!D$5=Assumptions!$B$106,INDEX(Assumptions!$B$108:$B$112,MATCH('Cash flow forecast'!$B88,Assumptions!$A$108:$A$112,0))*(INDEX(Assumptions!$C$4:$C$46,MATCH("Total Full",Assumptions!$A$4:$A$46,0))),(C88*(1+INDEX(Assumptions!$C$108:$C$112,MATCH('Cash flow forecast'!$B88,Assumptions!$A$108:$A$112,0))/12))*(1+INDEX(Assumptions!$D$108:$D$112,MATCH('Cash flow forecast'!$B88,Assumptions!$A$108:$A$112,0))/12))) -> 0 | E88: =IF(E$5<Assumptions!$B$106,0,IF('Cash flow forecast'!E$5=Assumptions!$B$106,INDEX(Assumptions!$B$108:$B$112,MATCH('Cash flow forecast'!$B88,Assumptions!$A$108:$A$112,0))*(INDEX(Assumptions!$C$4:$C$46,MATCH("Total Full",Assumptions!$A$4:$A$46,0))),(D88*(1+INDEX(Assumptions!$C$108:$C$112,MATCH('Cash flow forecast'!$B88,Assumptions!$A$108:$A$112,0))/12))*(1+INDEX(Assumptions!$D$108:$D$112,MATCH('Cash flow forecast'!$B88,Assumptions!$A$108:$A$112,0))/12))) -> 0 | F88: =IF(F$5<Assumptions!$B$106,0,IF('Cash flow forecast'!F$5=Assumptions!$B$106,INDEX(Assumptions!$B$108:$B$112,MATCH('Cash flow forecast'!$B88,Assumptions!$A$108:$A$112,0))*(INDEX(Assumptions!$C$4:$C$46,MATCH("Total Full",Assumptions!$A$4:$A$46,0))),(E88*(1+INDEX(Assumptions!$C$108:$C$112,MATCH('Cash flow forecast'!$B88,Assumptions!$A$108:$A$112,0))/12))*(1+INDEX(Assumptions!$D$108:$D$112,MATCH('Cash flow forecast'!$B88,Assumptions!$A$108:$A$112,0))/12))) -> 75.7 | G88: =IF(G$5<Assumptions!$B$106,0,IF('Cash flow forecast'!G$5=Assumptions!$B$106,INDEX(Assumptions!$B$108:$B$112,MATCH('Cash flow forecast'!$B88,Assumptions!$A$108:$A$112,0))*(INDEX(Assumptions!$C$4:$C$46,MATCH("Total Full",Assumptions!$A$4:$A$46,0))),(F88*(1+INDEX(Assumptions!$C$108:$C$112,MATCH('Cash flow forecast'!$B88,Assumptions!$A$108:$A$112,0))/12))*(1+INDEX(Assumptions!$D$108:$D$112,MATCH('Cash flow forecast'!$B88,Assumptions!$A$108:$A$112,0))/12))) -> 75.888724 | H88: =IF(H$5<Assumptions!$B$106,0,IF('Cash flow forecast'!H$5=Assumptions!$B$106,INDEX(Assumptions!$B$108:$B$112,MATCH('Cash flow forecast'!$B88,Assumptions!$A$108:$A$112,0))*(INDEX(Assumptions!$C$4:$C$46,MATCH("Total Full",Assumptions!$A$4:$A$46,0))),(G88*(1+INDEX(Assumptions!$C$108:$C$112,MATCH('Cash flow forecast'!$B88,Assumptions!$A$108:$A$112,0))/12))*(1+INDEX(Assumptions!$D$108:$D$112,MATCH('Cash flow forecast'!$B88,Assumptions!$A$108:$A$112,0))/12))) -> 76.077919 | I88: =IF(I$5<Assumptions!$B$106,0,IF('Cash flow forecast'!I$5=Assumptions!$B$106,INDEX(Assumptions!$B$108:$B$112,MATCH('Cash flow forecast'!$B88,Assumptions!$A$108:$A$112,0))*(INDEX(Assumptions!$C$4:$C$46,MATCH("Total Full",Assumptions!$A$4:$A$46,0))),(H88*(1+INDEX(Assumptions!$C$108:$C$112,MATCH('Cash flow forecast'!$B88,Assumptions!$A$108:$A$112,0))/12))*(1+INDEX(Assumptions!$D$108:$D$112,MATCH('Cash flow forecast'!$B88,Assumptions!$A$108:$A$112,0))/12))) -> 76.267586 | J88: =IF(J$5<Assumptions!$B$106,0,IF('Cash flow forecast'!J$5=Assumptions!$B$106,INDEX(Assumptions!$B$108:$B$112,MATCH('Cash flow forecast'!$B88,Assumptions!$A$108:$A$112,0))*(INDEX(Assumptions!$C$4:$C$46,MATCH("Total Full",Assumptions!$A$4:$A$46,0))),(I88*(1+INDEX(Assumptions!$C$108:$C$112,MATCH('Cash flow forecast'!$B88,Assumptions!$A$108:$A$112,0))/12))*(1+INDEX(Assumptions!$D$108:$D$112,MATCH('Cash flow forecast'!$B88,Assumptions!$A$108:$A$112,0))/12))) -> 76.457725 | K88: =IF(K$5<Assumptions!$B$106,0,IF('Cash flow forecast'!K$5=Assumptions!$B$106,INDEX(Assumptions!$B$108:$B$112,MATCH('Cash flow forecast'!$B88,Assumptions!$A$108:$A$112,0))*(INDEX(Assumptions!$C$4:$C$46,MATCH("Total Full",Assumptions!$A$4:$A$46,0))),(J88*(1+INDEX(Assumptions!$C$108:$C$112,MATCH('Cash flow forecast'!$B88,Assumptions!$A$108:$A$112,0))/12))*(1+INDEX(Assumptions!$D$108:$D$112,MATCH('Cash flow forecast'!$B88,Assumptions!$A$108:$A$112,0))/12))) -> 76.648338 | ... Z88: =IF(Z$5<Assumptions!$B$106,0,IF('Cash flow forecast'!Z$5=Assumptions!$B$106,INDEX(Assumptions!$B$108:$B$112,MATCH('Cash flow forecast'!$B88,Assumptions!$A$108:$A$112,0))*(INDEX(Assumptions!$C$4:$C$46,MATCH("Total Full",Assumptions!$A$4:$A$46,0))),(Y88*(1+INDEX(Assumptions!$C$108:$C$112,MATCH('Cash flow forecast'!$B88,Assumptions!$A$108:$A$112,0))/12))*(1+INDEX(Assumptions!$D$108:$D$112,MATCH('Cash flow forecast'!$B88,Assumptions!$A$108:$A$112,0))/12))) -> 79.565233 | AA88: =SUMIFS($C88:$N88,$C$6:$N$6,AA$5) -> 154.25403 | AB88: =SUMIFS($C88:$N88,$C$6:$N$6,AB$5) -> 75.7 | AC88: =SUMIFS($C88:$N88,$C$6:$N$6,AC$5) -> 228.23423 | AD88: =SUMIFS($C88:$N88,$C$6:$N$6,AD$5) -> 229.94549 | AE88: =SUM($C88:$N88) -> 688.13375 | AF88: =SUMIFS($O88:$Z88,$O$6:$Z$6,AF$5) -> 236.34815 | AG88: =SUMIFS($O88:$Z88,$O$6:$Z$6,AG$5) -> 233.4066 | AH88: =SUMIFS($O88:$Z88,$O$6:$Z$6,AH$5) -> 235.15664 | AI88: =SUMIFS($O88:$Z88,$O$6:$Z$6,AI$5) -> 236.91981 | AJ88: =SUM($O88:$Z88) -> 941.8312 | AK88: =AVERAGE(AE88,AJ88)/AVERAGE($AE$106,$AJ$106) -> 0.0016512809
B89: Queen Package Orders | C89: =IF(C$5<Assumptions!$B$106,0,INDEX(Assumptions!$B$108:$B$112,MATCH('Cash flow forecast'!$B89,Assumptions!$A$108:$A$112,0))*(INDEX(Assumptions!$C$4:$C$46,MATCH("Total Queen",Assumptions!$A$4:$A$46,0)))) -> 0 | D89: =IF(D$5<Assumptions!$B$106,0,IF('Cash flow forecast'!D$5=Assumptions!$B$106,INDEX(Assumptions!$B$108:$B$112,MATCH('Cash flow forecast'!$B89,Assumptions!$A$108:$A$112,0))*(INDEX(Assumptions!$C$4:$C$46,MATCH("Total Queen",Assumptions!$A$4:$A$46,0))),(C89*(1+INDEX(Assumptions!$C$108:$C$112,MATCH('Cash flow forecast'!$B89,Assumptions!$A$108:$A$112,0))/12))*(1+INDEX(Assumptions!$D$108:$D$112,MATCH('Cash flow forecast'!$B89,Assumptions!$A$108:$A$112,0))/12))) -> 0 | E89: =IF(E$5<Assumptions!$B$106,0,IF('Cash flow forecast'!E$5=Assumptions!$B$106,INDEX(Assumptions!$B$108:$B$112,MATCH('Cash flow forecast'!$B89,Assumptions!$A$108:$A$112,0))*(INDEX(Assumptions!$C$4:$C$46,MATCH("Total Queen",Assumptions!$A$4:$A$46,0))),(D89*(1+INDEX(Assumptions!$C$108:$C$112,MATCH('Cash flow forecast'!$B89,Assumptions!$A$108:$A$112,0))/12))*(1+INDEX(Assumptions!$D$108:$D$112,MATCH('Cash flow forecast'!$B89,Assumptions!$A$108:$A$112,0))/12))) -> 0 | F89: =IF(F$5<Assumptions!$B$106,0,IF('Cash flow forecast'!F$5=Assumptions!$B$106,INDEX(Assumptions!$B$108:$B$112,MATCH('Cash flow forecast'!$B89,Assumptions!$A$108:$A$112,0))*(INDEX(Assumptions!$C$4:$C$46,MATCH("Total Queen",Assumptions!$A$4:$A$46,0))),(E89*(1+INDEX(Assumptions!$C$108:$C$112,MATCH('Cash flow forecast'!$B89,Assumptions!$A$108:$A$112,0))/12))*(1+INDEX(Assumptions!$D$108:$D$112,MATCH('Cash flow forecast'!$B89,Assumptions!$A$108:$A$112,0))/12))) -> 130 | G89: =IF(G$5<Assumptions!$B$106,0,IF('Cash flow forecast'!G$5=Assumptions!$B$106,INDEX(Assumptions!$B$108:$B$112,MATCH('Cash flow forecast'!$B89,Assumptions!$A$108:$A$112,0))*(INDEX(Assumptions!$C$4:$C$46,MATCH("Total Queen",Assumptions!$A$4:$A$46,0))),(F89*(1+INDEX(Assumptions!$C$108:$C$112,MATCH('Cash flow forecast'!$B89,Assumptions!$A$108:$A$112,0))/12))*(1+INDEX(Assumptions!$D$108:$D$112,MATCH('Cash flow forecast'!$B89,Assumptions!$A$108:$A$112,0))/12))) -> 130.3241 | H89: =IF(H$5<Assumptions!$B$106,0,IF('Cash flow forecast'!H$5=Assumptions!$B$106,INDEX(Assumptions!$B$108:$B$112,MATCH('Cash flow forecast'!$B89,Assumptions!$A$108:$A$112,0))*(INDEX(Assumptions!$C$4:$C$46,MATCH("Total Queen",Assumptions!$A$4:$A$46,0))),(G89*(1+INDEX(Assumptions!$C$108:$C$112,MATCH('Cash flow forecast'!$B89,Assumptions!$A$108:$A$112,0))/12))*(1+INDEX(Assumptions!$D$108:$D$112,MATCH('Cash flow forecast'!$B89,Assumptions!$A$108:$A$112,0))/12))) -> 130.649 | I89: =IF(I$5<Assumptions!$B$106,0,IF('Cash flow forecast'!I$5=Assumptions!$B$106,INDEX(Assumptions!$B$108:$B$112,MATCH('Cash flow forecast'!$B89,Assumptions!$A$108:$A$112,0))*(INDEX(Assumptions!$C$4:$C$46,MATCH("Total Queen",Assumptions!$A$4:$A$46,0))),(H89*(1+INDEX(Assumptions!$C$108:$C$112,MATCH('Cash flow forecast'!$B89,Assumptions!$A$108:$A$112,0))/12))*(1+INDEX(Assumptions!$D$108:$D$112,MATCH('Cash flow forecast'!$B89,Assumptions!$A$108:$A$112,0))/12))) -> 130.97472 | J89: =IF(J$5<Assumptions!$B$106,0,IF('Cash flow forecast'!J$5=Assumptions!$B$106,INDEX(Assumptions!$B$108:$B$112,MATCH('Cash flow forecast'!$B89,Assumptions!$A$108:$A$112,0))*(INDEX(Assumptions!$C$4:$C$46,MATCH("Total Queen",Assumptions!$A$4:$A$46,0))),(I89*(1+INDEX(Assumptions!$C$108:$C$112,MATCH('Cash flow forecast'!$B89,Assumptions!$A$108:$A$112,0))/12))*(1+INDEX(Assumptions!$D$108:$D$112,MATCH('Cash flow forecast'!$B89,Assumptions!$A$108:$A$112,0))/12))) -> 131.30124 | K89: =IF(K$5<Assumptions!$B$106,0,IF('Cash flow forecast'!K$5=Assumptions!$B$106,INDEX(Assumptions!$B$108:$B$112,MATCH('Cash flow forecast'!$B89,Assumptions!$A$108:$A$112,0))*(INDEX(Assumptions!$C$4:$C$46,MATCH("Total Queen",Assumptions!$A$4:$A$46,0))),(J89*(1+INDEX(Assumptions!$C$108:$C$112,MATCH('Cash flow forecast'!$B89,Assumptions!$A$108:$A$112,0))/12))*(1+INDEX(Assumptions!$D$108:$D$112,MATCH('Cash flow forecast'!$B89,Assumptions!$A$108:$A$112,0))/12))) -> 131.62859 | ... Z89: =IF(Z$5<Assumptions!$B$106,0,IF('Cash flow forecast'!Z$5=Assumptions!$B$106,INDEX(Assumptions!$B$108:$B$112,MATCH('Cash flow forecast'!$B89,Assumptions!$A$108:$A$112,0))*(INDEX(Assumptions!$C$4:$C$46,MATCH("Total Queen",Assumptions!$A$4:$A$46,0))),(Y89*(1+INDEX(Assumptions!$C$108:$C$112,MATCH('Cash flow forecast'!$B89,Assumptions!$A$108:$A$112,0))/12))*(1+INDEX(Assumptions!$D$108:$D$112,MATCH('Cash flow forecast'!$B89,Assumptions!$A$108:$A$112,0))/12))) -> 136.63778 | AA89: =SUMIFS($C89:$N89,$C$6:$N$6,AA$5) -> 264.90123 | AB89: =SUMIFS($C89:$N89,$C$6:$N$6,AB$5) -> 130 | AC89: =SUMIFS($C89:$N89,$C$6:$N$6,AC$5) -> 391.94782 | AD89: =SUMIFS($C89:$N89,$C$6:$N$6,AD$5) -> 394.88657 | AE89: =SUM($C89:$N89) -> 1181.7356 | AF89: =SUMIFS($O89:$Z89,$O$6:$Z$6,AF$5) -> 405.8819 | AG89: =SUMIFS($O89:$Z89,$O$6:$Z$6,AG$5) -> 400.83036 | AH89: =SUMIFS($O89:$Z89,$O$6:$Z$6,AH$5) -> 403.83571 | AI89: =SUMIFS($O89:$Z89,$O$6:$Z$6,AI$5) -> 406.86361 | AJ89: =SUM($O89:$Z89) -> 1617.4116 | AK89: =AVERAGE(AE89,AJ89)/AVERAGE($AE$106,$AJ$106) -> 0.0028357532
B90: King Package Orders | C90: =IF(C$5<Assumptions!$B$106,0,INDEX(Assumptions!$B$108:$B$112,MATCH('Cash flow forecast'!$B90,Assumptions!$A$108:$A$112,0))*(INDEX(Assumptions!$C$4:$C$46,MATCH("Total King",Assumptions!$A$4:$A$46,0)))) -> 0 | D90: =IF(D$5<Assumptions!$B$106,0,IF('Cash flow forecast'!D$5=Assumptions!$B$106,INDEX(Assumptions!$B$108:$B$112,MATCH('Cash flow forecast'!$B90,Assumptions!$A$108:$A$112,0))*(INDEX(Assumptions!$C$4:$C$46,MATCH("Total King",Assumptions!$A$4:$A$46,0))),(C90*(1+INDEX(Assumptions!$C$108:$C$112,MATCH('Cash flow forecast'!$B90,Assumptions!$A$108:$A$112,0))/12))*(1+INDEX(Assumptions!$D$108:$D$112,MATCH('Cash flow forecast'!$B90,Assumptions!$A$108:$A$112,0))/12))) -> 0 | E90: =IF(E$5<Assumptions!$B$106,0,IF('Cash flow forecast'!E$5=Assumptions!$B$106,INDEX(Assumptions!$B$108:$B$112,MATCH('Cash flow forecast'!$B90,Assumptions!$A$108:$A$112,0))*(INDEX(Assumptions!$C$4:$C$46,MATCH("Total King",Assumptions!$A$4:$A$46,0))),(D90*(1+INDEX(Assumptions!$C$108:$C$112,MATCH('Cash flow forecast'!$B90,Assumptions!$A$108:$A$112,0))/12))*(1+INDEX(Assumptions!$D$108:$D$112,MATCH('Cash flow forecast'!$B90,Assumptions!$A$108:$A$112,0))/12))) -> 0 | F90: =IF(F$5<Assumptions!$B$106,0,IF('Cash flow forecast'!F$5=Assumptions!$B$106,INDEX(Assumptions!$B$108:$B$112,MATCH('Cash flow forecast'!$B90,Assumptions!$A$108:$A$112,0))*(INDEX(Assumptions!$C$4:$C$46,MATCH("Total King",Assumptions!$A$4:$A$46,0))),(E90*(1+INDEX(Assumptions!$C$108:$C$112,MATCH('Cash flow forecast'!$B90,Assumptions!$A$108:$A$112,0))/12))*(1+INDEX(Assumptions!$D$108:$D$112,MATCH('Cash flow forecast'!$B90,Assumptions!$A$108:$A$112,0))/12))) -> 170 | G90: =IF(G$5<Assumptions!$B$106,0,IF('Cash flow forecast'!G$5=Assumptions!$B$106,INDEX(Assumptions!$B$108:$B$112,MATCH('Cash flow forecast'!$B90,Assumptions!$A$108:$A$112,0))*(INDEX(Assumptions!$C$4:$C$46,MATCH("Total King",Assumptions!$A$4:$A$46,0))),(F90*(1+INDEX(Assumptions!$C$108:$C$112,MATCH('Cash flow forecast'!$B90,Assumptions!$A$108:$A$112,0))/12))*(1+INDEX(Assumptions!$D$108:$D$112,MATCH('Cash flow forecast'!$B90,Assumptions!$A$108:$A$112,0))/12))) -> 170.42382 | H90: =IF(H$5<Assumptions!$B$106,0,IF('Cash flow forecast'!H$5=Assumptions!$B$106,INDEX(Assumptions!$B$108:$B$112,MATCH('Cash flow forecast'!$B90,Assumptions!$A$108:$A$112,0))*(INDEX(Assumptions!$C$4:$C$46,MATCH("Total King",Assumptions!$A$4:$A$46,0))),(G90*(1+INDEX(Assumptions!$C$108:$C$112,MATCH('Cash flow forecast'!$B90,Assumptions!$A$108:$A$112,0))/12))*(1+INDEX(Assumptions!$D$108:$D$112,MATCH('Cash flow forecast'!$B90,Assumptions!$A$108:$A$112,0))/12))) -> 170.8487 | I90: =IF(I$5<Assumptions!$B$106,0,IF('Cash flow forecast'!I$5=Assumptions!$B$106,INDEX(Assumptions!$B$108:$B$112,MATCH('Cash flow forecast'!$B90,Assumptions!$A$108:$A$112,0))*(INDEX(Assumptions!$C$4:$C$46,MATCH("Total King",Assumptions!$A$4:$A$46,0))),(H90*(1+INDEX(Assumptions!$C$108:$C$112,MATCH('Cash flow forecast'!$B90,Assumptions!$A$108:$A$112,0))/12))*(1+INDEX(Assumptions!$D$108:$D$112,MATCH('Cash flow forecast'!$B90,Assumptions!$A$108:$A$112,0))/12))) -> 171.27463 | J90: =IF(J$5<Assumptions!$B$106,0,IF('Cash flow forecast'!J$5=Assumptions!$B$106,INDEX(Assumptions!$B$108:$B$112,MATCH('Cash flow forecast'!$B90,Assumptions!$A$108:$A$112,0))*(INDEX(Assumptions!$C$4:$C$46,MATCH("Total King",Assumptions!$A$4:$A$46,0))),(I90*(1+INDEX(Assumptions!$C$108:$C$112,MATCH('Cash flow forecast'!$B90,Assumptions!$A$108:$A$112,0))/12))*(1+INDEX(Assumptions!$D$108:$D$112,MATCH('Cash flow forecast'!$B90,Assumptions!$A$108:$A$112,0))/12))) -> 171.70163 | K90: =IF(K$5<Assumptions!$B$106,0,IF('Cash flow forecast'!K$5=Assumptions!$B$106,INDEX(Assumptions!$B$108:$B$112,MATCH('Cash flow forecast'!$B90,Assumptions!$A$108:$A$112,0))*(INDEX(Assumptions!$C$4:$C$46,MATCH("Total King",Assumptions!$A$4:$A$46,0))),(J90*(1+INDEX(Assumptions!$C$108:$C$112,MATCH('Cash flow forecast'!$B90,Assumptions!$A$108:$A$112,0))/12))*(1+INDEX(Assumptions!$D$108:$D$112,MATCH('Cash flow forecast'!$B90,Assumptions!$A$108:$A$112,0))/12))) -> 172.12969 | ... Z90: =IF(Z$5<Assumptions!$B$106,0,IF('Cash flow forecast'!Z$5=Assumptions!$B$106,INDEX(Assumptions!$B$108:$B$112,MATCH('Cash flow forecast'!$B90,Assumptions!$A$108:$A$112,0))*(INDEX(Assumptions!$C$4:$C$46,MATCH("Total King",Assumptions!$A$4:$A$46,0))),(Y90*(1+INDEX(Assumptions!$C$108:$C$112,MATCH('Cash flow forecast'!$B90,Assumptions!$A$108:$A$112,0))/12))*(1+INDEX(Assumptions!$D$108:$D$112,MATCH('Cash flow forecast'!$B90,Assumptions!$A$108:$A$112,0))/12))) -> 178.68018 | AA90: =SUMIFS($C90:$N90,$C$6:$N$6,AA$5) -> 346.40931 | AB90: =SUMIFS($C90:$N90,$C$6:$N$6,AB$5) -> 170 | AC90: =SUMIFS($C90:$N90,$C$6:$N$6,AC$5) -> 512.54715 | AD90: =SUMIFS($C90:$N90,$C$6:$N$6,AD$5) -> 516.39014 | AE90: =SUM($C90:$N90) -> 1545.3466 | AF90: =SUMIFS($O90:$Z90,$O$6:$Z$6,AF$5) -> 530.76864 | AG90: =SUMIFS($O90:$Z90,$O$6:$Z$6,AG$5) -> 524.16278 | AH90: =SUMIFS($O90:$Z90,$O$6:$Z$6,AH$5) -> 528.09286 | AI90: =SUMIFS($O90:$Z90,$O$6:$Z$6,AI$5) -> 532.05241 | AJ90: =SUM($O90:$Z90) -> 2115.0767 | AK90: =AVERAGE(AE90,AJ90)/AVERAGE($AE$106,$AJ$106) -> 0.0037082926
B91: Universal Package Orders | C91: =IF(C$5<Assumptions!$B$106,0,INDEX(Assumptions!$B$108:$B$112,MATCH('Cash flow forecast'!$B91,Assumptions!$A$108:$A$112,0))*(INDEX(Assumptions!$C$4:$C$46,MATCH("Total Universal",Assumptions!$A$4:$A$46,0)))) -> 0 | D91: =IF(D$5<Assumptions!$B$106,0,IF('Cash flow forecast'!D$5=Assumptions!$B$106,INDEX(Assumptions!$B$108:$B$112,MATCH('Cash flow forecast'!$B91,Assumptions!$A$108:$A$112,0))*(INDEX(Assumptions!$C$4:$C$46,MATCH("Total Universal",Assumptions!$A$4:$A$46,0))),(C91*(1+INDEX(Assumptions!$C$108:$C$112,MATCH('Cash flow forecast'!$B91,Assumptions!$A$108:$A$112,0))/12))*(1+INDEX(Assumptions!$D$108:$D$112,MATCH('Cash flow forecast'!$B91,Assumptions!$A$108:$A$112,0))/12))) -> 0 | E91: =IF(E$5<Assumptions!$B$106,0,IF('Cash flow forecast'!E$5=Assumptions!$B$106,INDEX(Assumptions!$B$108:$B$112,MATCH('Cash flow forecast'!$B91,Assumptions!$A$108:$A$112,0))*(INDEX(Assumptions!$C$4:$C$46,MATCH("Total Universal",Assumptions!$A$4:$A$46,0))),(D91*(1+INDEX(Assumptions!$C$108:$C$112,MATCH('Cash flow forecast'!$B91,Assumptions!$A$108:$A$112,0))/12))*(1+INDEX(Assumptions!$D$108:$D$112,MATCH('Cash flow forecast'!$B91,Assumptions!$A$108:$A$112,0))/12))) -> 0 | F91: =IF(F$5<Assumptions!$B$106,0,IF('Cash flow forecast'!F$5=Assumptions!$B$106,INDEX(Assumptions!$B$108:$B$112,MATCH('Cash flow forecast'!$B91,Assumptions!$A$108:$A$112,0))*(INDEX(Assumptions!$C$4:$C$46,MATCH("Total Universal",Assumptions!$A$4:$A$46,0))),(E91*(1+INDEX(Assumptions!$C$108:$C$112,MATCH('Cash flow forecast'!$B91,Assumptions!$A$108:$A$112,0))/12))*(1+INDEX(Assumptions!$D$108:$D$112,MATCH('Cash flow forecast'!$B91,Assumptions!$A$108:$A$112,0))/12))) -> 43.55 | G91: =IF(G$5<Assumptions!$B$106,0,IF('Cash flow forecast'!G$5=Assumptions!$B$106,INDEX(Assumptions!$B$108:$B$112,MATCH('Cash flow forecast'!$B91,Assumptions!$A$108:$A$112,0))*(INDEX(Assumptions!$C$4:$C$46,MATCH("Total Universal",Assumptions!$A$4:$A$46,0))),(F91*(1+INDEX(Assumptions!$C$108:$C$112,MATCH('Cash flow forecast'!$B91,Assumptions!$A$108:$A$112,0))/12))*(1+INDEX(Assumptions!$D$108:$D$112,MATCH('Cash flow forecast'!$B91,Assumptions!$A$108:$A$112,0))/12))) -> 43.658573 | H91: =IF(H$5<Assumptions!$B$106,0,IF('Cash flow forecast'!H$5=Assumptions!$B$106,INDEX(Assumptions!$B$108:$B$112,MATCH('Cash flow forecast'!$B91,Assumptions!$A$108:$A$112,0))*(INDEX(Assumptions!$C$4:$C$46,MATCH("Total Universal",Assumptions!$A$4:$A$46,0))),(G91*(1+INDEX(Assumptions!$C$108:$C$112,MATCH('Cash flow forecast'!$B91,Assumptions!$A$108:$A$112,0))/12))*(1+INDEX(Assumptions!$D$108:$D$112,MATCH('Cash flow forecast'!$B91,Assumptions!$A$108:$A$112,0))/12))) -> 43.767416 | I91: =IF(I$5<Assumptions!$B$106,0,IF('Cash flow forecast'!I$5=Assumptions!$B$106,INDEX(Assumptions!$B$108:$B$112,MATCH('Cash flow forecast'!$B91,Assumptions!$A$108:$A$112,0))*(INDEX(Assumptions!$C$4:$C$46,MATCH("Total Universal",Assumptions!$A$4:$A$46,0))),(H91*(1+INDEX(Assumptions!$C$108:$C$112,MATCH('Cash flow forecast'!$B91,Assumptions!$A$108:$A$112,0))/12))*(1+INDEX(Assumptions!$D$108:$D$112,MATCH('Cash flow forecast'!$B91,Assumptions!$A$108:$A$112,0))/12))) -> 43.87653 | J91: =IF(J$5<Assumptions!$B$106,0,IF('Cash flow forecast'!J$5=Assumptions!$B$106,INDEX(Assumptions!$B$108:$B$112,MATCH('Cash flow forecast'!$B91,Assumptions!$A$108:$A$112,0))*(INDEX(Assumptions!$C$4:$C$46,MATCH("Total Universal",Assumptions!$A$4:$A$46,0))),(I91*(1+INDEX(Assumptions!$C$108:$C$112,MATCH('Cash flow forecast'!$B91,Assumptions!$A$108:$A$112,0))/12))*(1+INDEX(Assumptions!$D$108:$D$112,MATCH('Cash flow forecast'!$B91,Assumptions!$A$108:$A$112,0))/12))) -> 43.985917 | K91: =IF(K$5<Assumptions!$B$106,0,IF('Cash flow forecast'!K$5=Assumptions!$B$106,INDEX(Assumptions!$B$108:$B$112,MATCH('Cash flow forecast'!$B91,Assumptions!$A$108:$A$112,0))*(INDEX(Assumptions!$C$4:$C$46,MATCH("Total Universal",Assumptions!$A$4:$A$46,0))),(J91*(1+INDEX(Assumptions!$C$108:$C$112,MATCH('Cash flow forecast'!$B91,Assumptions!$A$108:$A$112,0))/12))*(1+INDEX(Assumptions!$D$108:$D$112,MATCH('Cash flow forecast'!$B91,Assumptions!$A$108:$A$112,0))/12))) -> 44.095576 | ... Z91: =IF(Z$5<Assumptions!$B$106,0,IF('Cash flow forecast'!Z$5=Assumptions!$B$106,INDEX(Assumptions!$B$108:$B$112,MATCH('Cash flow forecast'!$B91,Assumptions!$A$108:$A$112,0))*(INDEX(Assumptions!$C$4:$C$46,MATCH("Total Universal",Assumptions!$A$4:$A$46,0))),(Y91*(1+INDEX(Assumptions!$C$108:$C$112,MATCH('Cash flow forecast'!$B91,Assumptions!$A$108:$A$112,0))/12))*(1+INDEX(Assumptions!$D$108:$D$112,MATCH('Cash flow forecast'!$B91,Assumptions!$A$108:$A$112,0))/12))) -> 45.773658 | AA91: =SUMIFS($C91:$N91,$C$6:$N$6,AA$5) -> 88.741913 | AB91: =SUMIFS($C91:$N91,$C$6:$N$6,AB$5) -> 43.55 | AC91: =SUMIFS($C91:$N91,$C$6:$N$6,AC$5) -> 131.30252 | AD91: =SUMIFS($C91:$N91,$C$6:$N$6,AD$5) -> 132.287 | AE91: =SUM($C91:$N91) -> 395.88143 | AF91: =SUMIFS($O91:$Z91,$O$6:$Z$6,AF$5) -> 135.97044 | AG91: =SUMIFS($O91:$Z91,$O$6:$Z$6,AG$5) -> 134.27817 | AH91: =SUMIFS($O91:$Z91,$O$6:$Z$6,AH$5) -> 135.28496 | AI91: =SUMIFS($O91:$Z91,$O$6:$Z$6,AI$5) -> 136.29931 | AJ91: =SUM($O91:$Z91) -> 541.83288 | AK91: =AVERAGE(AE91,AJ91)/AVERAGE($AE$106,$AJ$106) -> 0.00094997732
B92: Total Retail Costs | C92: =SUM(C87:C91) -> 0 | D92: =SUM(D87:D91) -> 0 | E92: =SUM(E87:E91) -> 0 | F92: =SUM(F87:F91) -> 510.6 | G92: =SUM(G87:G91) -> 512.25294 | H92: =SUM(H87:H91) -> 513.91254 | I92: =SUM(I87:I91) -> 515.57881 | J92: =SUM(J87:J91) -> 517.25181 | ... AD92: =SUM(AD87:AD91) -> 1556.8014 | AE92: =SUM($C92:$N92) -> 4655.4688 | AF92: =SUM(AF87:AF91) -> 1613.8559 | AG92: =SUM(AG87:AG91) -> 1587.468 | AH92: =SUM(AH87:AH91) -> 1603.083 | AI92: =SUM(AI87:AI91) -> 1618.8897 | AJ92: =SUM($O92:$Z92) -> 6423.2966 | AK92: =AVERAGE(AE92,AJ92)/AVERAGE($AE$106,$AJ$106) -> 0.011223648
B93: Licensing Costs:
B94: Exclusive:
B95: Initial Fee | C95: 0 | D95: 0 | E95: 0 | F95: 0 | G95: 0 | H95: 0 | I95: 0 | J95: 0 | K95: 0 | L95: 0 | M95: 0 | N95: 0 | O95: 0 | P95: 0 | Q95: 0 | R95: 0 | S95: 0 | T95: 0 | U95: 0 | V95: 0 | W95: 0 | X95: 0 | Y95: 0 | Z95: 0 | AA95: =SUMIFS($C95:$N95,$C$6:$N$6,AA$5) -> 0 | AB95: =SUMIFS($C95:$N95,$C$6:$N$6,AB$5) -> 0 | AC95: =SUMIFS($C95:$N95,$C$6:$N$6,AC$5) -> 0 | AD95: =SUMIFS($C95:$N95,$C$6:$N$6,AD$5) -> 0 | AE95: =SUM($C95:$N95) -> 0 | AF95: =SUMIFS($C95:$N95,$C$6:$N$6,AF$5) -> 0 | AG95: =SUMIFS($C95:$N95,$C$6:$N$6,AG$5) -> 0 | AH95: =SUMIFS($C95:$N95,$C$6:$N$6,AH$5) -> 0 | AI95: =SUMIFS($C95:$N95,$C$6:$N$6,AI$5) -> 0 | AJ95: =SUM($C95:$N95) -> 0 | AK95: =AVERAGE(AE95,AJ95)/AVERAGE($AE$106,$AJ$106) -> 0
B96: Rev. Share Costs | C96: 0 | D96: 0 | E96: 0 | F96: 0 | G96: 0 | H96: 0 | I96: 0 | J96: 0 | K96: 0 | L96: 0 | M96: 0 | N96: 0 | O96: 0 | P96: 0 | Q96: 0 | R96: 0 | S96: 0 | T96: 0 | U96: 0 | V96: 0 | W96: 0 | X96: 0 | Y96: 0 | Z96: 0 | AA96: =SUMIFS($C96:$N96,$C$6:$N$6,AA$5) -> 0 | AB96: =SUMIFS($C96:$N96,$C$6:$N$6,AB$5) -> 0 | AC96: =SUMIFS($C96:$N96,$C$6:$N$6,AC$5) -> 0 | AD96: =SUMIFS($C96:$N96,$C$6:$N$6,AD$5) -> 0 | AE96: =SUM($C96:$N96) -> 0 | AF96: =SUMIFS($C96:$N96,$C$6:$N$6,AF$5) -> 0 | AG96: =SUMIFS($C96:$N96,$C$6:$N$6,AG$5) -> 0 | AH96: =SUMIFS($C96:$N96,$C$6:$N$6,AH$5) -> 0 | AI96: =SUMIFS($C96:$N96,$C$6:$N$6,AI$5) -> 0 | AJ96: =SUM($C96:$N96) -> 0 | AK96: =AVERAGE(AE96,AJ96)/AVERAGE($AE$106,$AJ$106) -> 0
B97: Units | C97: 0 | D97: 0 | E97: 0 | F97: 0 | G97: 0 | H97: 0 | I97: 0 | J97: 0 | K97: 0 | L97: 0 | M97: 0 | N97: 0 | O97: 0 | P97: 0 | Q97: 0 | R97: 0 | S97: 0 | T97: 0 | U97: 0 | V97: 0 | W97: 0 | X97: 0 | Y97: 0 | Z97: 0 | AA97: =SUMIFS($C97:$N97,$C$6:$N$6,AA$5) -> 0 | AB97: =SUMIFS($C97:$N97,$C$6:$N$6,AB$5) -> 0 | AC97: =SUMIFS($C97:$N97,$C$6:$N$6,AC$5) -> 0 | AD97: =SUMIFS($C97:$N97,$C$6:$N$6,AD$5) -> 0 | AE97: =SUM($C97:$N97) -> 0 | AF97: =SUMIFS($C97:$N97,$C$6:$N$6,AF$5) -> 0 | AG97: =SUMIFS($C97:$N97,$C$6:$N$6,AG$5) -> 0 | AH97: =SUMIFS($C97:$N97,$C$6:$N$6,AH$5) -> 0 | AI97: =SUMIFS($C97:$N97,$C$6:$N$6,AI$5) -> 0 | AJ97: =SUM($C97:$N97) -> 0 | AK97: =AVERAGE(AE97,AJ97)/AVERAGE($AE$106,$AJ$106) -> 0
B98: Total Exclusive Costs | C98: =C96+C95 -> 0 | D98: =D96+D95 -> 0 | E98: =E96+E95 -> 0 | F98: =F96+F95 -> 0 | G98: =G96+G95 -> 0 | H98: =H96+H95 -> 0 | I98: =I96+I95 -> 0 | J98: =J96+J95 -> 0 | ... AJ98: =AJ96+AJ95 -> 0 | AK98: =AVERAGE(AE98,AJ98)/AVERAGE($AE$106,$AJ$106) -> 0
B99: Non-Exclusive:
B100: Rev. Share Costs | C100: 0 | D100: 0 | E100: 0 | F100: 0 | G100: 0 | H100: 0 | I100: 0 | J100: 0 | K100: 0 | L100: 0 | M100: 0 | N100: 0 | O100: 0 | P100: 0 | Q100: 0 | R100: 0 | S100: 0 | T100: 0 | U100: 0 | V100: 0 | W100: 0 | X100: 0 | Y100: 0 | Z100: 0 | AA100: =SUMIFS($C100:$N100,$C$6:$N$6,AA$5) -> 0 | AB100: =SUMIFS($C100:$N100,$C$6:$N$6,AB$5) -> 0 | AC100: =SUMIFS($C100:$N100,$C$6:$N$6,AC$5) -> 0 | AD100: =SUMIFS($C100:$N100,$C$6:$N$6,AD$5) -> 0 | AE100: =SUM($C100:$N100) -> 0 | AF100: =SUMIFS($C100:$N100,$C$6:$N$6,AF$5) -> 0 | AG100: =SUMIFS($C100:$N100,$C$6:$N$6,AG$5) -> 0 | AH100: =SUMIFS($C100:$N100,$C$6:$N$6,AH$5) -> 0 | AI100: =SUMIFS($C100:$N100,$C$6:$N$6,AI$5) -> 0 | AJ100: =SUM($C100:$N100) -> 0 | AK100: =AVERAGE(AE100,AJ100)/AVERAGE($AE$106,$AJ$106) -> 0
B101: Units | C101: 0 | D101: 0 | E101: 0 | F101: 0 | G101: 0 | H101: 0 | I101: 0 | J101: 0 | K101: 0 | L101: 0 | M101: 0 | N101: 0 | O101: 0 | P101: 0 | Q101: 0 | R101: 0 | S101: 0 | T101: 0 | U101: 0 | V101: 0 | W101: 0 | X101: 0 | Y101: 0 | Z101: 0 | AA101: =SUMIFS($C101:$N101,$C$6:$N$6,AA$5) -> 0 | AB101: =SUMIFS($C101:$N101,$C$6:$N$6,AB$5) -> 0 | AC101: =SUMIFS($C101:$N101,$C$6:$N$6,AC$5) -> 0 | AD101: =SUMIFS($C101:$N101,$C$6:$N$6,AD$5) -> 0 | AE101: =SUM($C101:$N101) -> 0 | AF101: =SUMIFS($C101:$N101,$C$6:$N$6,AF$5) -> 0 | AG101: =SUMIFS($C101:$N101,$C$6:$N$6,AG$5) -> 0 | AH101: =SUMIFS($C101:$N101,$C$6:$N$6,AH$5) -> 0 | AI101: =SUMIFS($C101:$N101,$C$6:$N$6,AI$5) -> 0 | AJ101: =SUM($C101:$N101) -> 0 | AK101: =AVERAGE(AE101,AJ101)/AVERAGE($AE$106,$AJ$106) -> 0
B102: Total Non-Exclusive Costs | C102: =C100 -> 0 | D102: =D100 -> 0 | E102: =E100 -> 0 | F102: =F100 -> 0 | G102: =G100 -> 0 | H102: =H100 -> 0 | I102: =I100 -> 0 | J102: =J100 -> 0 | ... Z102: =Z100 -> 0 | AA102: =AA100+AA99 -> 0 | AB102: =AB100+AB99 -> 0 | AC102: =AC100+AC99 -> 0 | AD102: =AD100+AD99 -> 0 | AE102: =AE100+AE99 -> 0 | AF102: =AF100+AF99 -> 0 | AG102: =AG100+AG99 -> 0 | AH102: =AH100+AH99 -> 0 | ... AJ102: =AJ100+AJ99 -> 0 | AK102: =AVERAGE(AE102,AJ102)/AVERAGE($AE$106,$AJ$106) -> 0
B104: Total Licensing Costs | C104: =SUM(C102,C98) -> 0 | D104: =SUM(D102,D98) -> 0 | E104: =SUM(E102,E98) -> 0 | F104: =SUM(F102,F98) -> 0 | G104: =SUM(G102,G98) -> 0 | H104: =SUM(H102,H98) -> 0 | I104: =SUM(I102,I98) -> 0 | J104: =SUM(J102,J98) -> 0 | ... AJ104: =SUM(AJ102,AJ98) -> 0 | AK104: =AVERAGE(AE104,AJ104)/AVERAGE($AE$106,$AJ$106) -> 0
B106: Total Operating Costs | C106: =C85+C92+C104 -> 136641.75 | D106: =D85+D92+D104 -> 0 | E106: =E85+E92+E104 -> 78081 | F106: =F85+F92+F104 -> 510.6 | G106: =G85+G92+G104 -> 512.25294 | H106: =H85+H92+H104 -> 513.91254 | I106: =I85+I92+I104 -> 137157.33 | J106: =J85+J92+J104 -> 517.25181 | ... AJ106: =AJ85+AJ92+AJ104 -> 552990.3
B108: Gross Profit
B110: Wholesale Profit: | AK110: Annual % of Revenue
...

Sheet Formatting
C1: Month
B2: Q1 | C2: 1
B3: Q1 | C3: =C2+1 -> 2
B4: Q1 | C4: =C3+1 -> 3
B5: Q2 | C5: =C4+1 -> 4
B6: Q2 | C6: =C5+1 -> 5
B7: Q2 | C7: =C6+1 -> 6
B8: Q3 | C8: =C7+1 -> 7
B9: Q3 | C9: =C8+1 -> 8
B10: Q3 | C10: =C9+1 -> 9
B11: Q4 | C11: =C10+1 -> 10
B12: Q4 | C12: =C11+1 -> 11
B13: Q4 | C13: =C12+1 -> 12
A20: Small Hotels
A22: # of Reorders | B22: # of Reorders/Yr | C22: #of hotels | E22: Start | F22: Reorders--->
A23: =C23*B23 -> 5 | B23: =Assumptions!$B$57 -> 1 | C23: =Assumptions!$B$51 -> 5 | D23: Start hotels | E23: =Assumptions!$B$2 -> 45809 | F23: =EDATE(E23,Assumptions!$B$58) -> 45992 | G23: =EDATE(F23,Assumptions!$B$58) -> 46174 | H23: =EDATE(G23,Assumptions!$B$58) -> 46357 | I23: =EDATE(H23,Assumptions!$B$58) -> 46539 | J23: =EDATE(I23,Assumptions!$B$58) -> 46722 | K23: =EDATE(J23,Assumptions!$B$58) -> 46905 | L23: =EDATE(K23,Assumptions!$B$58) -> 47088 | M23: =EDATE(L23,Assumptions!$B$58) -> 47270 | ... T23: =EDATE(S23,Assumptions!$B$58) -> 48549
E24: =$A$23 -> 5 | F24: =$A$23 -> 5 | G24: =$A$23 -> 5 | H24: =$A$23 -> 5 | I24: =$A$23 -> 5 | J24: =$A$23 -> 5 | K24: =$A$23 -> 5 | L24: =$A$23 -> 5 | ... T24: =$A$23 -> 5
A25: =C25*B25 -> 2 | B25: =Assumptions!$B$57 -> 1 | C25: =Assumptions!$B$52 -> 2 | D25: New hotels in Yr1 | E25: =EDATE($E$23,Assumptions!$B$54) -> 45870 | F25: =EDATE(E25,Assumptions!$B$58) -> 46054 | G25: =EDATE(F25,Assumptions!$B$58) -> 46235 | H25: =EDATE(G25,Assumptions!$B$58) -> 46419 | I25: =EDATE(H25,Assumptions!$B$58) -> 46600 | J25: =EDATE(I25,Assumptions!$B$58) -> 46784 | K25: =EDATE(J25,Assumptions!$B$58) -> 46966 | L25: =EDATE(K25,Assumptions!$B$58) -> 47150 | M25: =EDATE(L25,Assumptions!$B$58) -> 47331 | ... T25: =EDATE(S25,Assumptions!$B$58) -> 48611
E26: =$A$25 -> 2 | F26: =$A$25 -> 2 | G26: =$A$25 -> 2 | H26: =$A$25 -> 2 | I26: =$A$25 -> 2 | J26: =$A$25 -> 2 | K26: =$A$25 -> 2 | L26: =$A$25 -> 2 | ... T26: =$A$25 -> 2
A27: =C27*B27 -> 5 | B27: =Assumptions!$B$57 -> 1 | C27: =Assumptions!$C$52 -> 5 | D27: New hotels in Yr 2 | E27: =EDATE($E$23,Assumptions!$C$54+12) -> 46447 | F27: =EDATE(E27,Assumptions!$B$58) -> 46631 | G27: =EDATE(F27,Assumptions!$B$58) -> 46813 | H27: =EDATE(G27,Assumptions!$B$58) -> 46997 | I27: =EDATE(H27,Assumptions!$B$58) -> 47178 | J27: =EDATE(I27,Assumptions!$B$58) -> 47362 | K27: =EDATE(J27,Assumptions!$B$58) -> 47543 | L27: =EDATE(K27,Assumptions!$B$58) -> 47727 | M27: =EDATE(L27,Assumptions!$B$58) -> 47908 | ... T27: =EDATE(S27,Assumptions!$B$58) -> 49188
E28: =$A$27 -> 5 | F28: =$A$27 -> 5 | G28: =$A$27 -> 5 | H28: =$A$27 -> 5 | I28: =$A$27 -> 5 | J28: =$A$27 -> 5 | K28: =$A$27 -> 5 | L28: =$A$27 -> 5 | ... T28: =$A$27 -> 5
A30: Medium Hotels
A32: # of Reorders | B32: # of Reorders/Yr | C32: #of hotels | E32: Start | F32: Reorders--->
A33: =C33*B33 -> 1 | B33: =Assumptions!$B$75 -> 1 | C33: =Assumptions!$B$70 -> 1 | D33: Start hotels | E33: =Assumptions!$B$2 -> 45809 | F33: =EDATE(E33,Assumptions!$B$58) -> 45992 | G33: =EDATE(F33,Assumptions!$B$58) -> 46174 | H33: =EDATE(G33,Assumptions!$B$58) -> 46357 | I33: =EDATE(H33,Assumptions!$B$58) -> 46539 | J33: =EDATE(I33,Assumptions!$B$58) -> 46722 | K33: =EDATE(J33,Assumptions!$B$58) -> 46905 | L33: =EDATE(K33,Assumptions!$B$58) -> 47088 | M33: =EDATE(L33,Assumptions!$B$58) -> 47270 | ... T33: =EDATE(S33,Assumptions!$B$58) -> 48549
E34: =$A$33 -> 1 | F34: =$A$33 -> 1 | G34: =$A$33 -> 1 | H34: =$A$33 -> 1 | I34: =$A$33 -> 1 | J34: =$A$33 -> 1 | K34: =$A$33 -> 1 | L34: =$A$33 -> 1 | ... T34: =$A$33 -> 1
A35: =C35*B35 -> 1 | B35: =Assumptions!$B$75 -> 1 | C35: =Assumptions!$B$71 -> 1 | D35: New hotels in Yr1 | E35: =EDATE($E$23,Assumptions!$B$54) -> 45870 | F35: =EDATE(E35,Assumptions!$B$58) -> 46054 | G35: =EDATE(F35,Assumptions!$B$58) -> 46235 | H35: =EDATE(G35,Assumptions!$B$58) -> 46419 | I35: =EDATE(H35,Assumptions!$B$58) -> 46600 | J35: =EDATE(I35,Assumptions!$B$58) -> 46784 | K35: =EDATE(J35,Assumptions!$B$58) -> 46966 | L35: =EDATE(K35,Assumptions!$B$58) -> 47150 | M35: =EDATE(L35,Assumptions!$B$58) -> 47331 | ... T35: =EDATE(S35,Assumptions!$B$58) -> 48611
E36: =$A$35 -> 1 | F36: =$A$35 -> 1 | G36: =$A$35 -> 1 | H36: =$A$35 -> 1 | I36: =$A$35 -> 1 | J36: =$A$35 -> 1 | K36: =$A$35 -> 1 | L36: =$A$35 -> 1 | ... T36: =$A$35 -> 1
A37: =C37*B37 -> 0 | B37: =Assumptions!$B$75 -> 1 | C37: =Assumptions!$C$71 -> 0 | D37: New hotels in Yr 2 | E37: =EDATE($E$23,Assumptions!$C$54+12) -> 46447 | F37: =EDATE(E37,Assumptions!$B$58) -> 46631 | G37: =EDATE(F37,Assumptions!$B$58) -> 46813 | H37: =EDATE(G37,Assumptions!$B$58) -> 46997 | I37: =EDATE(H37,Assumptions!$B$58) -> 47178 | J37: =EDATE(I37,Assumptions!$B$58) -> 47362 | K37: =EDATE(J37,Assumptions!$B$58) -> 47543 | L37: =EDATE(K37,Assumptions!$B$58) -> 47727 | M37: =EDATE(L37,Assumptions!$B$58) -> 47908 | ... T37: =EDATE(S37,Assumptions!$B$58) -> 49188
E38: =$A$37 -> 0 | F38: =$A$37 -> 0 | G38: =$A$37 -> 0 | H38: =$A$37 -> 0 | I38: =$A$37 -> 0 | J38: =$A$37 -> 0 | K38: =$A$37 -> 0 | L38: =$A$37 -> 0 | ... T38: =$A$37 -> 0
A40: Large Hotels
A42: # of Reorders | B42: # of Reorders/Yr | C42: #of hotels | E42: Start | F42: Reorders--->
A43: =C43*B43 -> 1 | B43: =Assumptions!$B$93 -> 1 | C43: =Assumptions!$B$88 -> 1 | D43: Start hotels | E43: =Assumptions!$B$2 -> 45809 | F43: =EDATE(E43,Assumptions!$B$58) -> 45992 | G43: =EDATE(F43,Assumptions!$B$58) -> 46174 | H43: =EDATE(G43,Assumptions!$B$58) -> 46357 | I43: =EDATE(H43,Assumptions!$B$58) -> 46539 | J43: =EDATE(I43,Assumptions!$B$58) -> 46722 | K43: =EDATE(J43,Assumptions!$B$58) -> 46905 | L43: =EDATE(K43,Assumptions!$B$58) -> 47088 | M43: =EDATE(L43,Assumptions!$B$58) -> 47270 | ... T43: =EDATE(S43,Assumptions!$B$58) -> 48549
E44: =$A$43 -> 1 | F44: =$A$43 -> 1 | G44: =$A$43 -> 1 | H44: =$A$43 -> 1 | I44: =$A$43 -> 1 | J44: =$A$43 -> 1 | K44: =$A$43 -> 1 | L44: =$A$43 -> 1 | ... T44: =$A$43 -> 1
A45: =C45*B45 -> 1 | B45: =Assumptions!$B$93 -> 1 | C45: =Assumptions!$B$89 -> 1 | D45: New hotels in Yr1 | E45: =EDATE($E$23,Assumptions!$B$54) -> 45870 | F45: =EDATE(E45,Assumptions!$B$58) -> 46054 | G45: =EDATE(F45,Assumptions!$B$58) -> 46235 | H45: =EDATE(G45,Assumptions!$B$58) -> 46419 | I45: =EDATE(H45,Assumptions!$B$58) -> 46600 | J45: =EDATE(I45,Assumptions!$B$58) -> 46784 | K45: =EDATE(J45,Assumptions!$B$58) -> 46966 | L45: =EDATE(K45,Assumptions!$B$58) -> 47150 | M45: =EDATE(L45,Assumptions!$B$58) -> 47331 | ... T45: =EDATE(S45,Assumptions!$B$58) -> 48611
E46: =$A$45 -> 1 | F46: =$A$45 -> 1 | G46: =$A$45 -> 1 | H46: =$A$45 -> 1 | I46: =$A$45 -> 1 | J46: =$A$45 -> 1 | K46: =$A$45 -> 1 | L46: =$A$45 -> 1 | ... T46: =$A$45 -> 1
A47: =C47*B47 -> 1 | B47: =Assumptions!$B$93 -> 1 | C47: =Assumptions!$C$89 -> 1 | D47: New hotels in Yr 2 | E47: =EDATE($E$23,Assumptions!$C$54+12) -> 46447 | F47: =EDATE(E47,Assumptions!$B$58) -> 46631 | G47: =EDATE(F47,Assumptions!$B$58) -> 46813 | H47: =EDATE(G47,Assumptions!$B$58) -> 46997 | I47: =EDATE(H47,Assumptions!$B$58) -> 47178 | J47: =EDATE(I47,Assumptions!$B$58) -> 47362 | K47: =EDATE(J47,Assumptions!$B$58) -> 47543 | L47: =EDATE(K47,Assumptions!$B$58) -> 47727 | M47: =EDATE(L47,Assumptions!$B$58) -> 47908 | ... T47: =EDATE(S47,Assumptions!$B$58) -> 49188
E48: =$A$47 -> 1 | F48: =$A$47 -> 1 | G48: =$A$47 -> 1 | H48: =$A$47 -> 1 | I48: =$A$47 -> 1 | J48: =$A$47 -> 1 | K48: =$A$47 -> 1 | L48: =$A$47 -> 1 | ... T48: =$A$47 -> 1

Sheet Unit Costs
C2: =Assumptions!B3 -> TC250
C3: Cost/Unit | D3: TC200 | E3: TC250 | F3: B6257 | G3: TC300
B4: Twin Package:
B5: Twin Top Sheet | C5: =INDEX($D5:$G5,MATCH($C$2,$D$3:$G$3,0)) -> 5.14 | D5: 4.99 | E5: 5.14 | F5: 5.65 | G5: 6.36
B6: Twin Bottom Sheet | C6: =INDEX($D6:$G6,MATCH($C$2,$D$3:$G$3,0)) -> 0
B7: Twin Decorative Sheet | C7: =INDEX($D7:$G7,MATCH($C$2,$D$3:$G$3,0)) -> 6.15 | D7: 5.97 | E7: 6.15 | F7: 6.74 | G7: 7.62
B8: Twin Fitted Sheet | C8: =INDEX($D8:$G8,MATCH($C$2,$D$3:$G$3,0)) -> 5.84 | D8: 5.66 | E8: 5.84 | F8: 6.37 | G8: 7.21
B9: Std Pillow Case | C9: =INDEX($D9:$G9,MATCH($C$2,$D$3:$G$3,0)) -> 1.14 | D9: 1.11 | E9: 1.14 | F9: 1.24 | G9: 1.39
B10: Total Twin | C10: =SUM(C5:C9) -> 18.27
B12: Full Package:
B13: Full Top Sheet | C13: =INDEX($D13:$G13,MATCH($C$2,$D$3:$G$3,0)) -> 4 | D13: 4 | E13: 4 | F13: 4 | G13: 6
B14: Full Bottom Sheet | C14: =INDEX($D14:$G14,MATCH($C$2,$D$3:$G$3,0)) -> 0
B15: Full Decorative Sheet | C15: =INDEX($D15:$G15,MATCH($C$2,$D$3:$G$3,0)) -> 7 | D15: 4 | E15: 7 | F15: 2 | G15: 8
B16: Full Fitted Sheet | C16: =INDEX($D16:$G16,MATCH($C$2,$D$3:$G$3,0)) -> 3 | D16: 9 | E16: 3 | F16: 4 | G16: 10
B17: Std Pillow Case | C17: =INDEX($D17:$G17,MATCH($C$2,$D$3:$G$3,0)) -> 9 | D17: 9 | E17: 9 | F17: 4 | G17: 7
B18: Total Full | C18: =SUM(C13:C17) -> 23
B20: Queen Package:
B21: Queen Top (Flat) Sheet | C21: =INDEX($D21:$G21,MATCH($C$2,$D$3:$G$3,0)) -> 9 | D21: 8 | E21: 9 | F21: 10 | G21: 9
B22: Queen Bottom (fitted 2.0) Sheet | C22: =INDEX($D22:$G22,MATCH($C$2,$D$3:$G$3,0)) -> 0
B23: Queen Decorative Sheet | C23: =INDEX($D23:$G23,MATCH($C$2,$D$3:$G$3,0)) -> 7 | D23: 8 | E23: 7 | F23: 6 | G23: 7
B24: Queen Fitted Sheet | C24: =INDEX($D24:$G24,MATCH($C$2,$D$3:$G$3,0)) -> 7 | D24: 8 | E24: 7 | F24: 5 | G24: 2
B25: Queen Pillow Case | C25: =INDEX($D25:$G25,MATCH($C$2,$D$3:$G$3,0)) -> 3 | D25: 6 | E25: 3 | F25: 3 | G25: 8
B26: Total Queen | C26: =SUM(C21:C25) -> 26
B28: King Package:
B29: King Top Sheet | C29: =INDEX($D29:$G29,MATCH($C$2,$D$3:$G$3,0)) -> 10 | D29: 3 | E29: 10 | F29: 7 | G29: 4
B30: King Bottom Sheet | C30: =INDEX($D30:$G30,MATCH($C$2,$D$3:$G$3,0)) -> 0
B31: King Decor Sheet | C31: =INDEX($D31:$G31,MATCH($C$2,$D$3:$G$3,0)) -> 7 | D31: 6 | E31: 7 | F31: 2 | G31: 6
B32: King Fitted Sheet | C32: =INDEX($D32:$G32,MATCH($C$2,$D$3:$G$3,0)) -> 9 | D32: 3 | E32: 9 | F32: 2 | G32: 8
B33: King Pillow Case | C33: =INDEX($D33:$G33,MATCH($C$2,$D$3:$G$3,0)) -> 8 | D33: 7 | E33: 8 | F33: 7 | G33: 9
B34: Total King | C34: =SUM(C29:C33) -> 34
A36: *Plug in costs | B36: Universal Package:
B37: Universal Top Sheet | C37: =INDEX($D37:$G37,MATCH($C$2,$D$3:$G$3,0)) -> 8.71 | D37: 8.43 | E37: 8.71 | F37: 9.54 | G37: 10.84
B38: Universal Bottom Sheet | C38: =INDEX($D38:$G38,MATCH($C$2,$D$3:$G$3,0)) -> 0
B39: Universal Decor Sheet | C39: =INDEX($D39:$G39,MATCH($C$2,$D$3:$G$3,0)) -> 0
B40: Universal Fitted Sheet | C40: =INDEX($D40:$G40,MATCH($C$2,$D$3:$G$3,0)) -> 0
B41: Universal Pillow Case | C41: =INDEX($D41:$G41,MATCH($C$2,$D$3:$G$3,0)) -> 0
B42: Total Universal | C42: =SUM(C37:C41) -> 8.71
